Workbook

Sheet Applications
A1: Date Applied | B1: Company | C1: Role Title | D1: Level | E1: Country | F1: City / Remote | G1: Fit Score (%) | H1: Channel | I1: Referral / Contact Name | J1: Sponsorship Question? | K1: Status | L1: Response Date | M1: Days to Response | N1: Next Action | O1: Next Action Date | P1: Notes | Q1: Interview/Screen Date(s) | R1: Gap Category | S1: Key Requirements | T1: Functional Fit (0-100) | U1: Seniority Fit (0-100) | V1: Domain Fit (0-100) | W1: Evidence Strength (0-100) | X1: Location/Auth Fit (0-100) | Y1: Competitive Positioning (0-100) | Z1: Relationship Access (0-100) | AA1: Strategic Fit Score | AB1: Pursuit Tier | AC1: Human Access Status | AD1: Outreach Count | AE1: Days Since Apply | AF1: Application Quality Flag
B2: eBay | C2: Lead Product Program Manager | D2: Lead | E2: Canada | F2: Toronto | G2: 55 | H2: Cold Portal | J2: No | K2: Rejected | L2: 46226 | M2: =IF(OR(L265="",A265=""),"",L265-A265) | P2: Rejected via Workday notification 07/23: "significant interest" in the role, decided not to move forward. Distinct from eBay Technical Program Manager, Search (Interviewing) and other eBay entries already logged. Original apply date not confirmed. ROLE (confirmed via posting, req R0073551, Toronto): "Lead Product Program Manager" — blends product management ownership with program delivery, more product-strategy-weighted than Elena's TPM/portfolio background. STRENGTHS: cross-functional delivery, executive communication. GAPS: product strategy/roadmap ownership (vs. program execution) is a lighter part of the resume; e-commerce/marketplace product domain not previously evidenced. | T2: =IF(G2="","",G2) | U2: =IF(C2="","",IF(OR(ISNUMBER(SEARCH("Director",C2)),ISNUMBER(SEARCH("Lead",C2)),ISNUMBER(SEARCH("Senior",C2)),ISNUMBER(SEARCH("Sr.",C2))),90,IF(OR(ISNUMBER(SEARCH("Manager",C2)),ISNUMBER(SEARCH("Program",C2)),ISNUMBER(SEARCH("Portfolio",C2))),80,60))) | V2: =IF(C2="","",IF(OR(ISNUMBER(SEARCH("AI",C2)),ISNUMBER(SEARCH("Data",C2)),ISNUMBER(SEARCH("Technology",C2)),ISNUMBER(SEARCH("Technical",C2)),ISNUMBER(SEARCH("Engineering",C2)),ISNUMBER(SEARCH("Platform",C2)),ISNUMBER(SEARCH("Portfolio",C2))),85,65)) | W2: =IF(C2="","",MIN(100,50+IF(S2<>"",25,0)+IF(R2<>"",15,0)+IF(P2<>"",10,0))) | X2: =IF(E2="","",IF(OR(E2="Canada",E2="CA"),100,IF(OR(E2="United States",E2="USA",E2="US"),IF(J2="Yes",45,75),65))) | Y2: =IF(C2="","",IF(OR(ISNUMBER(SEARCH("Program",C2)),ISNUMBER(SEARCH("Portfolio",C2)),ISNUMBER(SEARCH("Operations",C2)),ISNUMBER(SEARCH("Transformation",C2))),85,IF(ISNUMBER(SEARCH("Product Manager",C2)),55,70))) | Z2: =IF(C2="","",MIN(100,IF(I2<>"",60,10)+IF(AA2>0,MIN(40,AA2*20),0))) | AA2: =IF(T2="","",ROUND(T2*25%+U2*15%+V2*10%+W2*15%+X2*15%+Y2*10%+Z2*10%,0)) | AB2: =IF(AA2="","",IF(X2<50,"Selective / Barrier",IF(AA2>=80,"Tier 1 - Pursue",IF(AA2>=70,"Tier 2 - Pursue",IF(AA2>=60,"Tier 3 - Selective","Do Not Pursue"))))) | AC2: =IF(C2="","",IF(I2<>"","Named Contact",IF(AA2>0,"Outreach Logged","Cold"))) | AD2: =IF(B2="","",COUNTIF('Outreach Log'!$C:$C,B2)) | AE2: =IF(A2="","",IF(OR(K2="Rejected",K2="Closed"),IF(L2<>"",L2-A2,TODAY()-A2),TODAY()-A2)) | AF2: =IF(C2="","",IF(AND(AA2>=70,AC2="Cold"),"High-fit but cold",IF(AND(AA2<60,K2="Applied"),"Low-fit application",IF(AND(AA2>=70,OR(AC2="Named Contact",AC2="Outreach Logged")),"Targeted pursuit","Review"))))
B3: eBay | C3: Sr. Product Manager, Search AI | D3: Senior | E3: Canada | F3: Toronto | G3: 40 | H3: Cold Portal | J3: No | K3: Rejected | L3: 46245 | M3: =IF(OR(L266="",A266=""),"",L266-A266) | P3: Rejected via eBay Workday 08/11 3:40am ET - standard significant interest notice. Not previously logged; original apply date unknown. DISTINCT from Technical Program Manager, Search (R0074668) which remains at Interviewing. ROLE (confirmed via posting): this is a PRODUCT MANAGER role, not TPM — owns product strategy/roadmap for search AI/ML features, runs A/B tests, defines product vision with UX/design. GAPS: this is product ownership, not program delivery — a meaningfully different discipline from Elena's TPM/portfolio background; no direct product-management title or P&L/roadmap-ownership evidence in resume. Likely applied for AI-domain overlap, but role function mismatch explains the fast rejection. | T3: =IF(G3="","",G3) | U3: =IF(C3="","",IF(OR(ISNUMBER(SEARCH("Director",C3)),ISNUMBER(SEARCH("Lead",C3)),ISNUMBER(SEARCH("Senior",C3)),ISNUMBER(SEARCH("Sr.",C3))),90,IF(OR(ISNUMBER(SEARCH("Manager",C3)),ISNUMBER(SEARCH("Program",C3)),ISNUMBER(SEARCH("Portfolio",C3))),80,60))) | V3: =IF(C3="","",IF(OR(ISNUMBER(SEARCH("AI",C3)),ISNUMBER(SEARCH("Data",C3)),ISNUMBER(SEARCH("Technology",C3)),ISNUMBER(SEARCH("Technical",C3)),ISNUMBER(SEARCH("Engineering",C3)),ISNUMBER(SEARCH("Platform",C3)),ISNUMBER(SEARCH("Portfolio",C3))),85,65)) | W3: =IF(C3="","",MIN(100,50+IF(S3<>"",25,0)+IF(R3<>"",15,0)+IF(P3<>"",10,0))) | X3: =IF(E3="","",IF(OR(E3="Canada",E3="CA"),100,IF(OR(E3="United States",E3="USA",E3="US"),IF(J3="Yes",45,75),65))) | Y3: =IF(C3="","",IF(OR(ISNUMBER(SEARCH("Program",C3)),ISNUMBER(SEARCH("Portfolio",C3)),ISNUMBER(SEARCH("Operations",C3)),ISNUMBER(SEARCH("Transformation",C3))),85,IF(ISNUMBER(SEARCH("Product Manager",C3)),55,70))) | Z3: =IF(C3="","",MIN(100,IF(I3<>"",60,10)+IF(AA3>0,MIN(40,AA3*20),0))) | AA3: =IF(T3="","",ROUND(T3*25%+U3*15%+V3*10%+W3*15%+X3*15%+Y3*10%+Z3*10%,0)) | AB3: =IF(AA3="","",IF(X3<50,"Selective / Barrier",IF(AA3>=80,"Tier 1 - Pursue",IF(AA3>=70,"Tier 2 - Pursue",IF(AA3>=60,"Tier 3 - Selective","Do Not Pursue"))))) | AC3: =IF(C3="","",IF(I3<>"","Named Contact",IF(AA3>0,"Outreach Logged","Cold"))) | AD3: =IF(B3="","",COUNTIF('Outreach Log'!$C:$C,B3)) | AE3: =IF(A3="","",IF(OR(K3="Rejected",K3="Closed"),IF(L3<>"",L3-A3,TODAY()-A3),TODAY()-A3)) | AF3: =IF(C3="","",IF(AND(AA3>=70,AC3="Cold"),"High-fit but cold",IF(AND(AA3<60,K3="Applied"),"Low-fit application",IF(AND(AA3>=70,OR(AC3="Named Contact",AC3="Outreach Logged")),"Targeted pursuit","Review"))))
B4: eBay | C4: Program Manager: AI in Search | D4: Manager | E4: Canada | F4: Toronto | H4: Cold Portal | J4: No | K4: Rejected | L4: 46044 | M4: =IF(OR(L267="",A267=""),"",L267-A267) | P4: REJECTED 2026-01-22: eBay (ebay@myworkday.com) — "decided not to move forward." Date Applied unknown — Elena to confirm. Retroactively logged via full eBay inbox review 2026-09-12. | T4: =IF(G4="","",G4) | U4: =IF(C4="","",IF(OR(ISNUMBER(SEARCH("Director",C4)),ISNUMBER(SEARCH("Lead",C4)),ISNUMBER(SEARCH("Senior",C4)),ISNUMBER(SEARCH("Sr.",C4))),90,IF(OR(ISNUMBER(SEARCH("Manager",C4)),ISNUMBER(SEARCH("Program",C4)),ISNUMBER(SEARCH("Portfolio",C4))),80,60))) | V4: =IF(C4="","",IF(OR(ISNUMBER(SEARCH("AI",C4)),ISNUMBER(SEARCH("Data",C4)),ISNUMBER(SEARCH("Technology",C4)),ISNUMBER(SEARCH("Technical",C4)),ISNUMBER(SEARCH("Engineering",C4)),ISNUMBER(SEARCH("Platform",C4)),ISNUMBER(SEARCH("Portfolio",C4))),85,65)) | W4: =IF(C4="","",MIN(100,50+IF(S4<>"",25,0)+IF(R4<>"",15,0)+IF(P4<>"",10,0))) | X4: =IF(E4="","",IF(OR(E4="Canada",E4="CA"),100,IF(OR(E4="United States",E4="USA",E4="US"),IF(J4="Yes",45,75),65))) | Y4: =IF(C4="","",IF(OR(ISNUMBER(SEARCH("Program",C4)),ISNUMBER(SEARCH("Portfolio",C4)),ISNUMBER(SEARCH("Operations",C4)),ISNUMBER(SEARCH("Transformation",C4))),85,IF(ISNUMBER(SEARCH("Product Manager",C4)),55,70))) | Z4: =IF(C4="","",MIN(100,IF(I4<>"",60,10)+IF(AA4>0,MIN(40,AA4*20),0))) | AA4: =IF(T4="","",ROUND(T4*25%+U4*15%+V4*10%+W4*15%+X4*15%+Y4*10%+Z4*10%,0)) | AB4: =IF(AA4="","",IF(X4<50,"Selective / Barrier",IF(AA4>=80,"Tier 1 - Pursue",IF(AA4>=70,"Tier 2 - Pursue",IF(AA4>=60,"Tier 3 - Selective","Do Not Pursue"))))) | AC4: =IF(C4="","",IF(I4<>"","Named Contact",IF(AA4>0,"Outreach Logged","Cold"))) | AD4: =IF(B4="","",COUNTIF('Outreach Log'!$C:$C,B4)) | AE4: =IF(A4="","",IF(OR(K4="Rejected",K4="Closed"),IF(L4<>"",L4-A4,TODAY()-A4),TODAY()-A4)) | AF4: =IF(C4="","",IF(AND(AA4>=70,AC4="Cold"),"High-fit but cold",IF(AND(AA4<60,K4="Applied"),"Low-fit application",IF(AND(AA4>=70,OR(AC4="Named Contact",AC4="Outreach Logged")),"Targeted pursuit","Review"))))
B5: eBay | C5: Sr. Technical Program Manager | D5: Senior | E5: Canada | F5: Toronto | H5: Cold Portal | J5: No | K5: Rejected | L5: 46058 | M5: =IF(OR(L268="",A268=""),"",L268-A268) | P5: REJECTED 2026-02-05: eBay — "recruiting priorities have changed, no longer hiring for this role." Date Applied unknown — Elena to confirm. Distinct from row 141 (Sr. Technical Program Manager - R0074952, applied 8/14, still Applied) — different req. Retroactively logged 2026-09-12. | T5: =IF(G5="","",G5) | U5: =IF(C5="","",IF(OR(ISNUMBER(SEARCH("Director",C5)),ISNUMBER(SEARCH("Lead",C5)),ISNUMBER(SEARCH("Senior",C5)),ISNUMBER(SEARCH("Sr.",C5))),90,IF(OR(ISNUMBER(SEARCH("Manager",C5)),ISNUMBER(SEARCH("Program",C5)),ISNUMBER(SEARCH("Portfolio",C5))),80,60))) | V5: =IF(C5="","",IF(OR(ISNUMBER(SEARCH("AI",C5)),ISNUMBER(SEARCH("Data",C5)),ISNUMBER(SEARCH("Technology",C5)),ISNUMBER(SEARCH("Technical",C5)),ISNUMBER(SEARCH("Engineering",C5)),ISNUMBER(SEARCH("Platform",C5)),ISNUMBER(SEARCH("Portfolio",C5))),85,65)) | W5: =IF(C5="","",MIN(100,50+IF(S5<>"",25,0)+IF(R5<>"",15,0)+IF(P5<>"",10,0))) | X5: =IF(E5="","",IF(OR(E5="Canada",E5="CA"),100,IF(OR(E5="United States",E5="USA",E5="US"),IF(J5="Yes",45,75),65))) | Y5: =IF(C5="","",IF(OR(ISNUMBER(SEARCH("Program",C5)),ISNUMBER(SEARCH("Portfolio",C5)),ISNUMBER(SEARCH("Operations",C5)),ISNUMBER(SEARCH("Transformation",C5))),85,IF(ISNUMBER(SEARCH("Product Manager",C5)),55,70))) | Z5: =IF(C5="","",MIN(100,IF(I5<>"",60,10)+IF(AA5>0,MIN(40,AA5*20),0))) | AA5: =IF(T5="","",ROUND(T5*25%+U5*15%+V5*10%+W5*15%+X5*15%+Y5*10%+Z5*10%,0)) | AB5: =IF(AA5="","",IF(X5<50,"Selective / Barrier",IF(AA5>=80,"Tier 1 - Pursue",IF(AA5>=70,"Tier 2 - Pursue",IF(AA5>=60,"Tier 3 - Selective","Do Not Pursue"))))) | AC5: =IF(C5="","",IF(I5<>"","Named Contact",IF(AA5>0,"Outreach Logged","Cold"))) | AD5: =IF(B5="","",COUNTIF('Outreach Log'!$C:$C,B5)) | AE5: =IF(A5="","",IF(OR(K5="Rejected",K5="Closed"),IF(L5<>"",L5-A5,TODAY()-A5),TODAY()-A5)) | AF5: =IF(C5="","",IF(AND(AA5>=70,AC5="Cold"),"High-fit but cold",IF(AND(AA5<60,K5="Applied"),"Low-fit application",IF(AND(AA5>=70,OR(AC5="Named Contact",AC5="Outreach Logged")),"Targeted pursuit","Review"))))
B6: eBay | C6: Senior Design Program Manager | D6: Senior | E6: Canada | F6: Toronto | H6: Cold Portal | J6: No | K6: Rejected | L6: 46066 | M6: =IF(OR(L269="",A269=""),"",L269-A269) | P6: REJECTED 2026-02-13: eBay — "decided not to move forward." Date Applied unknown — Elena to confirm. Retroactively logged 2026-09-12. | T6: =IF(G6="","",G6) | U6: =IF(C6="","",IF(OR(ISNUMBER(SEARCH("Director",C6)),ISNUMBER(SEARCH("Lead",C6)),ISNUMBER(SEARCH("Senior",C6)),ISNUMBER(SEARCH("Sr.",C6))),90,IF(OR(ISNUMBER(SEARCH("Manager",C6)),ISNUMBER(SEARCH("Program",C6)),ISNUMBER(SEARCH("Portfolio",C6))),80,60))) | V6: =IF(C6="","",IF(OR(ISNUMBER(SEARCH("AI",C6)),ISNUMBER(SEARCH("Data",C6)),ISNUMBER(SEARCH("Technology",C6)),ISNUMBER(SEARCH("Technical",C6)),ISNUMBER(SEARCH("Engineering",C6)),ISNUMBER(SEARCH("Platform",C6)),ISNUMBER(SEARCH("Portfolio",C6))),85,65)) | W6: =IF(C6="","",MIN(100,50+IF(S6<>"",25,0)+IF(R6<>"",15,0)+IF(P6<>"",10,0))) | X6: =IF(E6="","",IF(OR(E6="Canada",E6="CA"),100,IF(OR(E6="United States",E6="USA",E6="US"),IF(J6="Yes",45,75),65))) | Y6: =IF(C6="","",IF(OR(ISNUMBER(SEARCH("Program",C6)),ISNUMBER(SEARCH("Portfolio",C6)),ISNUMBER(SEARCH("Operations",C6)),ISNUMBER(SEARCH("Transformation",C6))),85,IF(ISNUMBER(SEARCH("Product Manager",C6)),55,70))) | Z6: =IF(C6="","",MIN(100,IF(I6<>"",60,10)+IF(AA6>0,MIN(40,AA6*20),0))) | AA6: =IF(T6="","",ROUND(T6*25%+U6*15%+V6*10%+W6*15%+X6*15%+Y6*10%+Z6*10%,0)) | AB6: =IF(AA6="","",IF(X6<50,"Selective / Barrier",IF(AA6>=80,"Tier 1 - Pursue",IF(AA6>=70,"Tier 2 - Pursue",IF(AA6>=60,"Tier 3 - Selective","Do Not Pursue"))))) | AC6: =IF(C6="","",IF(I6<>"","Named Contact",IF(AA6>0,"Outreach Logged","Cold"))) | AD6: =IF(B6="","",COUNTIF('Outreach Log'!$C:$C,B6)) | AE6: =IF(A6="","",IF(OR(K6="Rejected",K6="Closed"),IF(L6<>"",L6-A6,TODAY()-A6),TODAY()-A6)) | AF6: =IF(C6="","",IF(AND(AA6>=70,AC6="Cold"),"High-fit but cold",IF(AND(AA6<60,K6="Applied"),"Low-fit application",IF(AND(AA6>=70,OR(AC6="Named Contact",AC6="Outreach Logged")),"Targeted pursuit","Review"))))
B7: eBay | C7: Senior Staff Design Program Manager | D7: Senior | E7: Canada | F7: Toronto | H7: Cold Portal | J7: No | K7: Rejected | L7: 46067 | M7: =IF(OR(L270="",A270=""),"",L270-A270) | P7: REJECTED 2026-02-14: eBay — "decided not to move forward." Date Applied unknown — Elena to confirm. Retroactively logged 2026-09-12. | T7: =IF(G7="","",G7) | U7: =IF(C7="","",IF(OR(ISNUMBER(SEARCH("Director",C7)),ISNUMBER(SEARCH("Lead",C7)),ISNUMBER(SEARCH("Senior",C7)),ISNUMBER(SEARCH("Sr.",C7))),90,IF(OR(ISNUMBER(SEARCH("Manager",C7)),ISNUMBER(SEARCH("Program",C7)),ISNUMBER(SEARCH("Portfolio",C7))),80,60))) | V7: =IF(C7="","",IF(OR(ISNUMBER(SEARCH("AI",C7)),ISNUMBER(SEARCH("Data",C7)),ISNUMBER(SEARCH("Technology",C7)),ISNUMBER(SEARCH("Technical",C7)),ISNUMBER(SEARCH("Engineering",C7)),ISNUMBER(SEARCH("Platform",C7)),ISNUMBER(SEARCH("Portfolio",C7))),85,65)) | W7: =IF(C7="","",MIN(100,50+IF(S7<>"",25,0)+IF(R7<>"",15,0)+IF(P7<>"",10,0))) | X7: =IF(E7="","",IF(OR(E7="Canada",E7="CA"),100,IF(OR(E7="United States",E7="USA",E7="US"),IF(J7="Yes",45,75),65))) | Y7: =IF(C7="","",IF(OR(ISNUMBER(SEARCH("Program",C7)),ISNUMBER(SEARCH("Portfolio",C7)),ISNUMBER(SEARCH("Operations",C7)),ISNUMBER(SEARCH("Transformation",C7))),85,IF(ISNUMBER(SEARCH("Product Manager",C7)),55,70))) | Z7: =IF(C7="","",MIN(100,IF(I7<>"",60,10)+IF(AA7>0,MIN(40,AA7*20),0))) | AA7: =IF(T7="","",ROUND(T7*25%+U7*15%+V7*10%+W7*15%+X7*15%+Y7*10%+Z7*10%,0)) | AB7: =IF(AA7="","",IF(X7<50,"Selective / Barrier",IF(AA7>=80,"Tier 1 - Pursue",IF(AA7>=70,"Tier 2 - Pursue",IF(AA7>=60,"Tier 3 - Selective","Do Not Pursue"))))) | AC7: =IF(C7="","",IF(I7<>"","Named Contact",IF(AA7>0,"Outreach Logged","Cold"))) | AD7: =IF(B7="","",COUNTIF('Outreach Log'!$C:$C,B7)) | AE7: =IF(A7="","",IF(OR(K7="Rejected",K7="Closed"),IF(L7<>"",L7-A7,TODAY()-A7),TODAY()-A7)) | AF7: =IF(C7="","",IF(AND(AA7>=70,AC7="Cold"),"High-fit but cold",IF(AND(AA7<60,K7="Applied"),"Low-fit application",IF(AND(AA7>=70,OR(AC7="Named Contact",AC7="Outreach Logged")),"Targeted pursuit","Review"))))
B8: eBay | C8: Sr.Tech Program Manager - Global Trust | D8: Senior | E8: Canada | F8: Toronto | H8: Cold Portal | J8: No | K8: Rejected | L8: 46074 | M8: =IF(OR(L271="",A271=""),"",L271-A271) | P8: REJECTED 2026-02-21: eBay — "decided not to move forward." Date Applied unknown — Elena to confirm. Retroactively logged 2026-09-12. | T8: =IF(G8="","",G8) | U8: =IF(C8="","",IF(OR(ISNUMBER(SEARCH("Director",C8)),ISNUMBER(SEARCH("Lead",C8)),ISNUMBER(SEARCH("Senior",C8)),ISNUMBER(SEARCH("Sr.",C8))),90,IF(OR(ISNUMBER(SEARCH("Manager",C8)),ISNUMBER(SEARCH("Program",C8)),ISNUMBER(SEARCH("Portfolio",C8))),80,60))) | V8: =IF(C8="","",IF(OR(ISNUMBER(SEARCH("AI",C8)),ISNUMBER(SEARCH("Data",C8)),ISNUMBER(SEARCH("Technology",C8)),ISNUMBER(SEARCH("Technical",C8)),ISNUMBER(SEARCH("Engineering",C8)),ISNUMBER(SEARCH("Platform",C8)),ISNUMBER(SEARCH("Portfolio",C8))),85,65)) | W8: =IF(C8="","",MIN(100,50+IF(S8<>"",25,0)+IF(R8<>"",15,0)+IF(P8<>"",10,0))) | X8: =IF(E8="","",IF(OR(E8="Canada",E8="CA"),100,IF(OR(E8="United States",E8="USA",E8="US"),IF(J8="Yes",45,75),65))) | Y8: =IF(C8="","",IF(OR(ISNUMBER(SEARCH("Program",C8)),ISNUMBER(SEARCH("Portfolio",C8)),ISNUMBER(SEARCH("Operations",C8)),ISNUMBER(SEARCH("Transformation",C8))),85,IF(ISNUMBER(SEARCH("Product Manager",C8)),55,70))) | Z8: =IF(C8="","",MIN(100,IF(I8<>"",60,10)+IF(AA8>0,MIN(40,AA8*20),0))) | AA8: =IF(T8="","",ROUND(T8*25%+U8*15%+V8*10%+W8*15%+X8*15%+Y8*10%+Z8*10%,0)) | AB8: =IF(AA8="","",IF(X8<50,"Selective / Barrier",IF(AA8>=80,"Tier 1 - Pursue",IF(AA8>=70,"Tier 2 - Pursue",IF(AA8>=60,"Tier 3 - Selective","Do Not Pursue"))))) | AC8: =IF(C8="","",IF(I8<>"","Named Contact",IF(AA8>0,"Outreach Logged","Cold"))) | AD8: =IF(B8="","",COUNTIF('Outreach Log'!$C:$C,B8)) | AE8: =IF(A8="","",IF(OR(K8="Rejected",K8="Closed"),IF(L8<>"",L8-A8,TODAY()-A8),TODAY()-A8)) | AF8: =IF(C8="","",IF(AND(AA8>=70,AC8="Cold"),"High-fit but cold",IF(AND(AA8<60,K8="Applied"),"Low-fit application",IF(AND(AA8>=70,OR(AC8="Named Contact",AC8="Outreach Logged")),"Targeted pursuit","Review"))))
B9: eBay | C9: Lead Technical Program Manager | D9: Lead | E9: Canada | F9: Toronto | H9: Cold Portal | J9: No | K9: Rejected | L9: 46087 | M9: =IF(OR(L272="",A272=""),"",L272-A272) | P9: REJECTED 2026-03-06: eBay — "recruiting priorities have changed, no longer hiring for this role." Date Applied unknown — Elena to confirm. First of two separate applications with this exact title (see also 4/25 rejection). Retroactively logged 2026-09-12. | T9: =IF(G9="","",G9) | U9: =IF(C9="","",IF(OR(ISNUMBER(SEARCH("Director",C9)),ISNUMBER(SEARCH("Lead",C9)),ISNUMBER(SEARCH("Senior",C9)),ISNUMBER(SEARCH("Sr.",C9))),90,IF(OR(ISNUMBER(SEARCH("Manager",C9)),ISNUMBER(SEARCH("Program",C9)),ISNUMBER(SEARCH("Portfolio",C9))),80,60))) | V9: =IF(C9="","",IF(OR(ISNUMBER(SEARCH("AI",C9)),ISNUMBER(SEARCH("Data",C9)),ISNUMBER(SEARCH("Technology",C9)),ISNUMBER(SEARCH("Technical",C9)),ISNUMBER(SEARCH("Engineering",C9)),ISNUMBER(SEARCH("Platform",C9)),ISNUMBER(SEARCH("Portfolio",C9))),85,65)) | W9: =IF(C9="","",MIN(100,50+IF(S9<>"",25,0)+IF(R9<>"",15,0)+IF(P9<>"",10,0))) | X9: =IF(E9="","",IF(OR(E9="Canada",E9="CA"),100,IF(OR(E9="United States",E9="USA",E9="US"),IF(J9="Yes",45,75),65))) | Y9: =IF(C9="","",IF(OR(ISNUMBER(SEARCH("Program",C9)),ISNUMBER(SEARCH("Portfolio",C9)),ISNUMBER(SEARCH("Operations",C9)),ISNUMBER(SEARCH("Transformation",C9))),85,IF(ISNUMBER(SEARCH("Product Manager",C9)),55,70))) | Z9: =IF(C9="","",MIN(100,IF(I9<>"",60,10)+IF(AA9>0,MIN(40,AA9*20),0))) | AA9: =IF(T9="","",ROUND(T9*25%+U9*15%+V9*10%+W9*15%+X9*15%+Y9*10%+Z9*10%,0)) | AB9: =IF(AA9="","",IF(X9<50,"Selective / Barrier",IF(AA9>=80,"Tier 1 - Pursue",IF(AA9>=70,"Tier 2 - Pursue",IF(AA9>=60,"Tier 3 - Selective","Do Not Pursue"))))) | AC9: =IF(C9="","",IF(I9<>"","Named Contact",IF(AA9>0,"Outreach Logged","Cold"))) | AD9: =IF(B9="","",COUNTIF('Outreach Log'!$C:$C,B9)) | AE9: =IF(A9="","",IF(OR(K9="Rejected",K9="Closed"),IF(L9<>"",L9-A9,TODAY()-A9),TODAY()-A9)) | AF9: =IF(C9="","",IF(AND(AA9>=70,AC9="Cold"),"High-fit but cold",IF(AND(AA9<60,K9="Applied"),"Low-fit application",IF(AND(AA9>=70,OR(AC9="Named Contact",AC9="Outreach Logged")),"Targeted pursuit","Review"))))
B10: eBay | C10: Senior RAI Program Manager | D10: Senior | E10: Canada | F10: Toronto | H10: Cold Portal | J10: No | K10: Rejected | L10: 46088 | M10: =IF(OR(L273="",A273=""),"",L273-A273) | P10: REJECTED 2026-03-07: eBay — "decided not to move forward." Date Applied unknown — Elena to confirm. Retroactively logged 2026-09-12. | T10: =IF(G10="","",G10) | U10: =IF(C10="","",IF(OR(ISNUMBER(SEARCH("Director",C10)),ISNUMBER(SEARCH("Lead",C10)),ISNUMBER(SEARCH("Senior",C10)),ISNUMBER(SEARCH("Sr.",C10))),90,IF(OR(ISNUMBER(SEARCH("Manager",C10)),ISNUMBER(SEARCH("Program",C10)),ISNUMBER(SEARCH("Portfolio",C10))),80,60))) | V10: =IF(C10="","",IF(OR(ISNUMBER(SEARCH("AI",C10)),ISNUMBER(SEARCH("Data",C10)),ISNUMBER(SEARCH("Technology",C10)),ISNUMBER(SEARCH("Technical",C10)),ISNUMBER(SEARCH("Engineering",C10)),ISNUMBER(SEARCH("Platform",C10)),ISNUMBER(SEARCH("Portfolio",C10))),85,65)) | W10: =IF(C10="","",MIN(100,50+IF(S10<>"",25,0)+IF(R10<>"",15,0)+IF(P10<>"",10,0))) | X10: =IF(E10="","",IF(OR(E10="Canada",E10="CA"),100,IF(OR(E10="United States",E10="USA",E10="US"),IF(J10="Yes",45,75),65))) | Y10: =IF(C10="","",IF(OR(ISNUMBER(SEARCH("Program",C10)),ISNUMBER(SEARCH("Portfolio",C10)),ISNUMBER(SEARCH("Operations",C10)),ISNUMBER(SEARCH("Transformation",C10))),85,IF(ISNUMBER(SEARCH("Product Manager",C10)),55,70))) | Z10: =IF(C10="","",MIN(100,IF(I10<>"",60,10)+IF(AA10>0,MIN(40,AA10*20),0))) | AA10: =IF(T10="","",ROUND(T10*25%+U10*15%+V10*10%+W10*15%+X10*15%+Y10*10%+Z10*10%,0)) | AB10: =IF(AA10="","",IF(X10<50,"Selective / Barrier",IF(AA10>=80,"Tier 1 - Pursue",IF(AA10>=70,"Tier 2 - Pursue",IF(AA10>=60,"Tier 3 - Selective","Do Not Pursue"))))) | AC10: =IF(C10="","",IF(I10<>"","Named Contact",IF(AA10>0,"Outreach Logged","Cold"))) | AD10: =IF(B10="","",COUNTIF('Outreach Log'!$C:$C,B10)) | AE10: =IF(A10="","",IF(OR(K10="Rejected",K10="Closed"),IF(L10<>"",L10-A10,TODAY()-A10),TODAY()-A10)) | AF10: =IF(C10="","",IF(AND(AA10>=70,AC10="Cold"),"High-fit but cold",IF(AND(AA10<60,K10="Applied"),"Low-fit application",IF(AND(AA10>=70,OR(AC10="Named Contact",AC10="Outreach Logged")),"Targeted pursuit","Review"))))
B11: eBay | C11: Senior Program Manager, Regulatory | D11: Senior | E11: Canada | F11: Toronto | H11: Cold Portal | J11: No | K11: Rejected | L11: 46114 | M11: =IF(OR(L274="",A274=""),"",L274-A274) | P11: REJECTED 2026-04-02: eBay — "decided not to move forward." Date Applied unknown — Elena to confirm. Retroactively logged 2026-09-12. | T11: =IF(G11="","",G11) | U11: =IF(C11="","",IF(OR(ISNUMBER(SEARCH("Director",C11)),ISNUMBER(SEARCH("Lead",C11)),ISNUMBER(SEARCH("Senior",C11)),ISNUMBER(SEARCH("Sr.",C11))),90,IF(OR(ISNUMBER(SEARCH("Manager",C11)),ISNUMBER(SEARCH("Program",C11)),ISNUMBER(SEARCH("Portfolio",C11))),80,60))) | V11: =IF(C11="","",IF(OR(ISNUMBER(SEARCH("AI",C11)),ISNUMBER(SEARCH("Data",C11)),ISNUMBER(SEARCH("Technology",C11)),ISNUMBER(SEARCH("Technical",C11)),ISNUMBER(SEARCH("Engineering",C11)),ISNUMBER(SEARCH("Platform",C11)),ISNUMBER(SEARCH("Portfolio",C11))),85,65)) | W11: =IF(C11="","",MIN(100,50+IF(S11<>"",25,0)+IF(R11<>"",15,0)+IF(P11<>"",10,0))) | X11: =IF(E11="","",IF(OR(E11="Canada",E11="CA"),100,IF(OR(E11="United States",E11="USA",E11="US"),IF(J11="Yes",45,75),65))) | Y11: =IF(C11="","",IF(OR(ISNUMBER(SEARCH("Program",C11)),ISNUMBER(SEARCH("Portfolio",C11)),ISNUMBER(SEARCH("Operations",C11)),ISNUMBER(SEARCH("Transformation",C11))),85,IF(ISNUMBER(SEARCH("Product Manager",C11)),55,70))) | Z11: =IF(C11="","",MIN(100,IF(I11<>"",60,10)+IF(AA11>0,MIN(40,AA11*20),0))) | AA11: =IF(T11="","",ROUND(T11*25%+U11*15%+V11*10%+W11*15%+X11*15%+Y11*10%+Z11*10%,0)) | AB11: =IF(AA11="","",IF(X11<50,"Selective / Barrier",IF(AA11>=80,"Tier 1 - Pursue",IF(AA11>=70,"Tier 2 - Pursue",IF(AA11>=60,"Tier 3 - Selective","Do Not Pursue"))))) | AC11: =IF(C11="","",IF(I11<>"","Named Contact",IF(AA11>0,"Outreach Logged","Cold"))) | AD11: =IF(B11="","",COUNTIF('Outreach Log'!$C:$C,B11)) | AE11: =IF(A11="","",IF(OR(K11="Rejected",K11="Closed"),IF(L11<>"",L11-A11,TODAY()-A11),TODAY()-A11)) | AF11: =IF(C11="","",IF(AND(AA11>=70,AC11="Cold"),"High-fit but cold",IF(AND(AA11<60,K11="Applied"),"Low-fit application",IF(AND(AA11>=70,OR(AC11="Named Contact",AC11="Outreach Logged")),"Targeted pursuit","Review"))))
B12: eBay | C12: Business Operations and Planning Manager | D12: Manager | E12: Canada | F12: Toronto | H12: Cold Portal | J12: No | K12: Rejected | L12: 46133 | M12: =IF(OR(L275="",A275=""),"",L275-A275) | P12: REJECTED 2026-04-21: eBay — "decided not to move forward." Date Applied unknown — Elena to confirm. Retroactively logged 2026-09-12. | T12: =IF(G12="","",G12) | U12: =IF(C12="","",IF(OR(ISNUMBER(SEARCH("Director",C12)),ISNUMBER(SEARCH("Lead",C12)),ISNUMBER(SEARCH("Senior",C12)),ISNUMBER(SEARCH("Sr.",C12))),90,IF(OR(ISNUMBER(SEARCH("Manager",C12)),ISNUMBER(SEARCH("Program",C12)),ISNUMBER(SEARCH("Portfolio",C12))),80,60))) | V12: =IF(C12="","",IF(OR(ISNUMBER(SEARCH("AI",C12)),ISNUMBER(SEARCH("Data",C12)),ISNUMBER(SEARCH("Technology",C12)),ISNUMBER(SEARCH("Technical",C12)),ISNUMBER(SEARCH("Engineering",C12)),ISNUMBER(SEARCH("Platform",C12)),ISNUMBER(SEARCH("Portfolio",C12))),85,65)) | W12: =IF(C12="","",MIN(100,50+IF(S12<>"",25,0)+IF(R12<>"",15,0)+IF(P12<>"",10,0))) | X12: =IF(E12="","",IF(OR(E12="Canada",E12="CA"),100,IF(OR(E12="United States",E12="USA",E12="US"),IF(J12="Yes",45,75),65))) | Y12: =IF(C12="","",IF(OR(ISNUMBER(SEARCH("Program",C12)),ISNUMBER(SEARCH("Portfolio",C12)),ISNUMBER(SEARCH("Operations",C12)),ISNUMBER(SEARCH("Transformation",C12))),85,IF(ISNUMBER(SEARCH("Product Manager",C12)),55,70))) | Z12: =IF(C12="","",MIN(100,IF(I12<>"",60,10)+IF(AA12>0,MIN(40,AA12*20),0))) | AA12: =IF(T12="","",ROUND(T12*25%+U12*15%+V12*10%+W12*15%+X12*15%+Y12*10%+Z12*10%,0)) | AB12: =IF(AA12="","",IF(X12<50,"Selective / Barrier",IF(AA12>=80,"Tier 1 - Pursue",IF(AA12>=70,"Tier 2 - Pursue",IF(AA12>=60,"Tier 3 - Selective","Do Not Pursue"))))) | AC12: =IF(C12="","",IF(I12<>"","Named Contact",IF(AA12>0,"Outreach Logged","Cold"))) | AD12: =IF(B12="","",COUNTIF('Outreach Log'!$C:$C,B12)) | AE12: =IF(A12="","",IF(OR(K12="Rejected",K12="Closed"),IF(L12<>"",L12-A12,TODAY()-A12),TODAY()-A12)) | AF12: =IF(C12="","",IF(AND(AA12>=70,AC12="Cold"),"High-fit but cold",IF(AND(AA12<60,K12="Applied"),"Low-fit application",IF(AND(AA12>=70,OR(AC12="Named Contact",AC12="Outreach Logged")),"Targeted pursuit","Review"))))
B13: eBay | C13: Lead Technical Program Manager (2nd application) | D13: Lead | E13: Canada | F13: Toronto | H13: Cold Portal | J13: No | K13: Rejected | L13: 46137 | M13: =IF(OR(L276="",A276=""),"",L276-A276) | P13: REJECTED 2026-04-25: eBay — "decided not to move forward." Date Applied unknown — Elena to confirm. Second, separate application with this exact title (see also 3/6 rejection — different req). Retroactively logged 2026-09-12. | T13: =IF(G13="","",G13) | U13: =IF(C13="","",IF(OR(ISNUMBER(SEARCH("Director",C13)),ISNUMBER(SEARCH("Lead",C13)),ISNUMBER(SEARCH("Senior",C13)),ISNUMBER(SEARCH("Sr.",C13))),90,IF(OR(ISNUMBER(SEARCH("Manager",C13)),ISNUMBER(SEARCH("Program",C13)),ISNUMBER(SEARCH("Portfolio",C13))),80,60))) | V13: =IF(C13="","",IF(OR(ISNUMBER(SEARCH("AI",C13)),ISNUMBER(SEARCH("Data",C13)),ISNUMBER(SEARCH("Technology",C13)),ISNUMBER(SEARCH("Technical",C13)),ISNUMBER(SEARCH("Engineering",C13)),ISNUMBER(SEARCH("Platform",C13)),ISNUMBER(SEARCH("Portfolio",C13))),85,65)) | W13: =IF(C13="","",MIN(100,50+IF(S13<>"",25,0)+IF(R13<>"",15,0)+IF(P13<>"",10,0))) | X13: =IF(E13="","",IF(OR(E13="Canada",E13="CA"),100,IF(OR(E13="United States",E13="USA",E13="US"),IF(J13="Yes",45,75),65))) | Y13: =IF(C13="","",IF(OR(ISNUMBER(SEARCH("Program",C13)),ISNUMBER(SEARCH("Portfolio",C13)),ISNUMBER(SEARCH("Operations",C13)),ISNUMBER(SEARCH("Transformation",C13))),85,IF(ISNUMBER(SEARCH("Product Manager",C13)),55,70))) | Z13: =IF(C13="","",MIN(100,IF(I13<>"",60,10)+IF(AA13>0,MIN(40,AA13*20),0))) | AA13: =IF(T13="","",ROUND(T13*25%+U13*15%+V13*10%+W13*15%+X13*15%+Y13*10%+Z13*10%,0)) | AB13: =IF(AA13="","",IF(X13<50,"Selective / Barrier",IF(AA13>=80,"Tier 1 - Pursue",IF(AA13>=70,"Tier 2 - Pursue",IF(AA13>=60,"Tier 3 - Selective","Do Not Pursue"))))) | AC13: =IF(C13="","",IF(I13<>"","Named Contact",IF(AA13>0,"Outreach Logged","Cold"))) | AD13: =IF(B13="","",COUNTIF('Outreach Log'!$C:$C,B13)) | AE13: =IF(A13="","",IF(OR(K13="Rejected",K13="Closed"),IF(L13<>"",L13-A13,TODAY()-A13),TODAY()-A13)) | AF13: =IF(C13="","",IF(AND(AA13>=70,AC13="Cold"),"High-fit but cold",IF(AND(AA13<60,K13="Applied"),"Low-fit application",IF(AND(AA13>=70,OR(AC13="Named Contact",AC13="Outreach Logged")),"Targeted pursuit","Review"))))
B14: eBay | C14: Director of Strategic Programs | D14: Director | E14: Canada | F14: Toronto | H14: Cold Portal | J14: No | K14: Rejected | L14: 46141 | M14: =IF(OR(L277="",A277=""),"",L277-A277) | P14: REJECTED 2026-04-29: eBay — "decided not to move forward." Date Applied unknown — Elena to confirm. Retroactively logged 2026-09-12. | T14: =IF(G14="","",G14) | U14: =IF(C14="","",IF(OR(ISNUMBER(SEARCH("Director",C14)),ISNUMBER(SEARCH("Lead",C14)),ISNUMBER(SEARCH("Senior",C14)),ISNUMBER(SEARCH("Sr.",C14))),90,IF(OR(ISNUMBER(SEARCH("Manager",C14)),ISNUMBER(SEARCH("Program",C14)),ISNUMBER(SEARCH("Portfolio",C14))),80,60))) | V14: =IF(C14="","",IF(OR(ISNUMBER(SEARCH("AI",C14)),ISNUMBER(SEARCH("Data",C14)),ISNUMBER(SEARCH("Technology",C14)),ISNUMBER(SEARCH("Technical",C14)),ISNUMBER(SEARCH("Engineering",C14)),ISNUMBER(SEARCH("Platform",C14)),ISNUMBER(SEARCH("Portfolio",C14))),85,65)) | W14: =IF(C14="","",MIN(100,50+IF(S14<>"",25,0)+IF(R14<>"",15,0)+IF(P14<>"",10,0))) | X14: =IF(E14="","",IF(OR(E14="Canada",E14="CA"),100,IF(OR(E14="United States",E14="USA",E14="US"),IF(J14="Yes",45,75),65))) | Y14: =IF(C14="","",IF(OR(ISNUMBER(SEARCH("Program",C14)),ISNUMBER(SEARCH("Portfolio",C14)),ISNUMBER(SEARCH("Operations",C14)),ISNUMBER(SEARCH("Transformation",C14))),85,IF(ISNUMBER(SEARCH("Product Manager",C14)),55,70))) | Z14: =IF(C14="","",MIN(100,IF(I14<>"",60,10)+IF(AA14>0,MIN(40,AA14*20),0))) | AA14: =IF(T14="","",ROUND(T14*25%+U14*15%+V14*10%+W14*15%+X14*15%+Y14*10%+Z14*10%,0)) | AB14: =IF(AA14="","",IF(X14<50,"Selective / Barrier",IF(AA14>=80,"Tier 1 - Pursue",IF(AA14>=70,"Tier 2 - Pursue",IF(AA14>=60,"Tier 3 - Selective","Do Not Pursue"))))) | AC14: =IF(C14="","",IF(I14<>"","Named Contact",IF(AA14>0,"Outreach Logged","Cold"))) | AD14: =IF(B14="","",COUNTIF('Outreach Log'!$C:$C,B14)) | AE14: =IF(A14="","",IF(OR(K14="Rejected",K14="Closed"),IF(L14<>"",L14-A14,TODAY()-A14),TODAY()-A14)) | AF14: =IF(C14="","",IF(AND(AA14>=70,AC14="Cold"),"High-fit but cold",IF(AND(AA14<60,K14="Applied"),"Low-fit application",IF(AND(AA14>=70,OR(AC14="Named Contact",AC14="Outreach Logged")),"Targeted pursuit","Review"))))
B15: eBay | C15: Sr. Engineering Program Manager | D15: Senior | E15: Canada | F15: Toronto | H15: Cold Portal | J15: No | K15: Rejected | L15: 46221 | M15: =IF(OR(L278="",A278=""),"",L278-A278) | P15: Advanced to next recruiting stage 2026-06-17 ("thrilled to invite you to the next stage"). REJECTED 2026-07-18: eBay — "decided not to move forward." Date Applied unknown — Elena to confirm. Distinct from row 38 (Director, AI Workflow Transformation, applied 7/5). Retroactively logged 2026-09-12. | Q15: 46190 | T15: =IF(G15="","",G15) | U15: =IF(C15="","",IF(OR(ISNUMBER(SEARCH("Director",C15)),ISNUMBER(SEARCH("Lead",C15)),ISNUMBER(SEARCH("Senior",C15)),ISNUMBER(SEARCH("Sr.",C15))),90,IF(OR(ISNUMBER(SEARCH("Manager",C15)),ISNUMBER(SEARCH("Program",C15)),ISNUMBER(SEARCH("Portfolio",C15))),80,60))) | V15: =IF(C15="","",IF(OR(ISNUMBER(SEARCH("AI",C15)),ISNUMBER(SEARCH("Data",C15)),ISNUMBER(SEARCH("Technology",C15)),ISNUMBER(SEARCH("Technical",C15)),ISNUMBER(SEARCH("Engineering",C15)),ISNUMBER(SEARCH("Platform",C15)),ISNUMBER(SEARCH("Portfolio",C15))),85,65)) | W15: =IF(C15="","",MIN(100,50+IF(S15<>"",25,0)+IF(R15<>"",15,0)+IF(P15<>"",10,0))) | X15: =IF(E15="","",IF(OR(E15="Canada",E15="CA"),100,IF(OR(E15="United States",E15="USA",E15="US"),IF(J15="Yes",45,75),65))) | Y15: =IF(C15="","",IF(OR(ISNUMBER(SEARCH("Program",C15)),ISNUMBER(SEARCH("Portfolio",C15)),ISNUMBER(SEARCH("Operations",C15)),ISNUMBER(SEARCH("Transformation",C15))),85,IF(ISNUMBER(SEARCH("Product Manager",C15)),55,70))) | Z15: =IF(C15="","",MIN(100,IF(I15<>"",60,10)+IF(AA15>0,MIN(40,AA15*20),0))) | AA15: =IF(T15="","",ROUND(T15*25%+U15*15%+V15*10%+W15*15%+X15*15%+Y15*10%+Z15*10%,0)) | AB15: =IF(AA15="","",IF(X15<50,"Selective / Barrier",IF(AA15>=80,"Tier 1 - Pursue",IF(AA15>=70,"Tier 2 - Pursue",IF(AA15>=60,"Tier 3 - Selective","Do Not Pursue"))))) | AC15: =IF(C15="","",IF(I15<>"","Named Contact",IF(AA15>0,"Outreach Logged","Cold"))) | AD15: =IF(B15="","",COUNTIF('Outreach Log'!$C:$C,B15)) | AE15: =IF(A15="","",IF(OR(K15="Rejected",K15="Closed"),IF(L15<>"",L15-A15,TODAY()-A15),TODAY()-A15)) | AF15: =IF(C15="","",IF(AND(AA15>=70,AC15="Cold"),"High-fit but cold",IF(AND(AA15<60,K15="Applied"),"Low-fit application",IF(AND(AA15>=70,OR(AC15="Named Contact",AC15="Outreach Logged")),"Targeted pursuit","Review"))))
B16: eBay | C16: Product Manager, Seller Experience | D16: Manager | E16: Canada | F16: Toronto | H16: Cold Portal | J16: No | K16: Rejected | L16: 46225 | M16: =IF(OR(L279="",A279=""),"",L279-A279) | P16: REJECTED 2026-07-22: eBay — "decided not to move forward." Date Applied unknown — Elena to confirm. Retroactively logged 2026-09-12. | T16: =IF(G16="","",G16) | U16: =IF(C16="","",IF(OR(ISNUMBER(SEARCH("Director",C16)),ISNUMBER(SEARCH("Lead",C16)),ISNUMBER(SEARCH("Senior",C16)),ISNUMBER(SEARCH("Sr.",C16))),90,IF(OR(ISNUMBER(SEARCH("Manager",C16)),ISNUMBER(SEARCH("Program",C16)),ISNUMBER(SEARCH("Portfolio",C16))),80,60))) | V16: =IF(C16="","",IF(OR(ISNUMBER(SEARCH("AI",C16)),ISNUMBER(SEARCH("Data",C16)),ISNUMBER(SEARCH("Technology",C16)),ISNUMBER(SEARCH("Technical",C16)),ISNUMBER(SEARCH("Engineering",C16)),ISNUMBER(SEARCH("Platform",C16)),ISNUMBER(SEARCH("Portfolio",C16))),85,65)) | W16: =IF(C16="","",MIN(100,50+IF(S16<>"",25,0)+IF(R16<>"",15,0)+IF(P16<>"",10,0))) | X16: =IF(E16="","",IF(OR(E16="Canada",E16="CA"),100,IF(OR(E16="United States",E16="USA",E16="US"),IF(J16="Yes",45,75),65))) | Y16: =IF(C16="","",IF(OR(ISNUMBER(SEARCH("Program",C16)),ISNUMBER(SEARCH("Portfolio",C16)),ISNUMBER(SEARCH("Operations",C16)),ISNUMBER(SEARCH("Transformation",C16))),85,IF(ISNUMBER(SEARCH("Product Manager",C16)),55,70))) | Z16: =IF(C16="","",MIN(100,IF(I16<>"",60,10)+IF(AA16>0,MIN(40,AA16*20),0))) | AA16: =IF(T16="","",ROUND(T16*25%+U16*15%+V16*10%+W16*15%+X16*15%+Y16*10%+Z16*10%,0)) | AB16: =IF(AA16="","",IF(X16<50,"Selective / Barrier",IF(AA16>=80,"Tier 1 - Pursue",IF(AA16>=70,"Tier 2 - Pursue",IF(AA16>=60,"Tier 3 - Selective","Do Not Pursue"))))) | AC16: =IF(C16="","",IF(I16<>"","Named Contact",IF(AA16>0,"Outreach Logged","Cold"))) | AD16: =IF(B16="","",COUNTIF('Outreach Log'!$C:$C,B16)) | AE16: =IF(A16="","",IF(OR(K16="Rejected",K16="Closed"),IF(L16<>"",L16-A16,TODAY()-A16),TODAY()-A16)) | AF16: =IF(C16="","",IF(AND(AA16>=70,AC16="Cold"),"High-fit but cold",IF(AND(AA16<60,K16="Applied"),"Low-fit application",IF(AND(AA16>=70,OR(AC16="Named Contact",AC16="Outreach Logged")),"Targeted pursuit","Review"))))
B17: OMERS / Oxford Properties | C17: Project Delivery Lead (14-Month Contract) | D17: Manager | E17: Canada | F17: Toronto | H17: Cold Portal | J17: No | K17: Rejected | L17: 46027 | M17: =IF(OR(L280="",A280=""),"",L280-A280) | P17: REJECTED 2026-01-05: OMERS/Oxford Properties (recruiting@jobalerts.omers.com) — "we have decided to pursue other candidates whose qualifications and experience are more in line with the position requirements." Date Applied: January 2026 (exact day unknown, confirmed by Elena). Distinct from row 163 (Program Manager, Program Management & Delivery, D&T CSI, applied 8/21) — separate application. Retroactively logged via Gmail screenshot review 2026-09-13. | T17: =IF(G17="","",G17) | U17: =IF(C17="","",IF(OR(ISNUMBER(SEARCH("Director",C17)),ISNUMBER(SEARCH("Lead",C17)),ISNUMBER(SEARCH("Senior",C17)),ISNUMBER(SEARCH("Sr.",C17))),90,IF(OR(ISNUMBER(SEARCH("Manager",C17)),ISNUMBER(SEARCH("Program",C17)),ISNUMBER(SEARCH("Portfolio",C17))),80,60))) | V17: =IF(C17="","",IF(OR(ISNUMBER(SEARCH("AI",C17)),ISNUMBER(SEARCH("Data",C17)),ISNUMBER(SEARCH("Technology",C17)),ISNUMBER(SEARCH("Technical",C17)),ISNUMBER(SEARCH("Engineering",C17)),ISNUMBER(SEARCH("Platform",C17)),ISNUMBER(SEARCH("Portfolio",C17))),85,65)) | W17: =IF(C17="","",MIN(100,50+IF(S17<>"",25,0)+IF(R17<>"",15,0)+IF(P17<>"",10,0))) | X17: =IF(E17="","",IF(OR(E17="Canada",E17="CA"),100,IF(OR(E17="United States",E17="USA",E17="US"),IF(J17="Yes",45,75),65))) | Y17: =IF(C17="","",IF(OR(ISNUMBER(SEARCH("Program",C17)),ISNUMBER(SEARCH("Portfolio",C17)),ISNUMBER(SEARCH("Operations",C17)),ISNUMBER(SEARCH("Transformation",C17))),85,IF(ISNUMBER(SEARCH("Product Manager",C17)),55,70))) | Z17: =IF(C17="","",MIN(100,IF(I17<>"",60,10)+IF(AA17>0,MIN(40,AA17*20),0))) | AA17: =IF(T17="","",ROUND(T17*25%+U17*15%+V17*10%+W17*15%+X17*15%+Y17*10%+Z17*10%,0)) | AB17: =IF(AA17="","",IF(X17<50,"Selective / Barrier",IF(AA17>=80,"Tier 1 - Pursue",IF(AA17>=70,"Tier 2 - Pursue",IF(AA17>=60,"Tier 3 - Selective","Do Not Pursue"))))) | AC17: =IF(C17="","",IF(I17<>"","Named Contact",IF(AA17>0,"Outreach Logged","Cold"))) | AD17: =IF(B17="","",COUNTIF('Outreach Log'!$C:$C,B17)) | AE17: =IF(A17="","",IF(OR(K17="Rejected",K17="Closed"),IF(L17<>"",L17-A17,TODAY()-A17),TODAY()-A17)) | AF17: =IF(C17="","",IF(AND(AA17>=70,AC17="Cold"),"High-fit but cold",IF(AND(AA17<60,K17="Applied"),"Low-fit application",IF(AND(AA17>=70,OR(AC17="Named Contact",AC17="Outreach Logged")),"Targeted pursuit","Review"))))
B18: eBay | C18: Sr. Product Mgr, Live Personalization | D18: Senior | E18: Canada | F18: Toronto | G18: 45 | H18: Cold Portal | J18: No | K18: Rejected | L18: 46279 | M18: =IF(OR(L281="",A281=""),"",L281-A281) | P18: REJECTED 2026-09-14: eBay Talent Acquisition Team — "recruiting priorities have changed, no longer hiring for this role." Date Applied unknown — Elena to confirm. Distinct from all other eBay Product Manager roles already logged (e.g. Sr. Product Manager, Search AI). Est. fit score: 45 — Product Manager title (not Program Manager), lower overlap with her core delivery/portfolio management track; personalization/product-feature domain is further from her direct experience. | T18: =IF(G18="","",G18) | U18: =IF(C18="","",IF(OR(ISNUMBER(SEARCH("Director",C18)),ISNUMBER(SEARCH("Lead",C18)),ISNUMBER(SEARCH("Senior",C18)),ISNUMBER(SEARCH("Sr.",C18))),90,IF(OR(ISNUMBER(SEARCH("Manager",C18)),ISNUMBER(SEARCH("Program",C18)),ISNUMBER(SEARCH("Portfolio",C18))),80,60))) | V18: =IF(C18="","",IF(OR(ISNUMBER(SEARCH("AI",C18)),ISNUMBER(SEARCH("Data",C18)),ISNUMBER(SEARCH("Technology",C18)),ISNUMBER(SEARCH("Technical",C18)),ISNUMBER(SEARCH("Engineering",C18)),ISNUMBER(SEARCH("Platform",C18)),ISNUMBER(SEARCH("Portfolio",C18))),85,65)) | W18: =IF(C18="","",MIN(100,50+IF(S18<>"",25,0)+IF(R18<>"",15,0)+IF(P18<>"",10,0))) | X18: =IF(E18="","",IF(OR(E18="Canada",E18="CA"),100,IF(OR(E18="United States",E18="USA",E18="US"),IF(J18="Yes",45,75),65))) | Y18: =IF(C18="","",IF(OR(ISNUMBER(SEARCH("Program",C18)),ISNUMBER(SEARCH("Portfolio",C18)),ISNUMBER(SEARCH("Operations",C18)),ISNUMBER(SEARCH("Transformation",C18))),85,IF(ISNUMBER(SEARCH("Product Manager",C18)),55,70))) | Z18: =IF(C18="","",MIN(100,IF(I18<>"",60,10)+IF(AA18>0,MIN(40,AA18*20),0))) | AA18: =IF(T18="","",ROUND(T18*25%+U18*15%+V18*10%+W18*15%+X18*15%+Y18*10%+Z18*10%,0)) | AB18: =IF(AA18="","",IF(X18<50,"Selective / Barrier",IF(AA18>=80,"Tier 1 - Pursue",IF(AA18>=70,"Tier 2 - Pursue",IF(AA18>=60,"Tier 3 - Selective","Do Not Pursue"))))) | AC18: =IF(C18="","",IF(I18<>"","Named Contact",IF(AA18>0,"Outreach Logged","Cold"))) | AD18: =IF(B18="","",COUNTIF('Outreach Log'!$C:$C,B18)) | AE18: =IF(A18="","",IF(OR(K18="Rejected",K18="Closed"),IF(L18<>"",L18-A18,TODAY()-A18),TODAY()-A18)) | AF18: =IF(C18="","",IF(AND(AA18>=70,AC18="Cold"),"High-fit but cold",IF(AND(AA18<60,K18="Applied"),"Low-fit application",IF(AND(AA18>=70,OR(AC18="Named Contact",AC18="Outreach Logged")),"Targeted pursuit","Review"))))
B19: OMERS / Oxford Properties | C19: Associate Director, AI Process Engineering (12 Months Contract) | D19: Assoc Director | E19: Canada | F19: Toronto | G19: 72 | H19: Cold Portal | J19: No | K19: Rejected | L19: 46085 | M19: =IF(OR(L282="",A282=""),"",L282-A282) | P19: REJECTED 2026-03-04: OMERS/Oxford Properties (recruiting@jobalerts.omers.com) — "decided to pursue other candidates whose qualifications and experience are more in line with the position requirements." Date Applied unknown — Elena to confirm. Third, distinct OMERS/Oxford Properties application — separate from Project Delivery Lead (rejected Jan) and Program Manager, D&T CSI (still Applied, applied 8/21). Retroactively logged via Gmail review 2026-09-15. Est. fit score: 72 — AI Process Engineering aligns with her Bell Data & AI portfolio and process-governance track record. | T19: =IF(G19="","",G19) | U19: =IF(C19="","",IF(OR(ISNUMBER(SEARCH("Director",C19)),ISNUMBER(SEARCH("Lead",C19)),ISNUMBER(SEARCH("Senior",C19)),ISNUMBER(SEARCH("Sr.",C19))),90,IF(OR(ISNUMBER(SEARCH("Manager",C19)),ISNUMBER(SEARCH("Program",C19)),ISNUMBER(SEARCH("Portfolio",C19))),80,60))) | V19: =IF(C19="","",IF(OR(ISNUMBER(SEARCH("AI",C19)),ISNUMBER(SEARCH("Data",C19)),ISNUMBER(SEARCH("Technology",C19)),ISNUMBER(SEARCH("Technical",C19)),ISNUMBER(SEARCH("Engineering",C19)),ISNUMBER(SEARCH("Platform",C19)),ISNUMBER(SEARCH("Portfolio",C19))),85,65)) | W19: =IF(C19="","",MIN(100,50+IF(S19<>"",25,0)+IF(R19<>"",15,0)+IF(P19<>"",10,0))) | X19: =IF(E19="","",IF(OR(E19="Canada",E19="CA"),100,IF(OR(E19="United States",E19="USA",E19="US"),IF(J19="Yes",45,75),65))) | Y19: =IF(C19="","",IF(OR(ISNUMBER(SEARCH("Program",C19)),ISNUMBER(SEARCH("Portfolio",C19)),ISNUMBER(SEARCH("Operations",C19)),ISNUMBER(SEARCH("Transformation",C19))),85,IF(ISNUMBER(SEARCH("Product Manager",C19)),55,70))) | Z19: =IF(C19="","",MIN(100,IF(I19<>"",60,10)+IF(AA19>0,MIN(40,AA19*20),0))) | AA19: =IF(T19="","",ROUND(T19*25%+U19*15%+V19*10%+W19*15%+X19*15%+Y19*10%+Z19*10%,0)) | AB19: =IF(AA19="","",IF(X19<50,"Selective / Barrier",IF(AA19>=80,"Tier 1 - Pursue",IF(AA19>=70,"Tier 2 - Pursue",IF(AA19>=60,"Tier 3 - Selective","Do Not Pursue"))))) | AC19: =IF(C19="","",IF(I19<>"","Named Contact",IF(AA19>0,"Outreach Logged","Cold"))) | AD19: =IF(B19="","",COUNTIF('Outreach Log'!$C:$C,B19)) | AE19: =IF(A19="","",IF(OR(K19="Rejected",K19="Closed"),IF(L19<>"",L19-A19,TODAY()-A19),TODAY()-A19)) | AF19: =IF(C19="","",IF(AND(AA19>=70,AC19="Cold"),"High-fit but cold",IF(AND(AA19<60,K19="Applied"),"Low-fit application",IF(AND(AA19>=70,OR(AC19="Named Contact",AC19="Outreach Logged")),"Targeted pursuit","Review"))))
B20: Equifax | C20: Head of Enterprise Project Management Office (EPMO) | D20: Director | E20: Canada | F20: Toronto | G20: 82 | H20: Cold Portal | J20: No | K20: Rejected | L20: 46192 | M20: =IF(OR(L283="",A283=""),"",L283-A283) | P20: Applied date unknown (likely March/early April 2026) — Elena to confirm. Interviewed by phone ~2026-04-24 with Christy Tillich (Manager, Talent Acquisition); Elena's own 2026-05-11 follow-up confirms she received an email that she was "moving to the next stage." REJECTED 2026-06-19: "after further review... decided to move forward with other candidates." Retroactively logged via Gmail review 2026-09-18 — was missing from tracker entirely. Est. fit score: 82 — Head of EPMO (Director-level) is a very strong title match to her core portfolio/PMO leadership lane. | Q20: 46136 | T20: =IF(G20="","",G20) | U20: =IF(C20="","",IF(OR(ISNUMBER(SEARCH("Director",C20)),ISNUMBER(SEARCH("Lead",C20)),ISNUMBER(SEARCH("Senior",C20)),ISNUMBER(SEARCH("Sr.",C20))),90,IF(OR(ISNUMBER(SEARCH("Manager",C20)),ISNUMBER(SEARCH("Program",C20)),ISNUMBER(SEARCH("Portfolio",C20))),80,60))) | V20: =IF(C20="","",IF(OR(ISNUMBER(SEARCH("AI",C20)),ISNUMBER(SEARCH("Data",C20)),ISNUMBER(SEARCH("Technology",C20)),ISNUMBER(SEARCH("Technical",C20)),ISNUMBER(SEARCH("Engineering",C20)),ISNUMBER(SEARCH("Platform",C20)),ISNUMBER(SEARCH("Portfolio",C20))),85,65)) | W20: =IF(C20="","",MIN(100,50+IF(S20<>"",25,0)+IF(R20<>"",15,0)+IF(P20<>"",10,0))) | X20: =IF(E20="","",IF(OR(E20="Canada",E20="CA"),100,IF(OR(E20="United States",E20="USA",E20="US"),IF(J20="Yes",45,75),65))) | Y20: =IF(C20="","",IF(OR(ISNUMBER(SEARCH("Program",C20)),ISNUMBER(SEARCH("Portfolio",C20)),ISNUMBER(SEARCH("Operations",C20)),ISNUMBER(SEARCH("Transformation",C20))),85,IF(ISNUMBER(SEARCH("Product Manager",C20)),55,70))) | Z20: =IF(C20="","",MIN(100,IF(I20<>"",60,10)+IF(AA20>0,MIN(40,AA20*20),0))) | AA20: =IF(T20="","",ROUND(T20*25%+U20*15%+V20*10%+W20*15%+X20*15%+Y20*10%+Z20*10%,0)) | AB20: =IF(AA20="","",IF(X20<50,"Selective / Barrier",IF(AA20>=80,"Tier 1 - Pursue",IF(AA20>=70,"Tier 2 - Pursue",IF(AA20>=60,"Tier 3 - Selective","Do Not Pursue"))))) | AC20: =IF(C20="","",IF(I20<>"","Named Contact",IF(AA20>0,"Outreach Logged","Cold"))) | AD20: =IF(B20="","",COUNTIF('Outreach Log'!$C:$C,B20)) | AE20: =IF(A20="","",IF(OR(K20="Rejected",K20="Closed"),IF(L20<>"",L20-A20,TODAY()-A20),TODAY()-A20)) | AF20: =IF(C20="","",IF(AND(AA20>=70,AC20="Cold"),"High-fit but cold",IF(AND(AA20<60,K20="Applied"),"Low-fit application",IF(AND(AA20>=70,OR(AC20="Named Contact",AC20="Outreach Logged")),"Targeted pursuit","Review"))))
B21: OLG (Ontario Lottery and Gaming Corporation) | C21: Senior IT Portfolio Operations Manager (Req R26_00102) | D21: Senior | E21: Canada | F21: Toronto | G21: 78 | H21: Recruiter (IT-IQ agency) | J21: No | K21: Rejected | L21: 46101 | M21: =IF(OR(L284="",A284=""),"",L284-A284) | P21: Applied date unknown (via IT-IQ agency, Sahand Sadr) — Elena to confirm. Virtual interview held 2026-03-05 with Meghayu Dave (OLG). REJECTED 2026-03-20: "we have hired a successful candidate and the role is closed now" — Elena noted this was never communicated to her directly until she followed up. Retroactively logged via Gmail review 2026-09-18 — was missing from tracker entirely. Est. fit score: 78 — Senior IT Portfolio Operations Manager is a strong title match to her core portfolio-management lane. | Q21: 46086 | T21: =IF(G21="","",G21) | U21: =IF(C21="","",IF(OR(ISNUMBER(SEARCH("Director",C21)),ISNUMBER(SEARCH("Lead",C21)),ISNUMBER(SEARCH("Senior",C21)),ISNUMBER(SEARCH("Sr.",C21))),90,IF(OR(ISNUMBER(SEARCH("Manager",C21)),ISNUMBER(SEARCH("Program",C21)),ISNUMBER(SEARCH("Portfolio",C21))),80,60))) | V21: =IF(C21="","",IF(OR(ISNUMBER(SEARCH("AI",C21)),ISNUMBER(SEARCH("Data",C21)),ISNUMBER(SEARCH("Technology",C21)),ISNUMBER(SEARCH("Technical",C21)),ISNUMBER(SEARCH("Engineering",C21)),ISNUMBER(SEARCH("Platform",C21)),ISNUMBER(SEARCH("Portfolio",C21))),85,65)) | W21: =IF(C21="","",MIN(100,50+IF(S21<>"",25,0)+IF(R21<>"",15,0)+IF(P21<>"",10,0))) | X21: =IF(E21="","",IF(OR(E21="Canada",E21="CA"),100,IF(OR(E21="United States",E21="USA",E21="US"),IF(J21="Yes",45,75),65))) | Y21: =IF(C21="","",IF(OR(ISNUMBER(SEARCH("Program",C21)),ISNUMBER(SEARCH("Portfolio",C21)),ISNUMBER(SEARCH("Operations",C21)),ISNUMBER(SEARCH("Transformation",C21))),85,IF(ISNUMBER(SEARCH("Product Manager",C21)),55,70))) | Z21: =IF(C21="","",MIN(100,IF(I21<>"",60,10)+IF(AA21>0,MIN(40,AA21*20),0))) | AA21: =IF(T21="","",ROUND(T21*25%+U21*15%+V21*10%+W21*15%+X21*15%+Y21*10%+Z21*10%,0)) | AB21: =IF(AA21="","",IF(X21<50,"Selective / Barrier",IF(AA21>=80,"Tier 1 - Pursue",IF(AA21>=70,"Tier 2 - Pursue",IF(AA21>=60,"Tier 3 - Selective","Do Not Pursue"))))) | AC21: =IF(C21="","",IF(I21<>"","Named Contact",IF(AA21>0,"Outreach Logged","Cold"))) | AD21: =IF(B21="","",COUNTIF('Outreach Log'!$C:$C,B21)) | AE21: =IF(A21="","",IF(OR(K21="Rejected",K21="Closed"),IF(L21<>"",L21-A21,TODAY()-A21),TODAY()-A21)) | AF21: =IF(C21="","",IF(AND(AA21>=70,AC21="Cold"),"High-fit but cold",IF(AND(AA21<60,K21="Applied"),"Low-fit application",IF(AND(AA21>=70,OR(AC21="Named Contact",AC21="Outreach Logged")),"Targeted pursuit","Review"))))
B22: TELUS | C22: Senior Project Manager - Program Office, Technology & Enablement for Channels (49833) | D22: Senior | E22: Canada | F22: Toronto | G22: 68 | H22: Cold Portal | J22: No | K22: Rejected | L22: 46027 | M22: =IF(OR(L285="",A285=""),"",L285-A285) | P22: Applied date unknown (before 2026-01-05) — Elena to confirm. REJECTED 2026-01-05: "after careful consideration... decided not to move forward." No separate confirmation email found. Retroactively logged 2026-09-18 — was missing from tracker entirely. | T22: =IF(G22="","",G22) | U22: =IF(C22="","",IF(OR(ISNUMBER(SEARCH("Director",C22)),ISNUMBER(SEARCH("Lead",C22)),ISNUMBER(SEARCH("Senior",C22)),ISNUMBER(SEARCH("Sr.",C22))),90,IF(OR(ISNUMBER(SEARCH("Manager",C22)),ISNUMBER(SEARCH("Program",C22)),ISNUMBER(SEARCH("Portfolio",C22))),80,60))) | V22: =IF(C22="","",IF(OR(ISNUMBER(SEARCH("AI",C22)),ISNUMBER(SEARCH("Data",C22)),ISNUMBER(SEARCH("Technology",C22)),ISNUMBER(SEARCH("Technical",C22)),ISNUMBER(SEARCH("Engineering",C22)),ISNUMBER(SEARCH("Platform",C22)),ISNUMBER(SEARCH("Portfolio",C22))),85,65)) | W22: =IF(C22="","",MIN(100,50+IF(S22<>"",25,0)+IF(R22<>"",15,0)+IF(P22<>"",10,0))) | X22: =IF(E22="","",IF(OR(E22="Canada",E22="CA"),100,IF(OR(E22="United States",E22="USA",E22="US"),IF(J22="Yes",45,75),65))) | Y22: =IF(C22="","",IF(OR(ISNUMBER(SEARCH("Program",C22)),ISNUMBER(SEARCH("Portfolio",C22)),ISNUMBER(SEARCH("Operations",C22)),ISNUMBER(SEARCH("Transformation",C22))),85,IF(ISNUMBER(SEARCH("Product Manager",C22)),55,70))) | Z22: =IF(C22="","",MIN(100,IF(I22<>"",60,10)+IF(AA22>0,MIN(40,AA22*20),0))) | AA22: =IF(T22="","",ROUND(T22*25%+U22*15%+V22*10%+W22*15%+X22*15%+Y22*10%+Z22*10%,0)) | AB22: =IF(AA22="","",IF(X22<50,"Selective / Barrier",IF(AA22>=80,"Tier 1 - Pursue",IF(AA22>=70,"Tier 2 - Pursue",IF(AA22>=60,"Tier 3 - Selective","Do Not Pursue"))))) | AC22: =IF(C22="","",IF(I22<>"","Named Contact",IF(AA22>0,"Outreach Logged","Cold"))) | AD22: =IF(B22="","",COUNTIF('Outreach Log'!$C:$C,B22)) | AE22: =IF(A22="","",IF(OR(K22="Rejected",K22="Closed"),IF(L22<>"",L22-A22,TODAY()-A22),TODAY()-A22)) | AF22: =IF(C22="","",IF(AND(AA22>=70,AC22="Cold"),"High-fit but cold",IF(AND(AA22<60,K22="Applied"),"Low-fit application",IF(AND(AA22>=70,OR(AC22="Named Contact",AC22="Outreach Logged")),"Targeted pursuit","Review"))))
B23: TELUS | C23: Manager - Program Office (52056) | D23: Manager | E23: Canada | F23: Toronto | G23: 65 | H23: Cold Portal | J23: No | K23: Rejected | L23: 46051 | M23: =IF(OR(L286="",A286=""),"",L286-A286) | P23: Applied date unknown (before 2026-01-29) — Elena to confirm. REJECTED 2026-01-29 (role filled): "position has now been filled." No separate confirmation email found. Retroactively logged 2026-09-18 — was missing from tracker entirely. | T23: =IF(G23="","",G23) | U23: =IF(C23="","",IF(OR(ISNUMBER(SEARCH("Director",C23)),ISNUMBER(SEARCH("Lead",C23)),ISNUMBER(SEARCH("Senior",C23)),ISNUMBER(SEARCH("Sr.",C23))),90,IF(OR(ISNUMBER(SEARCH("Manager",C23)),ISNUMBER(SEARCH("Program",C23)),ISNUMBER(SEARCH("Portfolio",C23))),80,60))) | V23: =IF(C23="","",IF(OR(ISNUMBER(SEARCH("AI",C23)),ISNUMBER(SEARCH("Data",C23)),ISNUMBER(SEARCH("Technology",C23)),ISNUMBER(SEARCH("Technical",C23)),ISNUMBER(SEARCH("Engineering",C23)),ISNUMBER(SEARCH("Platform",C23)),ISNUMBER(SEARCH("Portfolio",C23))),85,65)) | W23: =IF(C23="","",MIN(100,50+IF(S23<>"",25,0)+IF(R23<>"",15,0)+IF(P23<>"",10,0))) | X23: =IF(E23="","",IF(OR(E23="Canada",E23="CA"),100,IF(OR(E23="United States",E23="USA",E23="US"),IF(J23="Yes",45,75),65))) | Y23: =IF(C23="","",IF(OR(ISNUMBER(SEARCH("Program",C23)),ISNUMBER(SEARCH("Portfolio",C23)),ISNUMBER(SEARCH("Operations",C23)),ISNUMBER(SEARCH("Transformation",C23))),85,IF(ISNUMBER(SEARCH("Product Manager",C23)),55,70))) | Z23: =IF(C23="","",MIN(100,IF(I23<>"",60,10)+IF(AA23>0,MIN(40,AA23*20),0))) | AA23: =IF(T23="","",ROUND(T23*25%+U23*15%+V23*10%+W23*15%+X23*15%+Y23*10%+Z23*10%,0)) | AB23: =IF(AA23="","",IF(X23<50,"Selective / Barrier",IF(AA23>=80,"Tier 1 - Pursue",IF(AA23>=70,"Tier 2 - Pursue",IF(AA23>=60,"Tier 3 - Selective","Do Not Pursue"))))) | AC23: =IF(C23="","",IF(I23<>"","Named Contact",IF(AA23>0,"Outreach Logged","Cold"))) | AD23: =IF(B23="","",COUNTIF('Outreach Log'!$C:$C,B23)) | AE23: =IF(A23="","",IF(OR(K23="Rejected",K23="Closed"),IF(L23<>"",L23-A23,TODAY()-A23),TODAY()-A23)) | AF23: =IF(C23="","",IF(AND(AA23>=70,AC23="Cold"),"High-fit but cold",IF(AND(AA23<60,K23="Applied"),"Low-fit application",IF(AND(AA23>=70,OR(AC23="Named Contact",AC23="Outreach Logged")),"Targeted pursuit","Review"))))
B24: TELUS | C24: Manager - Program Office, Go-To-Market Governance (51554) | D24: Manager | E24: Canada | F24: Toronto | G24: 65 | H24: Cold Portal | J24: No | K24: Rejected | L24: 46055 | M24: =IF(OR(L287="",A287=""),"",L287-A287) | P24: Applied date unknown (before 2026-02-02) — Elena to confirm. REJECTED 2026-02-02 (role filled): "position has been filled." No separate confirmation email found. Retroactively logged 2026-09-18 — was missing from tracker entirely. | T24: =IF(G24="","",G24) | U24: =IF(C24="","",IF(OR(ISNUMBER(SEARCH("Director",C24)),ISNUMBER(SEARCH("Lead",C24)),ISNUMBER(SEARCH("Senior",C24)),ISNUMBER(SEARCH("Sr.",C24))),90,IF(OR(ISNUMBER(SEARCH("Manager",C24)),ISNUMBER(SEARCH("Program",C24)),ISNUMBER(SEARCH("Portfolio",C24))),80,60))) | V24: =IF(C24="","",IF(OR(ISNUMBER(SEARCH("AI",C24)),ISNUMBER(SEARCH("Data",C24)),ISNUMBER(SEARCH("Technology",C24)),ISNUMBER(SEARCH("Technical",C24)),ISNUMBER(SEARCH("Engineering",C24)),ISNUMBER(SEARCH("Platform",C24)),ISNUMBER(SEARCH("Portfolio",C24))),85,65)) | W24: =IF(C24="","",MIN(100,50+IF(S24<>"",25,0)+IF(R24<>"",15,0)+IF(P24<>"",10,0))) | X24: =IF(E24="","",IF(OR(E24="Canada",E24="CA"),100,IF(OR(E24="United States",E24="USA",E24="US"),IF(J24="Yes",45,75),65))) | Y24: =IF(C24="","",IF(OR(ISNUMBER(SEARCH("Program",C24)),ISNUMBER(SEARCH("Portfolio",C24)),ISNUMBER(SEARCH("Operations",C24)),ISNUMBER(SEARCH("Transformation",C24))),85,IF(ISNUMBER(SEARCH("Product Manager",C24)),55,70))) | Z24: =IF(C24="","",MIN(100,IF(I24<>"",60,10)+IF(AA24>0,MIN(40,AA24*20),0))) | AA24: =IF(T24="","",ROUND(T24*25%+U24*15%+V24*10%+W24*15%+X24*15%+Y24*10%+Z24*10%,0)) | AB24: =IF(AA24="","",IF(X24<50,"Selective / Barrier",IF(AA24>=80,"Tier 1 - Pursue",IF(AA24>=70,"Tier 2 - Pursue",IF(AA24>=60,"Tier 3 - Selective","Do Not Pursue"))))) | AC24: =IF(C24="","",IF(I24<>"","Named Contact",IF(AA24>0,"Outreach Logged","Cold"))) | AD24: =IF(B24="","",COUNTIF('Outreach Log'!$C:$C,B24)) | AE24: =IF(A24="","",IF(OR(K24="Rejected",K24="Closed"),IF(L24<>"",L24-A24,TODAY()-A24),TODAY()-A24)) | AF24: =IF(C24="","",IF(AND(AA24>=70,AC24="Cold"),"High-fit but cold",IF(AND(AA24<60,K24="Applied"),"Low-fit application",IF(AND(AA24>=70,OR(AC24="Named Contact",AC24="Outreach Logged")),"Targeted pursuit","Review"))))
B25: TELUS | C25: Manager, Mobile & Home Program Management (51942) | D25: Manager | E25: Canada | F25: Toronto | G25: 60 | H25: Cold Portal | J25: No | K25: Rejected | L25: 46058 | M25: =IF(OR(L288="",A288=""),"",L288-A288) | P25: Applied date unknown (before 2026-02-05) — Elena to confirm. REJECTED 2026-02-05: "after careful consideration... decided not to move forward." No separate confirmation email found. Retroactively logged 2026-09-18 — was missing from tracker entirely. | T25: =IF(G25="","",G25) | U25: =IF(C25="","",IF(OR(ISNUMBER(SEARCH("Director",C25)),ISNUMBER(SEARCH("Lead",C25)),ISNUMBER(SEARCH("Senior",C25)),ISNUMBER(SEARCH("Sr.",C25))),90,IF(OR(ISNUMBER(SEARCH("Manager",C25)),ISNUMBER(SEARCH("Program",C25)),ISNUMBER(SEARCH("Portfolio",C25))),80,60))) | V25: =IF(C25="","",IF(OR(ISNUMBER(SEARCH("AI",C25)),ISNUMBER(SEARCH("Data",C25)),ISNUMBER(SEARCH("Technology",C25)),ISNUMBER(SEARCH("Technical",C25)),ISNUMBER(SEARCH("Engineering",C25)),ISNUMBER(SEARCH("Platform",C25)),ISNUMBER(SEARCH("Portfolio",C25))),85,65)) | W25: =IF(C25="","",MIN(100,50+IF(S25<>"",25,0)+IF(R25<>"",15,0)+IF(P25<>"",10,0))) | X25: =IF(E25="","",IF(OR(E25="Canada",E25="CA"),100,IF(OR(E25="United States",E25="USA",E25="US"),IF(J25="Yes",45,75),65))) | Y25: =IF(C25="","",IF(OR(ISNUMBER(SEARCH("Program",C25)),ISNUMBER(SEARCH("Portfolio",C25)),ISNUMBER(SEARCH("Operations",C25)),ISNUMBER(SEARCH("Transformation",C25))),85,IF(ISNUMBER(SEARCH("Product Manager",C25)),55,70))) | Z25: =IF(C25="","",MIN(100,IF(I25<>"",60,10)+IF(AA25>0,MIN(40,AA25*20),0))) | AA25: =IF(T25="","",ROUND(T25*25%+U25*15%+V25*10%+W25*15%+X25*15%+Y25*10%+Z25*10%,0)) | AB25: =IF(AA25="","",IF(X25<50,"Selective / Barrier",IF(AA25>=80,"Tier 1 - Pursue",IF(AA25>=70,"Tier 2 - Pursue",IF(AA25>=60,"Tier 3 - Selective","Do Not Pursue"))))) | AC25: =IF(C25="","",IF(I25<>"","Named Contact",IF(AA25>0,"Outreach Logged","Cold"))) | AD25: =IF(B25="","",COUNTIF('Outreach Log'!$C:$C,B25)) | AE25: =IF(A25="","",IF(OR(K25="Rejected",K25="Closed"),IF(L25<>"",L25-A25,TODAY()-A25),TODAY()-A25)) | AF25: =IF(C25="","",IF(AND(AA25>=70,AC25="Cold"),"High-fit but cold",IF(AND(AA25<60,K25="Applied"),"Low-fit application",IF(AND(AA25>=70,OR(AC25="Named Contact",AC25="Outreach Logged")),"Targeted pursuit","Review"))))
A26: HOW TO USE: Fill one row per application (row 2 is an example — replace it). Yellow = cells you fill. "Days to Response" calculates automatically. Channel: how you applied. Sponsorship Question = did the application ask if you need visa sponsorship. Mark "Ghosted (30d+)" after 30 days of silence so the dashboard counts it.
A30: 2025-09-20 | B30: Block | C30: Program Delivery Manager, Releases GTM | D30: Senior | E30: US | F30: Bay Area, CA | G30: 71 | H30: Cold Portal | J30: Yes | K30: Rejected | P30: Leads Square's biannual Releases GTM program (product launch execution) within Business Operations; executive stakeholder management, Go/No-go decisions, cross-disciplinary leadership (design/product/eng/marketing/legal/finance). 12+ years program management/consulting in Fintech/Financial Services. Good fit: strong senior program leadership and executive interaction overlap; GTM/product-launch specificity and direct Fintech/Payments experience are the main gaps. Zone-based pay $217,800-$326,800 USD. | R30: Good fit — GTM/product-launch specificity and direct Fintech/Payments experience are gaps | S30: 12+ yrs program mgmt/consulting in Fintech/Financial Services. Executive interaction. Cross-disciplinary GTM leadership (design/product/eng/marketing/legal/finance). Change management. | T30: =IF(G30="","",G30) | U30: =IF(C30="","",IF(OR(ISNUMBER(SEARCH("Director",C30)),ISNUMBER(SEARCH("Lead",C30)),ISNUMBER(SEARCH("Senior",C30)),ISNUMBER(SEARCH("Sr.",C30))),90,IF(OR(ISNUMBER(SEARCH("Manager",C30)),ISNUMBER(SEARCH("Program",C30)),ISNUMBER(SEARCH("Portfolio",C30))),80,60))) | V30: =IF(C30="","",IF(OR(ISNUMBER(SEARCH("AI",C30)),ISNUMBER(SEARCH("Data",C30)),ISNUMBER(SEARCH("Technology",C30)),ISNUMBER(SEARCH("Technical",C30)),ISNUMBER(SEARCH("Engineering",C30)),ISNUMBER(SEARCH("Platform",C30)),ISNUMBER(SEARCH("Portfolio",C30))),85,65)) | W30: =IF(C30="","",MIN(100,50+IF(S30<>"",25,0)+IF(R30<>"",15,0)+IF(P30<>"",10,0))) | X30: =IF(E30="","",IF(OR(E30="Canada",E30="CA"),100,IF(OR(E30="United States",E30="USA",E30="US"),IF(J30="Yes",45,75),65))) | Y30: =IF(C30="","",IF(OR(ISNUMBER(SEARCH("Program",C30)),ISNUMBER(SEARCH("Portfolio",C30)),ISNUMBER(SEARCH("Operations",C30)),ISNUMBER(SEARCH("Transformation",C30))),85,IF(ISNUMBER(SEARCH("Product Manager",C30)),55,70))) | Z30: =IF(C30="","",MIN(100,IF(I30<>"",60,10)+IF(AA30>0,MIN(40,AA30*20),0))) | AA30: =IF(T30="","",ROUND(T30*25%+U30*15%+V30*10%+W30*15%+X30*15%+Y30*10%+Z30*10%,0)) | AB30: =IF(AA30="","",IF(X30<50,"Selective / Barrier",IF(AA30>=80,"Tier 1 - Pursue",IF(AA30>=70,"Tier 2 - Pursue",IF(AA30>=60,"Tier 3 - Selective","Do Not Pursue"))))) | AC30: =IF(C30="","",IF(I30<>"","Named Contact",IF(AA30>0,"Outreach Logged","Cold"))) | AD30: =IF(B30="","",COUNTIF('Outreach Log'!$C:$C,B30)) | AE30: =IF(A30="","",IF(OR(K30="Rejected",K30="Closed"),IF(L30<>"",L30-A30,TODAY()-A30),TODAY()-A30)) | AF30: =IF(C30="","",IF(AND(AA30>=70,AC30="Cold"),"High-fit but cold",IF(AND(AA30<60,K30="Applied"),"Low-fit application",IF(AND(AA30>=70,OR(AC30="Named Contact",AC30="Outreach Logged")),"Targeted pursuit","Review"))))
A31: 45889 | B31: DeepMind | C31: Program Manager (Legal Team, CORE Programs) | D31: Senior | E31: US | F31: Mountain View, CA | G31: 42 | H31: Cold Portal | J31: Yes | K31: Rejected | M31: =IF(OR(L30="",A30=""),"",L30-A30) | P31: From Greenhouse portal: 'Applied 13 months ago' (Mountain View, CA); date approximate, not found in Gmail search window | User confirmed: Inactive status in Greenhouse = Rejected. | CORE Programs team (Operations Group); owns Legal Team portfolio management, business case building, program delivery for legal/compliance/regulatory initiatives. Requires extensive legal program delivery experience, AI-related legal matters background preferred. Low fit: strong program management skills but no legal/compliance domain background — this is the primary mismatch driver. Base salary $147,000-$216,000 +bonus+equity. | R31: Domain mismatch (Legal/compliance background required) — lowest fit | S31: Extensive legal program delivery experience (AI-legal preferred). Portfolio mgmt for Legal Team. Business case building. Senior stakeholder partnering. | T31: =IF(G31="","",G31) | U31: =IF(C31="","",IF(OR(ISNUMBER(SEARCH("Director",C31)),ISNUMBER(SEARCH("Lead",C31)),ISNUMBER(SEARCH("Senior",C31)),ISNUMBER(SEARCH("Sr.",C31))),90,IF(OR(ISNUMBER(SEARCH("Manager",C31)),ISNUMBER(SEARCH("Program",C31)),ISNUMBER(SEARCH("Portfolio",C31))),80,60))) | V31: =IF(C31="","",IF(OR(ISNUMBER(SEARCH("AI",C31)),ISNUMBER(SEARCH("Data",C31)),ISNUMBER(SEARCH("Technology",C31)),ISNUMBER(SEARCH("Technical",C31)),ISNUMBER(SEARCH("Engineering",C31)),ISNUMBER(SEARCH("Platform",C31)),ISNUMBER(SEARCH("Portfolio",C31))),85,65)) | W31: =IF(C31="","",MIN(100,50+IF(S31<>"",25,0)+IF(R31<>"",15,0)+IF(P31<>"",10,0))) | X31: =IF(E31="","",IF(OR(E31="Canada",E31="CA"),100,IF(OR(E31="United States",E31="USA",E31="US"),IF(J31="Yes",45,75),65))) | Y31: =IF(C31="","",IF(OR(ISNUMBER(SEARCH("Program",C31)),ISNUMBER(SEARCH("Portfolio",C31)),ISNUMBER(SEARCH("Operations",C31)),ISNUMBER(SEARCH("Transformation",C31))),85,IF(ISNUMBER(SEARCH("Product Manager",C31)),55,70))) | Z31: =IF(C31="","",MIN(100,IF(I31<>"",60,10)+IF(AA31>0,MIN(40,AA31*20),0))) | AA31: =IF(T31="","",ROUND(T31*25%+U31*15%+V31*10%+W31*15%+X31*15%+Y31*10%+Z31*10%,0)) | AB31: =IF(AA31="","",IF(X31<50,"Selective / Barrier",IF(AA31>=80,"Tier 1 - Pursue",IF(AA31>=70,"Tier 2 - Pursue",IF(AA31>=60,"Tier 3 - Selective","Do Not Pursue"))))) | AC31: =IF(C31="","",IF(I31<>"","Named Contact",IF(AA31>0,"Outreach Logged","Cold"))) | AD31: =IF(B31="","",COUNTIF('Outreach Log'!$C:$C,B31)) | AE31: =IF(A31="","",IF(OR(K31="Rejected",K31="Closed"),IF(L31<>"",L31-A31,TODAY()-A31),TODAY()-A31)) | AF31: =IF(C31="","",IF(AND(AA31>=70,AC31="Cold"),"High-fit but cold",IF(AND(AA31<60,K31="Applied"),"Low-fit application",IF(AND(AA31>=70,OR(AC31="Named Contact",AC31="Outreach Logged")),"Targeted pursuit","Review"))))
A32: 45920 | B32: Anthropic | C32: Technical Program Manager, Compute Partnerships | D32: Senior | E32: US | F32: San Francisco, CA / New York City, NY | G32: 72 | H32: Cold Portal | J32: Yes | K32: Rejected | M32: =IF(OR(L31="",A31=""),"",L31-A31) | P32: From Greenhouse portal: 'Applied 12 months ago'; distinct from Sep 2026 Anthropic TPM Apps Platform application already in tracker; date approximate | Status corrected to Rejected per user verification (Sep 20, 2026). | Centralized TPM team; owns compute-partner relationships (AWS Bedrock, Google Vertex), aligns technical roadmaps between Anthropic and cloud partner engineering teams. 10+ years TPM/business-ops leadership, complex external partnership management, cloud/AI infra understanding. Good fit: strong overlap with executive stakeholder management and cross-functional program ownership; external partnership depth at this specific scale is the main unverified gap. | R32: Good fit — external cloud-partnership scale is the main unverified gap | S32: 10+ yrs TPM/biz-ops leadership. Complex external partnership mgmt (cloud providers). Cloud computing/AI infra understanding. Executive-level cross-functional coordination (GTM/Finance/Comms/Eng/Product). | T32: =IF(G32="","",G32) | U32: =IF(C32="","",IF(OR(ISNUMBER(SEARCH("Director",C32)),ISNUMBER(SEARCH("Lead",C32)),ISNUMBER(SEARCH("Senior",C32)),ISNUMBER(SEARCH("Sr.",C32))),90,IF(OR(ISNUMBER(SEARCH("Manager",C32)),ISNUMBER(SEARCH("Program",C32)),ISNUMBER(SEARCH("Portfolio",C32))),80,60))) | V32: =IF(C32="","",IF(OR(ISNUMBER(SEARCH("AI",C32)),ISNUMBER(SEARCH("Data",C32)),ISNUMBER(SEARCH("Technology",C32)),ISNUMBER(SEARCH("Technical",C32)),ISNUMBER(SEARCH("Engineering",C32)),ISNUMBER(SEARCH("Platform",C32)),ISNUMBER(SEARCH("Portfolio",C32))),85,65)) | W32: =IF(C32="","",MIN(100,50+IF(S32<>"",25,0)+IF(R32<>"",15,0)+IF(P32<>"",10,0))) | X32: =IF(E32="","",IF(OR(E32="Canada",E32="CA"),100,IF(OR(E32="United States",E32="USA",E32="US"),IF(J32="Yes",45,75),65))) | Y32: =IF(C32="","",IF(OR(ISNUMBER(SEARCH("Program",C32)),ISNUMBER(SEARCH("Portfolio",C32)),ISNUMBER(SEARCH("Operations",C32)),ISNUMBER(SEARCH("Transformation",C32))),85,IF(ISNUMBER(SEARCH("Product Manager",C32)),55,70))) | Z32: =IF(C32="","",MIN(100,IF(I32<>"",60,10)+IF(AA32>0,MIN(40,AA32*20),0))) | AA32: =IF(T32="","",ROUND(T32*25%+U32*15%+V32*10%+W32*15%+X32*15%+Y32*10%+Z32*10%,0)) | AB32: =IF(AA32="","",IF(X32<50,"Selective / Barrier",IF(AA32>=80,"Tier 1 - Pursue",IF(AA32>=70,"Tier 2 - Pursue",IF(AA32>=60,"Tier 3 - Selective","Do Not Pursue"))))) | AC32: =IF(C32="","",IF(I32<>"","Named Contact",IF(AA32>0,"Outreach Logged","Cold"))) | AD32: =IF(B32="","",COUNTIF('Outreach Log'!$C:$C,B32)) | AE32: =IF(A32="","",IF(OR(K32="Rejected",K32="Closed"),IF(L32<>"",L32-A32,TODAY()-A32),TODAY()-A32)) | AF32: =IF(C32="","",IF(AND(AA32>=70,AC32="Cold"),"High-fit but cold",IF(AND(AA32<60,K32="Applied"),"Low-fit application",IF(AND(AA32>=70,OR(AC32="Named Contact",AC32="Outreach Logged")),"Targeted pursuit","Review"))))
A33: 45920 | B33: Databricks | C33: Staff Technical Project Manager - AI/ML | D33: Staff | E33: US | F33: US-Remote | G33: 68 | H33: Cold Portal | J33: Yes | K33: Rejected | M33: =IF(OR(L32="",A32=""),"",L32-A32) | P33: From Greenhouse portal: 'Applied 12 months ago'; date approximate | Status corrected to Rejected per user verification (Sep 20, 2026). | Leads post-sales delivery of strategic AI/ML Professional Services projects (GenAI, Production ML/MLOps); global scope, teams up to 10, contracts $1M+. 5+ years PM, deep ML lifecycle knowledge, AGILE/PMI certification desirable. Moderate fit: strong stakeholder/executive delivery overlap, but requires deep hands-on ML/MLOps technical depth beyond enterprise portfolio background. Pay $102,800-$179,875 USD by zone. | R33: Technical depth gap (hands-on ML/MLOps) | S33: 5+ yrs PM, ML lifecycle knowledge (MLOps). Cloud AI platforms (SageMaker/Vertex/Azure ML). Global scope, $1M+ contracts. AGILE/PMI cert desirable. | T33: =IF(G33="","",G33) | U33: =IF(C33="","",IF(OR(ISNUMBER(SEARCH("Director",C33)),ISNUMBER(SEARCH("Lead",C33)),ISNUMBER(SEARCH("Senior",C33)),ISNUMBER(SEARCH("Sr.",C33))),90,IF(OR(ISNUMBER(SEARCH("Manager",C33)),ISNUMBER(SEARCH("Program",C33)),ISNUMBER(SEARCH("Portfolio",C33))),80,60))) | V33: =IF(C33="","",IF(OR(ISNUMBER(SEARCH("AI",C33)),ISNUMBER(SEARCH("Data",C33)),ISNUMBER(SEARCH("Technology",C33)),ISNUMBER(SEARCH("Technical",C33)),ISNUMBER(SEARCH("Engineering",C33)),ISNUMBER(SEARCH("Platform",C33)),ISNUMBER(SEARCH("Portfolio",C33))),85,65)) | W33: =IF(C33="","",MIN(100,50+IF(S33<>"",25,0)+IF(R33<>"",15,0)+IF(P33<>"",10,0))) | X33: =IF(E33="","",IF(OR(E33="Canada",E33="CA"),100,IF(OR(E33="United States",E33="USA",E33="US"),IF(J33="Yes",45,75),65))) | Y33: =IF(C33="","",IF(OR(ISNUMBER(SEARCH("Program",C33)),ISNUMBER(SEARCH("Portfolio",C33)),ISNUMBER(SEARCH("Operations",C33)),ISNUMBER(SEARCH("Transformation",C33))),85,IF(ISNUMBER(SEARCH("Product Manager",C33)),55,70))) | Z33: =IF(C33="","",MIN(100,IF(I33<>"",60,10)+IF(AA33>0,MIN(40,AA33*20),0))) | AA33: =IF(T33="","",ROUND(T33*25%+U33*15%+V33*10%+W33*15%+X33*15%+Y33*10%+Z33*10%,0)) | AB33: =IF(AA33="","",IF(X33<50,"Selective / Barrier",IF(AA33>=80,"Tier 1 - Pursue",IF(AA33>=70,"Tier 2 - Pursue",IF(AA33>=60,"Tier 3 - Selective","Do Not Pursue"))))) | AC33: =IF(C33="","",IF(I33<>"","Named Contact",IF(AA33>0,"Outreach Logged","Cold"))) | AD33: =IF(B33="","",COUNTIF('Outreach Log'!$C:$C,B33)) | AE33: =IF(A33="","",IF(OR(K33="Rejected",K33="Closed"),IF(L33<>"",L33-A33,TODAY()-A33),TODAY()-A33)) | AF33: =IF(C33="","",IF(AND(AA33>=70,AC33="Cold"),"High-fit but cold",IF(AND(AA33<60,K33="Applied"),"Low-fit application",IF(AND(AA33>=70,OR(AC33="Named Contact",AC33="Outreach Logged")),"Targeted pursuit","Review"))))
A34: 45920 | B34: PlayStation Global | C34: Staff Program Manager, Data & AI | D34: Staff | E34: US | F34: San Diego, CA / San Mateo, CA | G34: 79 | H34: Cold Portal | J34: Yes | K34: Rejected | M34: =IF(OR(L33="",A33=""),"",L33-A33) | P34: Staff TPM leading global-scale Data & AI programs cross-functionally (product, eng, design, biz ops, marketing, legal, finance) from concept to worldwide deployment. 15+ years enterprise program delivery, hands-on GenAI/agentic AI leadership, strong data platform/ML fluency. Strong fit: closely mirrors Bell Canada Data & AI Enterprise Architecture portfolio background and senior TPM experience; specific tool stack (expert JIRA, Tableau, Power BI, Domo, Databricks, SageMaker, Azure ML) is the main unverified gap. | R34: Strong fit — tool-stack depth (JIRA/BI platforms) unverified gap | S34: 15+ yrs enterprise program/project mgmt. Hands-on GenAI/agentic AI delivery. Data platform/ML fluency. Expert JIRA. Tools: Tableau, Power BI, Domo, Databricks, AWS SageMaker, Azure ML. | T34: =IF(G34="","",G34) | U34: =IF(C34="","",IF(OR(ISNUMBER(SEARCH("Director",C34)),ISNUMBER(SEARCH("Lead",C34)),ISNUMBER(SEARCH("Senior",C34)),ISNUMBER(SEARCH("Sr.",C34))),90,IF(OR(ISNUMBER(SEARCH("Manager",C34)),ISNUMBER(SEARCH("Program",C34)),ISNUMBER(SEARCH("Portfolio",C34))),80,60))) | V34: =IF(C34="","",IF(OR(ISNUMBER(SEARCH("AI",C34)),ISNUMBER(SEARCH("Data",C34)),ISNUMBER(SEARCH("Technology",C34)),ISNUMBER(SEARCH("Technical",C34)),ISNUMBER(SEARCH("Engineering",C34)),ISNUMBER(SEARCH("Platform",C34)),ISNUMBER(SEARCH("Portfolio",C34))),85,65)) | W34: =IF(C34="","",MIN(100,50+IF(S34<>"",25,0)+IF(R34<>"",15,0)+IF(P34<>"",10,0))) | X34: =IF(E34="","",IF(OR(E34="Canada",E34="CA"),100,IF(OR(E34="United States",E34="USA",E34="US"),IF(J34="Yes",45,75),65))) | Y34: =IF(C34="","",IF(OR(ISNUMBER(SEARCH("Program",C34)),ISNUMBER(SEARCH("Portfolio",C34)),ISNUMBER(SEARCH("Operations",C34)),ISNUMBER(SEARCH("Transformation",C34))),85,IF(ISNUMBER(SEARCH("Product Manager",C34)),55,70))) | Z34: =IF(C34="","",MIN(100,IF(I34<>"",60,10)+IF(AA34>0,MIN(40,AA34*20),0))) | AA34: =IF(T34="","",ROUND(T34*25%+U34*15%+V34*10%+W34*15%+X34*15%+Y34*10%+Z34*10%,0)) | AB34: =IF(AA34="","",IF(X34<50,"Selective / Barrier",IF(AA34>=80,"Tier 1 - Pursue",IF(AA34>=70,"Tier 2 - Pursue",IF(AA34>=60,"Tier 3 - Selective","Do Not Pursue"))))) | AC34: =IF(C34="","",IF(I34<>"","Named Contact",IF(AA34>0,"Outreach Logged","Cold"))) | AD34: =IF(B34="","",COUNTIF('Outreach Log'!$C:$C,B34)) | AE34: =IF(A34="","",IF(OR(K34="Rejected",K34="Closed"),IF(L34<>"",L34-A34,TODAY()-A34),TODAY()-A34)) | AF34: =IF(C34="","",IF(AND(AA34>=70,AC34="Cold"),"High-fit but cold",IF(AND(AA34<60,K34="Applied"),"Low-fit application",IF(AND(AA34>=70,OR(AC34="Named Contact",AC34="Outreach Logged")),"Targeted pursuit","Review"))))
A35: 45920 | B35: DeepMind | C35: Technical Program Manager, Post-Training | D35: Senior/Staff | E35: US | F35: Mountain View, CA / New York City, NY | G35: 58 | H35: Cold Portal | J35: Yes | K35: Rejected | M35: =IF(OR(L34="",A34=""),"",L34-A34) | P35: From Greenhouse portal: 'Applied 12 months ago'; distinct from DeepMind 'Program Manager' role already logged; date approximate | Status corrected to Rejected per user verification (Sep 20, 2026). | Post-training programs team (GenAI); drives Gemini Tool Use and Agents programs across full lifecycle (data quality, tool integration, eval). 8+ years leading large-scale engineering projects, strong technical/ML acumen, hands-on AI model training experience preferred. Moderate fit: strong program execution and stakeholder influence overlap, but requires deeper hands-on AI/ML technical depth than portfolio-level experience provides. Base salary $183,000-$271,000 +bonus+equity. | R35: Technical depth gap (hands-on AI/ML model training) | S35: BS CS/Eng. 8+ yrs leading large-scale eng projects. Strong technical acumen (API/Tool Use/Agent space). ML/AI principles understanding preferred. | T35: =IF(G35="","",G35) | U35: =IF(C35="","",IF(OR(ISNUMBER(SEARCH("Director",C35)),ISNUMBER(SEARCH("Lead",C35)),ISNUMBER(SEARCH("Senior",C35)),ISNUMBER(SEARCH("Sr.",C35))),90,IF(OR(ISNUMBER(SEARCH("Manager",C35)),ISNUMBER(SEARCH("Program",C35)),ISNUMBER(SEARCH("Portfolio",C35))),80,60))) | V35: =IF(C35="","",IF(OR(ISNUMBER(SEARCH("AI",C35)),ISNUMBER(SEARCH("Data",C35)),ISNUMBER(SEARCH("Technology",C35)),ISNUMBER(SEARCH("Technical",C35)),ISNUMBER(SEARCH("Engineering",C35)),ISNUMBER(SEARCH("Platform",C35)),ISNUMBER(SEARCH("Portfolio",C35))),85,65)) | W35: =IF(C35="","",MIN(100,50+IF(S35<>"",25,0)+IF(R35<>"",15,0)+IF(P35<>"",10,0))) | X35: =IF(E35="","",IF(OR(E35="Canada",E35="CA"),100,IF(OR(E35="United States",E35="USA",E35="US"),IF(J35="Yes",45,75),65))) | Y35: =IF(C35="","",IF(OR(ISNUMBER(SEARCH("Program",C35)),ISNUMBER(SEARCH("Portfolio",C35)),ISNUMBER(SEARCH("Operations",C35)),ISNUMBER(SEARCH("Transformation",C35))),85,IF(ISNUMBER(SEARCH("Product Manager",C35)),55,70))) | Z35: =IF(C35="","",MIN(100,IF(I35<>"",60,10)+IF(AA35>0,MIN(40,AA35*20),0))) | AA35: =IF(T35="","",ROUND(T35*25%+U35*15%+V35*10%+W35*15%+X35*15%+Y35*10%+Z35*10%,0)) | AB35: =IF(AA35="","",IF(X35<50,"Selective / Barrier",IF(AA35>=80,"Tier 1 - Pursue",IF(AA35>=70,"Tier 2 - Pursue",IF(AA35>=60,"Tier 3 - Selective","Do Not Pursue"))))) | AC35: =IF(C35="","",IF(I35<>"","Named Contact",IF(AA35>0,"Outreach Logged","Cold"))) | AD35: =IF(B35="","",COUNTIF('Outreach Log'!$C:$C,B35)) | AE35: =IF(A35="","",IF(OR(K35="Rejected",K35="Closed"),IF(L35<>"",L35-A35,TODAY()-A35),TODAY()-A35)) | AF35: =IF(C35="","",IF(AND(AA35>=70,AC35="Cold"),"High-fit but cold",IF(AND(AA35<60,K35="Applied"),"Low-fit application",IF(AND(AA35>=70,OR(AC35="Named Contact",AC35="Outreach Logged")),"Targeted pursuit","Review"))))
A36: 45950 | B36: Five9 | C36: Manager, AIA Program Management | D36: Manager (people manager) | E36: US | F36: US-Remote (Hybrid if near San Ramon, CA) | G36: 61 | H36: Cold Portal | J36: Yes | K36: Rejected | M36: =IF(OR(L35="",A35=""),"",L35-A35) | P36: Leads AI & Automation Program Management team within Professional Services; directly supervises Program Managers (hiring, performance reviews, coaching), owns portfolio financial management and executive client relationships. 5+ years management/leadership in AI/technical/cloud/contact center PS environment. Moderate fit: strong people-leadership and financial/program governance overlap, but contact-center/PS industry domain is a gap. Base salary $90,000-$216,000 USD. | R36: Industry domain gap (contact center/PS) — people-manager role | S36: 5+ yrs management/leadership, AI/technical/cloud/contact center PS pref. Directly supervises PM team (hiring/reviews/coaching). Financial mgmt, executive stakeholder relationships. | T36: =IF(G36="","",G36) | U36: =IF(C36="","",IF(OR(ISNUMBER(SEARCH("Director",C36)),ISNUMBER(SEARCH("Lead",C36)),ISNUMBER(SEARCH("Senior",C36)),ISNUMBER(SEARCH("Sr.",C36))),90,IF(OR(ISNUMBER(SEARCH("Manager",C36)),ISNUMBER(SEARCH("Program",C36)),ISNUMBER(SEARCH("Portfolio",C36))),80,60))) | V36: =IF(C36="","",IF(OR(ISNUMBER(SEARCH("AI",C36)),ISNUMBER(SEARCH("Data",C36)),ISNUMBER(SEARCH("Technology",C36)),ISNUMBER(SEARCH("Technical",C36)),ISNUMBER(SEARCH("Engineering",C36)),ISNUMBER(SEARCH("Platform",C36)),ISNUMBER(SEARCH("Portfolio",C36))),85,65)) | W36: =IF(C36="","",MIN(100,50+IF(S36<>"",25,0)+IF(R36<>"",15,0)+IF(P36<>"",10,0))) | X36: =IF(E36="","",IF(OR(E36="Canada",E36="CA"),100,IF(OR(E36="United States",E36="USA",E36="US"),IF(J36="Yes",45,75),65))) | Y36: =IF(C36="","",IF(OR(ISNUMBER(SEARCH("Program",C36)),ISNUMBER(SEARCH("Portfolio",C36)),ISNUMBER(SEARCH("Operations",C36)),ISNUMBER(SEARCH("Transformation",C36))),85,IF(ISNUMBER(SEARCH("Product Manager",C36)),55,70))) | Z36: =IF(C36="","",MIN(100,IF(I36<>"",60,10)+IF(AA36>0,MIN(40,AA36*20),0))) | AA36: =IF(T36="","",ROUND(T36*25%+U36*15%+V36*10%+W36*15%+X36*15%+Y36*10%+Z36*10%,0)) | AB36: =IF(AA36="","",IF(X36<50,"Selective / Barrier",IF(AA36>=80,"Tier 1 - Pursue",IF(AA36>=70,"Tier 2 - Pursue",IF(AA36>=60,"Tier 3 - Selective","Do Not Pursue"))))) | AC36: =IF(C36="","",IF(I36<>"","Named Contact",IF(AA36>0,"Outreach Logged","Cold"))) | AD36: =IF(B36="","",COUNTIF('Outreach Log'!$C:$C,B36)) | AE36: =IF(A36="","",IF(OR(K36="Rejected",K36="Closed"),IF(L36<>"",L36-A36,TODAY()-A36),TODAY()-A36)) | AF36: =IF(C36="","",IF(AND(AA36>=70,AC36="Cold"),"High-fit but cold",IF(AND(AA36<60,K36="Applied"),"Low-fit application",IF(AND(AA36>=70,OR(AC36="Named Contact",AC36="Outreach Logged")),"Targeted pursuit","Review"))))
A37: 45981 | B37: Lyft | C37: Senior Program Manager (TechOps) | D37: Senior | E37: Canada | F37: Toronto | G37: 74 | H37: Cold Portal | J37: No | K37: Rejected | M37: =IF(OR(L36="",A36=""),"",L36-A36) | P37: Corporate Engineering/IT/Privacy/Security TechOps program leadership: multi-year ERP/HCM/CRM transformations (Oracle, Anaplan, Workday, Salesforce), privacy compliance (GDPR/CCPA), security implementations. 8+ years complex transformation programs, 6+ years enterprise tech program delivery, $1M+ vendor budget management. Strong fit: closely mirrors enterprise portfolio/program leadership, governance, and executive reporting background. Hybrid 3 days/week. Base pay CAD $122,000-$152,500. From Greenhouse portal review. Rejected. | R37: Strong fit — enterprise TPM/governance match | S37: 8+ yrs transformation programs. 6+ yrs enterprise tech delivery (ERP/HCM/CRM: Oracle/Workday/Salesforce). Privacy/security compliance (GDPR/CCPA). $1M+ vendor budgets. | T37: =IF(G37="","",G37) | U37: =IF(C37="","",IF(OR(ISNUMBER(SEARCH("Director",C37)),ISNUMBER(SEARCH("Lead",C37)),ISNUMBER(SEARCH("Senior",C37)),ISNUMBER(SEARCH("Sr.",C37))),90,IF(OR(ISNUMBER(SEARCH("Manager",C37)),ISNUMBER(SEARCH("Program",C37)),ISNUMBER(SEARCH("Portfolio",C37))),80,60))) | V37: =IF(C37="","",IF(OR(ISNUMBER(SEARCH("AI",C37)),ISNUMBER(SEARCH("Data",C37)),ISNUMBER(SEARCH("Technology",C37)),ISNUMBER(SEARCH("Technical",C37)),ISNUMBER(SEARCH("Engineering",C37)),ISNUMBER(SEARCH("Platform",C37)),ISNUMBER(SEARCH("Portfolio",C37))),85,65)) | W37: =IF(C37="","",MIN(100,50+IF(S37<>"",25,0)+IF(R37<>"",15,0)+IF(P37<>"",10,0))) | X37: =IF(E37="","",IF(OR(E37="Canada",E37="CA"),100,IF(OR(E37="United States",E37="USA",E37="US"),IF(J37="Yes",45,75),65))) | Y37: =IF(C37="","",IF(OR(ISNUMBER(SEARCH("Program",C37)),ISNUMBER(SEARCH("Portfolio",C37)),ISNUMBER(SEARCH("Operations",C37)),ISNUMBER(SEARCH("Transformation",C37))),85,IF(ISNUMBER(SEARCH("Product Manager",C37)),55,70))) | Z37: =IF(C37="","",MIN(100,IF(I37<>"",60,10)+IF(AA37>0,MIN(40,AA37*20),0))) | AA37: =IF(T37="","",ROUND(T37*25%+U37*15%+V37*10%+W37*15%+X37*15%+Y37*10%+Z37*10%,0)) | AB37: =IF(AA37="","",IF(X37<50,"Selective / Barrier",IF(AA37>=80,"Tier 1 - Pursue",IF(AA37>=70,"Tier 2 - Pursue",IF(AA37>=60,"Tier 3 - Selective","Do Not Pursue"))))) | AC37: =IF(C37="","",IF(I37<>"","Named Contact",IF(AA37>0,"Outreach Logged","Cold"))) | AD37: =IF(B37="","",COUNTIF('Outreach Log'!$C:$C,B37)) | AE37: =IF(A37="","",IF(OR(K37="Rejected",K37="Closed"),IF(L37<>"",L37-A37,TODAY()-A37),TODAY()-A37)) | AF37: =IF(C37="","",IF(AND(AA37>=70,AC37="Cold"),"High-fit but cold",IF(AND(AA37<60,K37="Applied"),"Low-fit application",IF(AND(AA37>=70,OR(AC37="Named Contact",AC37="Outreach Logged")),"Targeted pursuit","Review"))))
A38: 45981 | B38: DeepMind | C38: Senior Program Manager, Central Programs | D38: Senior | E38: US | F38: Mountain View, CA | G38: 68 | H38: Cold Portal | J38: Yes | K38: Rejected | M38: =IF(OR(L37="",A37=""),"",L37-A37) | P38: From Greenhouse portal: 'Applied 10 months ago' (Mountain View, CA); distinct from Program Manager and TPM Post-Training roles already logged; date approximate | User confirmed rejected (Sep 20, 2026). | Central Programs team (Operations Group); leads large-scale, cross-functional company-wide strategic programs, partners with senior stakeholders across all GDM functions. No specific domain requirement — general large-scale program leadership. Good fit: strong overlap with enterprise portfolio/program leadership and executive stakeholder management background. Base salary $147,000-$216,000 +bonus+equity. Base salary $174,000-$258,000 +bonus+equity. | R38: Strong fit — general large-scale program leadership | S38: Large-scale cross-functional program leadership. Critical path/dependency mgmt. Senior stakeholder influence. Research/Product/Tech environment experience preferred. | T38: =IF(G38="","",G38) | U38: =IF(C38="","",IF(OR(ISNUMBER(SEARCH("Director",C38)),ISNUMBER(SEARCH("Lead",C38)),ISNUMBER(SEARCH("Senior",C38)),ISNUMBER(SEARCH("Sr.",C38))),90,IF(OR(ISNUMBER(SEARCH("Manager",C38)),ISNUMBER(SEARCH("Program",C38)),ISNUMBER(SEARCH("Portfolio",C38))),80,60))) | V38: =IF(C38="","",IF(OR(ISNUMBER(SEARCH("AI",C38)),ISNUMBER(SEARCH("Data",C38)),ISNUMBER(SEARCH("Technology",C38)),ISNUMBER(SEARCH("Technical",C38)),ISNUMBER(SEARCH("Engineering",C38)),ISNUMBER(SEARCH("Platform",C38)),ISNUMBER(SEARCH("Portfolio",C38))),85,65)) | W38: =IF(C38="","",MIN(100,50+IF(S38<>"",25,0)+IF(R38<>"",15,0)+IF(P38<>"",10,0))) | X38: =IF(E38="","",IF(OR(E38="Canada",E38="CA"),100,IF(OR(E38="United States",E38="USA",E38="US"),IF(J38="Yes",45,75),65))) | Y38: =IF(C38="","",IF(OR(ISNUMBER(SEARCH("Program",C38)),ISNUMBER(SEARCH("Portfolio",C38)),ISNUMBER(SEARCH("Operations",C38)),ISNUMBER(SEARCH("Transformation",C38))),85,IF(ISNUMBER(SEARCH("Product Manager",C38)),55,70))) | Z38: =IF(C38="","",MIN(100,IF(I38<>"",60,10)+IF(AA38>0,MIN(40,AA38*20),0))) | AA38: =IF(T38="","",ROUND(T38*25%+U38*15%+V38*10%+W38*15%+X38*15%+Y38*10%+Z38*10%,0)) | AB38: =IF(AA38="","",IF(X38<50,"Selective / Barrier",IF(AA38>=80,"Tier 1 - Pursue",IF(AA38>=70,"Tier 2 - Pursue",IF(AA38>=60,"Tier 3 - Selective","Do Not Pursue"))))) | AC38: =IF(C38="","",IF(I38<>"","Named Contact",IF(AA38>0,"Outreach Logged","Cold"))) | AD38: =IF(B38="","",COUNTIF('Outreach Log'!$C:$C,B38)) | AE38: =IF(A38="","",IF(OR(K38="Rejected",K38="Closed"),IF(L38<>"",L38-A38,TODAY()-A38),TODAY()-A38)) | AF38: =IF(C38="","",IF(AND(AA38>=70,AC38="Cold"),"High-fit but cold",IF(AND(AA38<60,K38="Applied"),"Low-fit application",IF(AND(AA38>=70,OR(AC38="Named Contact",AC38="Outreach Logged")),"Targeted pursuit","Review"))))
A39: 45981 | B39: SoFi | C39: AI Transformation Manager | D39: Senior/Manager | E39: US | F39: Multiple US locations (UT/CA/TX/WA/NC/NY/FL) | G39: 63 | H39: Cold Portal | J39: Yes | K39: Rejected | M39: =IF(OR(L38="",A38=""),"",L38-A38) | P39: From Greenhouse portal: 'Applied 10 months ago'; date approximate | User confirmed rejected (Sep 20, 2026). | Leads AI-enabled Finance/Accounting/Procurement transformation initiatives at national bank; owns projects concept-to-operationalization, ERP integration (Workday preferred), change management. 8+ years Finance-transformation experience with AI/ML exposure. Moderate fit: strong AI transformation and change management overlap with enterprise portfolio background, but requires deep Finance/Accounting domain expertise (internal controls, accounting principles) outside core experience. | R39: Domain mismatch (Finance/Accounting expertise required) | S39: 8+ yrs Finance transformation w/ AI/ML. Accounting principles/internal controls. ERP integration (Workday). Change management. Cross-functional Finance/Tech partnership. | T39: =IF(G39="","",G39) | U39: =IF(C39="","",IF(OR(ISNUMBER(SEARCH("Director",C39)),ISNUMBER(SEARCH("Lead",C39)),ISNUMBER(SEARCH("Senior",C39)),ISNUMBER(SEARCH("Sr.",C39))),90,IF(OR(ISNUMBER(SEARCH("Manager",C39)),ISNUMBER(SEARCH("Program",C39)),ISNUMBER(SEARCH("Portfolio",C39))),80,60))) | V39: =IF(C39="","",IF(OR(ISNUMBER(SEARCH("AI",C39)),ISNUMBER(SEARCH("Data",C39)),ISNUMBER(SEARCH("Technology",C39)),ISNUMBER(SEARCH("Technical",C39)),ISNUMBER(SEARCH("Engineering",C39)),ISNUMBER(SEARCH("Platform",C39)),ISNUMBER(SEARCH("Portfolio",C39))),85,65)) | W39: =IF(C39="","",MIN(100,50+IF(S39<>"",25,0)+IF(R39<>"",15,0)+IF(P39<>"",10,0))) | X39: =IF(E39="","",IF(OR(E39="Canada",E39="CA"),100,IF(OR(E39="United States",E39="USA",E39="US"),IF(J39="Yes",45,75),65))) | Y39: =IF(C39="","",IF(OR(ISNUMBER(SEARCH("Program",C39)),ISNUMBER(SEARCH("Portfolio",C39)),ISNUMBER(SEARCH("Operations",C39)),ISNUMBER(SEARCH("Transformation",C39))),85,IF(ISNUMBER(SEARCH("Product Manager",C39)),55,70))) | Z39: =IF(C39="","",MIN(100,IF(I39<>"",60,10)+IF(AA39>0,MIN(40,AA39*20),0))) | AA39: =IF(T39="","",ROUND(T39*25%+U39*15%+V39*10%+W39*15%+X39*15%+Y39*10%+Z39*10%,0)) | AB39: =IF(AA39="","",IF(X39<50,"Selective / Barrier",IF(AA39>=80,"Tier 1 - Pursue",IF(AA39>=70,"Tier 2 - Pursue",IF(AA39>=60,"Tier 3 - Selective","Do Not Pursue"))))) | AC39: =IF(C39="","",IF(I39<>"","Named Contact",IF(AA39>0,"Outreach Logged","Cold"))) | AD39: =IF(B39="","",COUNTIF('Outreach Log'!$C:$C,B39)) | AE39: =IF(A39="","",IF(OR(K39="Rejected",K39="Closed"),IF(L39<>"",L39-A39,TODAY()-A39),TODAY()-A39)) | AF39: =IF(C39="","",IF(AND(AA39>=70,AC39="Cold"),"High-fit but cold",IF(AND(AA39<60,K39="Applied"),"Low-fit application",IF(AND(AA39>=70,OR(AC39="Named Contact",AC39="Outreach Logged")),"Targeted pursuit","Review"))))
A40: 45981 | B40: TELUS Digital | C40: Director, Google Customer Engagement Services Practice | D40: Director | E40: Canada | F40: Remote Canada / Toronto / Vancouver | G40: 55 | H40: Cold Portal | J40: No | K40: Rejected | M40: =IF(OR(L39="",A39=""),"",L39-A39) | P40: From Greenhouse portal: 'Applied 10 months ago'; title cut off in screenshot; date approximate | User confirmed rejected (Sep 20, 2026). | Leads global Google Customer Engagement Services (CES/CCAI) practice: Conversational Agents (Dialogflow, GenAI Agents), Agent Assist, Conversational Insights. 10+ years tech consulting/digital transformation with AI/ML focus, 5+ years team leadership, hands-on Google CES/CCAI expertise required, strong contact-center domain knowledge. Moderate-low fit: strong AI leadership and consulting delivery overlap, but requires specific hands-on Google CES product expertise and contact-center domain depth not in background. Base salary $148,000-$185,000 CAD +bonus. | R40: Domain mismatch (contact-center/Google CES product expertise required) | S40: 10+ yrs tech consulting/digital transformation w/ AI/ML. 5+ yrs team leadership. Hands-on Google CES/CCAI (Dialogflow, Agent Assist). Contact-center ops/CX metrics knowledge. | T40: =IF(G40="","",G40) | U40: =IF(C40="","",IF(OR(ISNUMBER(SEARCH("Director",C40)),ISNUMBER(SEARCH("Lead",C40)),ISNUMBER(SEARCH("Senior",C40)),ISNUMBER(SEARCH("Sr.",C40))),90,IF(OR(ISNUMBER(SEARCH("Manager",C40)),ISNUMBER(SEARCH("Program",C40)),ISNUMBER(SEARCH("Portfolio",C40))),80,60))) | V40: =IF(C40="","",IF(OR(ISNUMBER(SEARCH("AI",C40)),ISNUMBER(SEARCH("Data",C40)),ISNUMBER(SEARCH("Technology",C40)),ISNUMBER(SEARCH("Technical",C40)),ISNUMBER(SEARCH("Engineering",C40)),ISNUMBER(SEARCH("Platform",C40)),ISNUMBER(SEARCH("Portfolio",C40))),85,65)) | W40: =IF(C40="","",MIN(100,50+IF(S40<>"",25,0)+IF(R40<>"",15,0)+IF(P40<>"",10,0))) | X40: =IF(E40="","",IF(OR(E40="Canada",E40="CA"),100,IF(OR(E40="United States",E40="USA",E40="US"),IF(J40="Yes",45,75),65))) | Y40: =IF(C40="","",IF(OR(ISNUMBER(SEARCH("Program",C40)),ISNUMBER(SEARCH("Portfolio",C40)),ISNUMBER(SEARCH("Operations",C40)),ISNUMBER(SEARCH("Transformation",C40))),85,IF(ISNUMBER(SEARCH("Product Manager",C40)),55,70))) | Z40: =IF(C40="","",MIN(100,IF(I40<>"",60,10)+IF(AA40>0,MIN(40,AA40*20),0))) | AA40: =IF(T40="","",ROUND(T40*25%+U40*15%+V40*10%+W40*15%+X40*15%+Y40*10%+Z40*10%,0)) | AB40: =IF(AA40="","",IF(X40<50,"Selective / Barrier",IF(AA40>=80,"Tier 1 - Pursue",IF(AA40>=70,"Tier 2 - Pursue",IF(AA40>=60,"Tier 3 - Selective","Do Not Pursue"))))) | AC40: =IF(C40="","",IF(I40<>"","Named Contact",IF(AA40>0,"Outreach Logged","Cold"))) | AD40: =IF(B40="","",COUNTIF('Outreach Log'!$C:$C,B40)) | AE40: =IF(A40="","",IF(OR(K40="Rejected",K40="Closed"),IF(L40<>"",L40-A40,TODAY()-A40),TODAY()-A40)) | AF40: =IF(C40="","",IF(AND(AA40>=70,AC40="Cold"),"High-fit but cold",IF(AND(AA40<60,K40="Applied"),"Low-fit application",IF(AND(AA40>=70,OR(AC40="Named Contact",AC40="Outreach Logged")),"Targeted pursuit","Review"))))
A41: 45981 | B41: Upstart | C41: Senior Program Manager | D41: Senior | E41: US | F41: US-Remote | G41: 66 | H41: Cold Portal | J41: Yes | K41: Rejected | M41: =IF(OR(L40="",A40=""),"",L40-A40) | P41: From Greenhouse portal: 'Applied 10 months ago'; date approximate | User confirmed rejected (Sep 20, 2026). | Servicing & Enablement team at AI lending marketplace; owns programs across operational systems/governance, employee/vendor engagement, accelerator program leadership, or borrower success. 6-8+ years program management/ops/strategy, preferably fintech/financial services/customer ops. Good fit: strong program governance, playbook-building, and cross-functional stakeholder alignment overlap; deep servicing/collections/lending-compliance domain knowledge (preferred, not required) is the gap. Base salary $100,000-$182,000 USD. | R41: Good fit — servicing/lending domain depth is a preferred-not-required gap | S41: 6-8+ yrs program mgmt/ops/strategy, fintech/financial services pref. Cross-functional Product/Eng/Risk/Compliance. Governance frameworks/playbooks. Servicing/collections domain a plus. | T41: =IF(G41="","",G41) | U41: =IF(C41="","",IF(OR(ISNUMBER(SEARCH("Director",C41)),ISNUMBER(SEARCH("Lead",C41)),ISNUMBER(SEARCH("Senior",C41)),ISNUMBER(SEARCH("Sr.",C41))),90,IF(OR(ISNUMBER(SEARCH("Manager",C41)),ISNUMBER(SEARCH("Program",C41)),ISNUMBER(SEARCH("Portfolio",C41))),80,60))) | V41: =IF(C41="","",IF(OR(ISNUMBER(SEARCH("AI",C41)),ISNUMBER(SEARCH("Data",C41)),ISNUMBER(SEARCH("Technology",C41)),ISNUMBER(SEARCH("Technical",C41)),ISNUMBER(SEARCH("Engineering",C41)),ISNUMBER(SEARCH("Platform",C41)),ISNUMBER(SEARCH("Portfolio",C41))),85,65)) | W41: =IF(C41="","",MIN(100,50+IF(S41<>"",25,0)+IF(R41<>"",15,0)+IF(P41<>"",10,0))) | X41: =IF(E41="","",IF(OR(E41="Canada",E41="CA"),100,IF(OR(E41="United States",E41="USA",E41="US"),IF(J41="Yes",45,75),65))) | Y41: =IF(C41="","",IF(OR(ISNUMBER(SEARCH("Program",C41)),ISNUMBER(SEARCH("Portfolio",C41)),ISNUMBER(SEARCH("Operations",C41)),ISNUMBER(SEARCH("Transformation",C41))),85,IF(ISNUMBER(SEARCH("Product Manager",C41)),55,70))) | Z41: =IF(C41="","",MIN(100,IF(I41<>"",60,10)+IF(AA41>0,MIN(40,AA41*20),0))) | AA41: =IF(T41="","",ROUND(T41*25%+U41*15%+V41*10%+W41*15%+X41*15%+Y41*10%+Z41*10%,0)) | AB41: =IF(AA41="","",IF(X41<50,"Selective / Barrier",IF(AA41>=80,"Tier 1 - Pursue",IF(AA41>=70,"Tier 2 - Pursue",IF(AA41>=60,"Tier 3 - Selective","Do Not Pursue"))))) | AC41: =IF(C41="","",IF(I41<>"","Named Contact",IF(AA41>0,"Outreach Logged","Cold"))) | AD41: =IF(B41="","",COUNTIF('Outreach Log'!$C:$C,B41)) | AE41: =IF(A41="","",IF(OR(K41="Rejected",K41="Closed"),IF(L41<>"",L41-A41,TODAY()-A41),TODAY()-A41)) | AF41: =IF(C41="","",IF(AND(AA41>=70,AC41="Cold"),"High-fit but cold",IF(AND(AA41<60,K41="Applied"),"Low-fit application",IF(AND(AA41>=70,OR(AC41="Named Contact",AC41="Outreach Logged")),"Targeted pursuit","Review"))))
A42: 46011 | B42: Affirm | C42: Senior Technical Program Manager | D42: Senior | E42: Canada | F42: Remote Canada | G42: 67 | H42: Cold Portal | J42: No | K42: Rejected | M42: =IF(OR(L41="",A41=""),"",L41-A41) | P42: From Greenhouse portal: 'Applied 9 months ago'; distinct from later 2026 Affirm applications already in tracker; date approximate | User confirmed: Inactive status in Greenhouse = Rejected. | Drives complex, multi-disciplinary technical programs for consumer product suite (BNPL platform); coordinates Engineering/Product/Design/Analytics through full program lifecycle. 5 years technical program management, CS/EE degree or equivalent, FinTech/Payments/Commerce a plus (not required). Good fit: strong stakeholder management and program lifecycle overlap; role expects technical architecture-level fluency which is a moderate gap versus portfolio-level technical exposure. Base pay CAD $125,000-$175,000. | R42: Good fit — technical architecture-level depth is a moderate gap | S42: 5 yrs technical PM. CS/EE degree or equivalent. Architecture-level technical understanding. Distributed backend systems. FinTech/Payments a plus, not required. | T42: =IF(G42="","",G42) | U42: =IF(C42="","",IF(OR(ISNUMBER(SEARCH("Director",C42)),ISNUMBER(SEARCH("Lead",C42)),ISNUMBER(SEARCH("Senior",C42)),ISNUMBER(SEARCH("Sr.",C42))),90,IF(OR(ISNUMBER(SEARCH("Manager",C42)),ISNUMBER(SEARCH("Program",C42)),ISNUMBER(SEARCH("Portfolio",C42))),80,60))) | V42: =IF(C42="","",IF(OR(ISNUMBER(SEARCH("AI",C42)),ISNUMBER(SEARCH("Data",C42)),ISNUMBER(SEARCH("Technology",C42)),ISNUMBER(SEARCH("Technical",C42)),ISNUMBER(SEARCH("Engineering",C42)),ISNUMBER(SEARCH("Platform",C42)),ISNUMBER(SEARCH("Portfolio",C42))),85,65)) | W42: =IF(C42="","",MIN(100,50+IF(S42<>"",25,0)+IF(R42<>"",15,0)+IF(P42<>"",10,0))) | X42: =IF(E42="","",IF(OR(E42="Canada",E42="CA"),100,IF(OR(E42="United States",E42="USA",E42="US"),IF(J42="Yes",45,75),65))) | Y42: =IF(C42="","",IF(OR(ISNUMBER(SEARCH("Program",C42)),ISNUMBER(SEARCH("Portfolio",C42)),ISNUMBER(SEARCH("Operations",C42)),ISNUMBER(SEARCH("Transformation",C42))),85,IF(ISNUMBER(SEARCH("Product Manager",C42)),55,70))) | Z42: =IF(C42="","",MIN(100,IF(I42<>"",60,10)+IF(AA42>0,MIN(40,AA42*20),0))) | AA42: =IF(T42="","",ROUND(T42*25%+U42*15%+V42*10%+W42*15%+X42*15%+Y42*10%+Z42*10%,0)) | AB42: =IF(AA42="","",IF(X42<50,"Selective / Barrier",IF(AA42>=80,"Tier 1 - Pursue",IF(AA42>=70,"Tier 2 - Pursue",IF(AA42>=60,"Tier 3 - Selective","Do Not Pursue"))))) | AC42: =IF(C42="","",IF(I42<>"","Named Contact",IF(AA42>0,"Outreach Logged","Cold"))) | AD42: =IF(B42="","",COUNTIF('Outreach Log'!$C:$C,B42)) | AE42: =IF(A42="","",IF(OR(K42="Rejected",K42="Closed"),IF(L42<>"",L42-A42,TODAY()-A42),TODAY()-A42)) | AF42: =IF(C42="","",IF(AND(AA42>=70,AC42="Cold"),"High-fit but cold",IF(AND(AA42<60,K42="Applied"),"Low-fit application",IF(AND(AA42>=70,OR(AC42="Named Contact",AC42="Outreach Logged")),"Targeted pursuit","Review"))))
... A45: 46011 | B45: Maven Clinic | C45: Client Delivery Manager (Technical) | D45: Mid-level | E45: US | F45: New York, NY / Remote | G45: 43 | H45: Cold Portal | J45: Yes | K45: Rejected | M45: =IF(OR(L44="",A44=""),"",L44-A44) | P45: From Greenhouse portal: 'Applied 9 months ago'; title cut off in screenshot; date approximate | User confirmed rejected (Sep 20, 2026). | Client Delivery Team; leads client onboarding/implementation requirements sessions (data mapping, file-based integrations, SFTP), troubleshoots test accounts, coordinates product/engineering/ops teams. Only 3-5 years experience required — a mid-level implementation role. Low fit: seniority mismatch (overqualified, well below 20+ years experience) plus healthcare/health-plan domain specificity; role is more hands-on technical implementation/integrations coordinator than senior program/portfolio leadership. Base salary $123,000-$135,000 USD. | R45: Seniority mismatch (overqualified, mid-level role) + healthcare domain gap | S45: 3-5 yrs integrations/ops/PM. Healthcare/health-plan ecosystem knowledge. Data mapping, SFTP, SQL/SSO/APIs a plus. Client-facing requirements gathering. | T45: =IF(G45="","",G45) | U45: =IF(C45="","",IF(OR(ISNUMBER(SEARCH("Director",C45)),ISNUMBER(SEARCH("Lead",C45)),ISNUMBER(SEARCH("Senior",C45)),ISNUMBER(SEARCH("Sr.",C45))),90,IF(OR(ISNUMBER(SEARCH("Manager",C45)),ISNUMBER(SEARCH("Program",C45)),ISNUMBER(SEARCH("Portfolio",C45))),80,60))) | V45: =IF(C45="","",IF(OR(ISNUMBER(SEARCH("AI",C45)),ISNUMBER(SEARCH("Data",C45)),ISNUMBER(SEARCH("Technology",C45)),ISNUMBER(SEARCH("Technical",C45)),ISNUMBER(SEARCH("Engineering",C45)),ISNUMBER(SEARCH("Platform",C45)),ISNUMBER(SEARCH("Portfolio",C45))),85,65)) | W45: =IF(C45="","",MIN(100,50+IF(S45<>"",25,0)+IF(R45<>"",15,0)+IF(P45<>"",10,0))) | X45: =IF(E45="","",IF(OR(E45="Canada",E45="CA"),100,IF(OR(E45="United States",E45="USA",E45="US"),IF(J45="Yes",45,75),65))) | Y45: =IF(C45="","",IF(OR(ISNUMBER(SEARCH("Program",C45)),ISNUMBER(SEARCH("Portfolio",C45)),ISNUMBER(SEARCH("Operations",C45)),ISNUMBER(SEARCH("Transformation",C45))),85,IF(ISNUMBER(SEARCH("Product Manager",C45)),55,70))) | Z45: =IF(C45="","",MIN(100,IF(I45<>"",60,10)+IF(AA45>0,MIN(40,AA45*20),0))) | AA45: =IF(T45="","",ROUND(T45*25%+U45*15%+V45*10%+W45*15%+X45*15%+Y45*10%+Z45*10%,0)) | AB45: =IF(AA45="","",IF(X45<50,"Selective / Barrier",IF(AA45>=80,"Tier 1 - Pursue",IF(AA45>=70,"Tier 2 - Pursue",IF(AA45>=60,"Tier 3 - Selective","Do Not Pursue"))))) | AC45: =IF(C45="","",IF(I45<>"","Named Contact",IF(AA45>0,"Outreach Logged","Cold"))) | AD45: =IF(B45="","",COUNTIF('Outreach Log'!$C:$C,B45)) | AE45: =IF(A45="","",IF(OR(K45="Rejected",K45="Closed"),IF(L45<>"",L45-A45,TODAY()-A45),TODAY()-A45)) | AF45: =IF(C45="","",IF(AND(AA45>=70,AC45="Cold"),"High-fit but cold",IF(AND(AA45<60,K45="Applied"),"Low-fit application",IF(AND(AA45>=70,OR(AC45="Named Contact",AC45="Outreach Logged")),"Targeted pursuit","Review"))))
A46: 46040 | B46: Manulife | C46: Technical Product Owner - US Insurance Technology | D46: IC/Owner | E46: Canada | F46: Toronto | G46: 55 | H46: Cold Portal | J46: No | K46: Applied | M46: =IF(OR(L2="",A2=""),"",L2-A2) | P46: Applied 2026-01-18 (Workday confirmation). No response found on file — likely Ghosted (30d+), but leaving as Applied since no explicit silence-tracking date was set at the time. Retroactively logged via full Manulife Gmail history review 2026-09-16 — was missing from tracker. | T46: =IF(G46="","",G46) | U46: =IF(C46="","",IF(OR(ISNUMBER(SEARCH("Director",C46)),ISNUMBER(SEARCH("Lead",C46)),ISNUMBER(SEARCH("Senior",C46)),ISNUMBER(SEARCH("Sr.",C46))),90,IF(OR(ISNUMBER(SEARCH("Manager",C46)),ISNUMBER(SEARCH("Program",C46)),ISNUMBER(SEARCH("Portfolio",C46))),80,60))) | V46: =IF(C46="","",IF(OR(ISNUMBER(SEARCH("AI",C46)),ISNUMBER(SEARCH("Data",C46)),ISNUMBER(SEARCH("Technology",C46)),ISNUMBER(SEARCH("Technical",C46)),ISNUMBER(SEARCH("Engineering",C46)),ISNUMBER(SEARCH("Platform",C46)),ISNUMBER(SEARCH("Portfolio",C46))),85,65)) | W46: =IF(C46="","",MIN(100,50+IF(S46<>"",25,0)+IF(R46<>"",15,0)+IF(P46<>"",10,0))) | X46: =IF(E46="","",IF(OR(E46="Canada",E46="CA"),100,IF(OR(E46="United States",E46="USA",E46="US"),IF(J46="Yes",45,75),65))) | Y46: =IF(C46="","",IF(OR(ISNUMBER(SEARCH("Program",C46)),ISNUMBER(SEARCH("Portfolio",C46)),ISNUMBER(SEARCH("Operations",C46)),ISNUMBER(SEARCH("Transformation",C46))),85,IF(ISNUMBER(SEARCH("Product Manager",C46)),55,70))) | Z46: =IF(C46="","",MIN(100,IF(I46<>"",60,10)+IF(AA46>0,MIN(40,AA46*20),0))) | AA46: =IF(T46="","",ROUND(T46*25%+U46*15%+V46*10%+W46*15%+X46*15%+Y46*10%+Z46*10%,0)) | AB46: =IF(AA46="","",IF(X46<50,"Selective / Barrier",IF(AA46>=80,"Tier 1 - Pursue",IF(AA46>=70,"Tier 2 - Pursue",IF(AA46>=60,"Tier 3 - Selective","Do Not Pursue"))))) | AC46: =IF(C46="","",IF(I46<>"","Named Contact",IF(AA46>0,"Outreach Logged","Cold"))) | AD46: =IF(B46="","",COUNTIF('Outreach Log'!$C:$C,B46)) | AE46: =IF(A46="","",IF(OR(K46="Rejected",K46="Closed"),IF(L46<>"",L46-A46,TODAY()-A46),TODAY()-A46)) | AF46: =IF(C46="","",IF(AND(AA46>=70,AC46="Cold"),"High-fit but cold",IF(AND(AA46<60,K46="Applied"),"Low-fit application",IF(AND(AA46>=70,OR(AC46="Named Contact",AC46="Outreach Logged")),"Targeted pursuit","Review"))))
A47: 46041 | B47: Manulife | C47: Director, Global Technology Strategy | D47: Director | E47: Canada | F47: Toronto | G47: 78 | H47: Cold Portal | J47: No | K47: Rejected | L47: 46076 | M47: =IF(OR(L3="",A3=""),"",L3-A3) | P47: Applied 2026-01-19. REJECTED 2026-02-23: "decided to pursue other candidates whose experience more closely..." Retroactively logged via full Manulife Gmail history review 2026-09-16. | T47: =IF(G47="","",G47) | U47: =IF(C47="","",IF(OR(ISNUMBER(SEARCH("Director",C47)),ISNUMBER(SEARCH("Lead",C47)),ISNUMBER(SEARCH("Senior",C47)),ISNUMBER(SEARCH("Sr.",C47))),90,IF(OR(ISNUMBER(SEARCH("Manager",C47)),ISNUMBER(SEARCH("Program",C47)),ISNUMBER(SEARCH("Portfolio",C47))),80,60))) | V47: =IF(C47="","",IF(OR(ISNUMBER(SEARCH("AI",C47)),ISNUMBER(SEARCH("Data",C47)),ISNUMBER(SEARCH("Technology",C47)),ISNUMBER(SEARCH("Technical",C47)),ISNUMBER(SEARCH("Engineering",C47)),ISNUMBER(SEARCH("Platform",C47)),ISNUMBER(SEARCH("Portfolio",C47))),85,65)) | W47: =IF(C47="","",MIN(100,50+IF(S47<>"",25,0)+IF(R47<>"",15,0)+IF(P47<>"",10,0))) | X47: =IF(E47="","",IF(OR(E47="Canada",E47="CA"),100,IF(OR(E47="United States",E47="USA",E47="US"),IF(J47="Yes",45,75),65))) | Y47: =IF(C47="","",IF(OR(ISNUMBER(SEARCH("Program",C47)),ISNUMBER(SEARCH("Portfolio",C47)),ISNUMBER(SEARCH("Operations",C47)),ISNUMBER(SEARCH("Transformation",C47))),85,IF(ISNUMBER(SEARCH("Product Manager",C47)),55,70))) | Z47: =IF(C47="","",MIN(100,IF(I47<>"",60,10)+IF(AA47>0,MIN(40,AA47*20),0))) | AA47: =IF(T47="","",ROUND(T47*25%+U47*15%+V47*10%+W47*15%+X47*15%+Y47*10%+Z47*10%,0)) | AB47: =IF(AA47="","",IF(X47<50,"Selective / Barrier",IF(AA47>=80,"Tier 1 - Pursue",IF(AA47>=70,"Tier 2 - Pursue",IF(AA47>=60,"Tier 3 - Selective","Do Not Pursue"))))) | AC47: =IF(C47="","",IF(I47<>"","Named Contact",IF(AA47>0,"Outreach Logged","Cold"))) | AD47: =IF(B47="","",COUNTIF('Outreach Log'!$C:$C,B47)) | AE47: =IF(A47="","",IF(OR(K47="Rejected",K47="Closed"),IF(L47<>"",L47-A47,TODAY()-A47),TODAY()-A47)) | AF47: =IF(C47="","",IF(AND(AA47>=70,AC47="Cold"),"High-fit but cold",IF(AND(AA47<60,K47="Applied"),"Low-fit application",IF(AND(AA47>=70,OR(AC47="Named Contact",AC47="Outreach Logged")),"Targeted pursuit","Review"))))
A48: 46041 | B48: TELUS | C48: Program Manager II (51946) | D48: Manager | E48: Canada | F48: Toronto | G48: 62 | H48: Cold Portal | J48: No | K48: Rejected | L48: 46051 | M48: =IF(OR(L4="",A4=""),"",L4-A4) | P48: Applied 2026-01-19 (confirmed via Workday confirmation email). REJECTED 2026-01-29: "after careful consideration... decided not to move forward." Retroactively logged 2026-09-18 — was missing from tracker entirely. | T48: =IF(G48="","",G48) | U48: =IF(C48="","",IF(OR(ISNUMBER(SEARCH("Director",C48)),ISNUMBER(SEARCH("Lead",C48)),ISNUMBER(SEARCH("Senior",C48)),ISNUMBER(SEARCH("Sr.",C48))),90,IF(OR(ISNUMBER(SEARCH("Manager",C48)),ISNUMBER(SEARCH("Program",C48)),ISNUMBER(SEARCH("Portfolio",C48))),80,60))) | V48: =IF(C48="","",IF(OR(ISNUMBER(SEARCH("AI",C48)),ISNUMBER(SEARCH("Data",C48)),ISNUMBER(SEARCH("Technology",C48)),ISNUMBER(SEARCH("Technical",C48)),ISNUMBER(SEARCH("Engineering",C48)),ISNUMBER(SEARCH("Platform",C48)),ISNUMBER(SEARCH("Portfolio",C48))),85,65)) | W48: =IF(C48="","",MIN(100,50+IF(S48<>"",25,0)+IF(R48<>"",15,0)+IF(P48<>"",10,0))) | X48: =IF(E48="","",IF(OR(E48="Canada",E48="CA"),100,IF(OR(E48="United States",E48="USA",E48="US"),IF(J48="Yes",45,75),65))) | Y48: =IF(C48="","",IF(OR(ISNUMBER(SEARCH("Program",C48)),ISNUMBER(SEARCH("Portfolio",C48)),ISNUMBER(SEARCH("Operations",C48)),ISNUMBER(SEARCH("Transformation",C48))),85,IF(ISNUMBER(SEARCH("Product Manager",C48)),55,70))) | Z48: =IF(C48="","",MIN(100,IF(I48<>"",60,10)+IF(AA48>0,MIN(40,AA48*20),0))) | AA48: =IF(T48="","",ROUND(T48*25%+U48*15%+V48*10%+W48*15%+X48*15%+Y48*10%+Z48*10%,0)) | AB48: =IF(AA48="","",IF(X48<50,"Selective / Barrier",IF(AA48>=80,"Tier 1 - Pursue",IF(AA48>=70,"Tier 2 - Pursue",IF(AA48>=60,"Tier 3 - Selective","Do Not Pursue"))))) | AC48: =IF(C48="","",IF(I48<>"","Named Contact",IF(AA48>0,"Outreach Logged","Cold"))) | AD48: =IF(B48="","",COUNTIF('Outreach Log'!$C:$C,B48)) | AE48: =IF(A48="","",IF(OR(K48="Rejected",K48="Closed"),IF(L48<>"",L48-A48,TODAY()-A48),TODAY()-A48)) | AF48: =IF(C48="","",IF(AND(AA48>=70,AC48="Cold"),"High-fit but cold",IF(AND(AA48<60,K48="Applied"),"Low-fit application",IF(AND(AA48>=70,OR(AC48="Named Contact",AC48="Outreach Logged")),"Targeted pursuit","Review"))))
A49: 46042 | B49: Capco | C49: Senior Program Manager - Enterprise Data Transformation | D49: Senior | E49: Canada | F49: Toronto | G49: 68 | H49: Cold Portal | J49: No | K49: Rejected | M49: =IF(OR(L48="",A48=""),"",L48-A48) | P49: Banking & Payments, Permanent. Leads Enterprise Data Management (EDM) transformation: data governance, quality, metadata, lineage, reference/master data across multiple workstreams/vendors for Tier 1 financial institutions. Regulatory-driven (e.g. BCBS 239-type frameworks); senior stakeholder/steering committee engagement. From Greenhouse portal review; distinct from other Capco applications. Rejected. | R49: Industry mismatch (Banking/Payments domain) | S49: Enterprise Data Management (EDM): governance, quality, metadata, lineage, MDM. Multi-vendor delivery. Regulatory frameworks (BCBS 239). Senior stakeholder/steering committee. | T49: =IF(G49="","",G49) | U49: =IF(C49="","",IF(OR(ISNUMBER(SEARCH("Director",C49)),ISNUMBER(SEARCH("Lead",C49)),ISNUMBER(SEARCH("Senior",C49)),ISNUMBER(SEARCH("Sr.",C49))),90,IF(OR(ISNUMBER(SEARCH("Manager",C49)),ISNUMBER(SEARCH("Program",C49)),ISNUMBER(SEARCH("Portfolio",C49))),80,60))) | V49: =IF(C49="","",IF(OR(ISNUMBER(SEARCH("AI",C49)),ISNUMBER(SEARCH("Data",C49)),ISNUMBER(SEARCH("Technology",C49)),ISNUMBER(SEARCH("Technical",C49)),ISNUMBER(SEARCH("Engineering",C49)),ISNUMBER(SEARCH("Platform",C49)),ISNUMBER(SEARCH("Portfolio",C49))),85,65)) | W49: =IF(C49="","",MIN(100,50+IF(S49<>"",25,0)+IF(R49<>"",15,0)+IF(P49<>"",10,0))) | X49: =IF(E49="","",IF(OR(E49="Canada",E49="CA"),100,IF(OR(E49="United States",E49="USA",E49="US"),IF(J49="Yes",45,75),65))) | Y49: =IF(C49="","",IF(OR(ISNUMBER(SEARCH("Program",C49)),ISNUMBER(SEARCH("Portfolio",C49)),ISNUMBER(SEARCH("Operations",C49)),ISNUMBER(SEARCH("Transformation",C49))),85,IF(ISNUMBER(SEARCH("Product Manager",C49)),55,70))) | Z49: =IF(C49="","",MIN(100,IF(I49<>"",60,10)+IF(AA49>0,MIN(40,AA49*20),0))) | AA49: =IF(T49="","",ROUND(T49*25%+U49*15%+V49*10%+W49*15%+X49*15%+Y49*10%+Z49*10%,0)) | AB49: =IF(AA49="","",IF(X49<50,"Selective / Barrier",IF(AA49>=80,"Tier 1 - Pursue",IF(AA49>=70,"Tier 2 - Pursue",IF(AA49>=60,"Tier 3 - Selective","Do Not Pursue"))))) | AC49: =IF(C49="","",IF(I49<>"","Named Contact",IF(AA49>0,"Outreach Logged","Cold"))) | AD49: =IF(B49="","",COUNTIF('Outreach Log'!$C:$C,B49)) | AE49: =IF(A49="","",IF(OR(K49="Rejected",K49="Closed"),IF(L49<>"",L49-A49,TODAY()-A49),TODAY()-A49)) | AF49: =IF(C49="","",IF(AND(AA49>=70,AC49="Cold"),"High-fit but cold",IF(AND(AA49<60,K49="Applied"),"Low-fit application",IF(AND(AA49>=70,OR(AC49="Named Contact",AC49="Outreach Logged")),"Targeted pursuit","Review"))))
A50: 46042 | B50: DeepMind | C50: Program Manager, GeminiApp Data Science | D50: Mid-level (4+ yrs) | E50: US | F50: New York City, NY | G50: 47 | H50: Cold Portal | J50: Yes | K50: Rejected | M50: =IF(OR(L49="",A49=""),"",L49-A49) | P50: GeminiApp Data Science team operational lead: workflow efficiency, review cadence/governance, team culture building, onboarding, comms/branding support. Only 4 years PM experience required — a mid-level/junior operational coordinator role. Low-moderate fit: seniority mismatch (overqualified) rather than a skills gap — role level sits well below 20+ years senior portfolio experience. Base salary $126,000-$181,000 +bonus+equity. | R50: Seniority mismatch (junior/mid-level role, overqualified) | S50: BA/BS + 4 yrs PM/project mgmt. Agile fast-paced product environment. Highly organized, self-starter. MBA/data-science PM experience a plus. | T50: =IF(G50="","",G50) | U50: =IF(C50="","",IF(OR(ISNUMBER(SEARCH("Director",C50)),ISNUMBER(SEARCH("Lead",C50)),ISNUMBER(SEARCH("Senior",C50)),ISNUMBER(SEARCH("Sr.",C50))),90,IF(OR(ISNUMBER(SEARCH("Manager",C50)),ISNUMBER(SEARCH("Program",C50)),ISNUMBER(SEARCH("Portfolio",C50))),80,60))) | V50: =IF(C50="","",IF(OR(ISNUMBER(SEARCH("AI",C50)),ISNUMBER(SEARCH("Data",C50)),ISNUMBER(SEARCH("Technology",C50)),ISNUMBER(SEARCH("Technical",C50)),ISNUMBER(SEARCH("Engineering",C50)),ISNUMBER(SEARCH("Platform",C50)),ISNUMBER(SEARCH("Portfolio",C50))),85,65)) | W50: =IF(C50="","",MIN(100,50+IF(S50<>"",25,0)+IF(R50<>"",15,0)+IF(P50<>"",10,0))) | X50: =IF(E50="","",IF(OR(E50="Canada",E50="CA"),100,IF(OR(E50="United States",E50="USA",E50="US"),IF(J50="Yes",45,75),65))) | Y50: =IF(C50="","",IF(OR(ISNUMBER(SEARCH("Program",C50)),ISNUMBER(SEARCH("Portfolio",C50)),ISNUMBER(SEARCH("Operations",C50)),ISNUMBER(SEARCH("Transformation",C50))),85,IF(ISNUMBER(SEARCH("Product Manager",C50)),55,70))) | Z50: =IF(C50="","",MIN(100,IF(I50<>"",60,10)+IF(AA50>0,MIN(40,AA50*20),0))) | AA50: =IF(T50="","",ROUND(T50*25%+U50*15%+V50*10%+W50*15%+X50*15%+Y50*10%+Z50*10%,0)) | AB50: =IF(AA50="","",IF(X50<50,"Selective / Barrier",IF(AA50>=80,"Tier 1 - Pursue",IF(AA50>=70,"Tier 2 - Pursue",IF(AA50>=60,"Tier 3 - Selective","Do Not Pursue"))))) | AC50: =IF(C50="","",IF(I50<>"","Named Contact",IF(AA50>0,"Outreach Logged","Cold"))) | AD50: =IF(B50="","",COUNTIF('Outreach Log'!$C:$C,B50)) | AE50: =IF(A50="","",IF(OR(K50="Rejected",K50="Closed"),IF(L50<>"",L50-A50,TODAY()-A50),TODAY()-A50)) | AF50: =IF(C50="","",IF(AND(AA50>=70,AC50="Cold"),"High-fit but cold",IF(AND(AA50<60,K50="Applied"),"Low-fit application",IF(AND(AA50>=70,OR(AC50="Named Contact",AC50="Outreach Logged")),"Targeted pursuit","Review"))))
A51: 46042 | B51: Capco | C51: Project Manager - Real Time Agent Assist | D51: Senior/Manager | E51: Canada | F51: Toronto | G51: 73 | H51: Cold Portal | J51: No | K51: Rejected | M51: =IF(OR(L50="",A50=""),"",L50-A50) | P51: Technology & Engineering, Permanent. Leads delivery of AI-powered Real Time Agent Assist capability (contact centre) from design through implementation, working with a third-party vendor; owns RAID log, financials/forecasting, and senior stakeholder engagement. Strong alignment with AI implementation and vendor-management background. From Greenhouse portal review; distinct from other Capco applications. Rejected. | R51: Good fit — AI/vendor management overlap strong | S51: AI-powered agent-assist delivery. RAID/financials ownership. Vendor management. Senior stakeholder engagement. | T51: =IF(G51="","",G51) | U51: =IF(C51="","",IF(OR(ISNUMBER(SEARCH("Director",C51)),ISNUMBER(SEARCH("Lead",C51)),ISNUMBER(SEARCH("Senior",C51)),ISNUMBER(SEARCH("Sr.",C51))),90,IF(OR(ISNUMBER(SEARCH("Manager",C51)),ISNUMBER(SEARCH("Program",C51)),ISNUMBER(SEARCH("Portfolio",C51))),80,60))) | V51: =IF(C51="","",IF(OR(ISNUMBER(SEARCH("AI",C51)),ISNUMBER(SEARCH("Data",C51)),ISNUMBER(SEARCH("Technology",C51)),ISNUMBER(SEARCH("Technical",C51)),ISNUMBER(SEARCH("Engineering",C51)),ISNUMBER(SEARCH("Platform",C51)),ISNUMBER(SEARCH("Portfolio",C51))),85,65)) | W51: =IF(C51="","",MIN(100,50+IF(S51<>"",25,0)+IF(R51<>"",15,0)+IF(P51<>"",10,0))) | X51: =IF(E51="","",IF(OR(E51="Canada",E51="CA"),100,IF(OR(E51="United States",E51="USA",E51="US"),IF(J51="Yes",45,75),65))) | Y51: =IF(C51="","",IF(OR(ISNUMBER(SEARCH("Program",C51)),ISNUMBER(SEARCH("Portfolio",C51)),ISNUMBER(SEARCH("Operations",C51)),ISNUMBER(SEARCH("Transformation",C51))),85,IF(ISNUMBER(SEARCH("Product Manager",C51)),55,70))) | Z51: =IF(C51="","",MIN(100,IF(I51<>"",60,10)+IF(AA51>0,MIN(40,AA51*20),0))) | AA51: =IF(T51="","",ROUND(T51*25%+U51*15%+V51*10%+W51*15%+X51*15%+Y51*10%+Z51*10%,0)) | AB51: =IF(AA51="","",IF(X51<50,"Selective / Barrier",IF(AA51>=80,"Tier 1 - Pursue",IF(AA51>=70,"Tier 2 - Pursue",IF(AA51>=60,"Tier 3 - Selective","Do Not Pursue"))))) | AC51: =IF(C51="","",IF(I51<>"","Named Contact",IF(AA51>0,"Outreach Logged","Cold"))) | AD51: =IF(B51="","",COUNTIF('Outreach Log'!$C:$C,B51)) | AE51: =IF(A51="","",IF(OR(K51="Rejected",K51="Closed"),IF(L51<>"",L51-A51,TODAY()-A51),TODAY()-A51)) | AF51: =IF(C51="","",IF(AND(AA51>=70,AC51="Cold"),"High-fit but cold",IF(AND(AA51<60,K51="Applied"),"Low-fit application",IF(AND(AA51>=70,OR(AC51="Named Contact",AC51="Outreach Logged")),"Targeted pursuit","Review"))))
A52: 46042 | B52: Databricks | C52: Staff Project Manager, Professional Services | D52: Staff | E52: US | F52: Northeast US | G52: 71 | H52: Cold Portal | J52: Yes | K52: Rejected | M52: =IF(OR(L51="",A51=""),"",L51-A51) | P52: From Greenhouse portal: 'Applied 8 months ago'; date approximate | User confirmed rejected/closed (Sep 20, 2026). | Field Engineering TPM; owns strategic programs bridging FE/Product/Engineering/Sales, field enablement scaling (ML/GenAI assets, solution accelerators), voice-of-field to product roadmap. 5+ years TPM in B2B SaaS/data/cloud. Good fit: strong cross-functional program ownership and stakeholder management overlap with data/AI portfolio background. Pay $102,800-$179,875 USD by zone. | R52: Good fit — cross-functional program ownership | S52: 5+ yrs TPM in B2B SaaS/data/cloud. Field Engineering cross-functional coordination. Databricks/Spark hands-on a plus. GenAI/ML program experience a plus. | T52: =IF(G52="","",G52) | U52: =IF(C52="","",IF(OR(ISNUMBER(SEARCH("Director",C52)),ISNUMBER(SEARCH("Lead",C52)),ISNUMBER(SEARCH("Senior",C52)),ISNUMBER(SEARCH("Sr.",C52))),90,IF(OR(ISNUMBER(SEARCH("Manager",C52)),ISNUMBER(SEARCH("Program",C52)),ISNUMBER(SEARCH("Portfolio",C52))),80,60))) | V52: =IF(C52="","",IF(OR(ISNUMBER(SEARCH("AI",C52)),ISNUMBER(SEARCH("Data",C52)),ISNUMBER(SEARCH("Technology",C52)),ISNUMBER(SEARCH("Technical",C52)),ISNUMBER(SEARCH("Engineering",C52)),ISNUMBER(SEARCH("Platform",C52)),ISNUMBER(SEARCH("Portfolio",C52))),85,65)) | W52: =IF(C52="","",MIN(100,50+IF(S52<>"",25,0)+IF(R52<>"",15,0)+IF(P52<>"",10,0))) | X52: =IF(E52="","",IF(OR(E52="Canada",E52="CA"),100,IF(OR(E52="United States",E52="USA",E52="US"),IF(J52="Yes",45,75),65))) | Y52: =IF(C52="","",IF(OR(ISNUMBER(SEARCH("Program",C52)),ISNUMBER(SEARCH("Portfolio",C52)),ISNUMBER(SEARCH("Operations",C52)),ISNUMBER(SEARCH("Transformation",C52))),85,IF(ISNUMBER(SEARCH("Product Manager",C52)),55,70))) | Z52: =IF(C52="","",MIN(100,IF(I52<>"",60,10)+IF(AA52>0,MIN(40,AA52*20),0))) | AA52: =IF(T52="","",ROUND(T52*25%+U52*15%+V52*10%+W52*15%+X52*15%+Y52*10%+Z52*10%,0)) | AB52: =IF(AA52="","",IF(X52<50,"Selective / Barrier",IF(AA52>=80,"Tier 1 - Pursue",IF(AA52>=70,"Tier 2 - Pursue",IF(AA52>=60,"Tier 3 - Selective","Do Not Pursue"))))) | AC52: =IF(C52="","",IF(I52<>"","Named Contact",IF(AA52>0,"Outreach Logged","Cold"))) | AD52: =IF(B52="","",COUNTIF('Outreach Log'!$C:$C,B52)) | AE52: =IF(A52="","",IF(OR(K52="Rejected",K52="Closed"),IF(L52<>"",L52-A52,TODAY()-A52),TODAY()-A52)) | AF52: =IF(C52="","",IF(AND(AA52>=70,AC52="Cold"),"High-fit but cold",IF(AND(AA52<60,K52="Applied"),"Low-fit application",IF(AND(AA52>=70,OR(AC52="Named Contact",AC52="Outreach Logged")),"Targeted pursuit","Review"))))
A53: 46056 | B53: McKesson | C53: Technical Program Manager – AI/ML Initiatives (JR0140444) | D53: Sr TPM | E53: Canada | F53: Mississauga, ON | G53: 80 | H53: Cold Portal | J53: No | K53: Rejected | L53: 46095 | M53: =IF(OR(L5="",A5=""),"",L5-A5) | P53: Applied 2026-02-03 (confirmed via Workday confirmation email). REJECTED 2026-03-14 (confirmed via Workday rejection email): "After careful consideration, we regret to inform you that you have not been selected for this position." Distinct from rows 136 and 242. Est. fit score: 80 — AI/ML Initiatives TPM title closely matches her Bell Data & AI portfolio work; McKesson healthcare vertical already has a strong precedent (row 136, 88% fit). | T53: =IF(G53="","",G53) | U53: =IF(C53="","",IF(OR(ISNUMBER(SEARCH("Director",C53)),ISNUMBER(SEARCH("Lead",C53)),ISNUMBER(SEARCH("Senior",C53)),ISNUMBER(SEARCH("Sr.",C53))),90,IF(OR(ISNUMBER(SEARCH("Manager",C53)),ISNUMBER(SEARCH("Program",C53)),ISNUMBER(SEARCH("Portfolio",C53))),80,60))) | V53: =IF(C53="","",IF(OR(ISNUMBER(SEARCH("AI",C53)),ISNUMBER(SEARCH("Data",C53)),ISNUMBER(SEARCH("Technology",C53)),ISNUMBER(SEARCH("Technical",C53)),ISNUMBER(SEARCH("Engineering",C53)),ISNUMBER(SEARCH("Platform",C53)),ISNUMBER(SEARCH("Portfolio",C53))),85,65)) | W53: =IF(C53="","",MIN(100,50+IF(S53<>"",25,0)+IF(R53<>"",15,0)+IF(P53<>"",10,0))) | X53: =IF(E53="","",IF(OR(E53="Canada",E53="CA"),100,IF(OR(E53="United States",E53="USA",E53="US"),IF(J53="Yes",45,75),65))) | Y53: =IF(C53="","",IF(OR(ISNUMBER(SEARCH("Program",C53)),ISNUMBER(SEARCH("Portfolio",C53)),ISNUMBER(SEARCH("Operations",C53)),ISNUMBER(SEARCH("Transformation",C53))),85,IF(ISNUMBER(SEARCH("Product Manager",C53)),55,70))) | Z53: =IF(C53="","",MIN(100,IF(I53<>"",60,10)+IF(AA53>0,MIN(40,AA53*20),0))) | AA53: =IF(T53="","",ROUND(T53*25%+U53*15%+V53*10%+W53*15%+X53*15%+Y53*10%+Z53*10%,0)) | AB53: =IF(AA53="","",IF(X53<50,"Selective / Barrier",IF(AA53>=80,"Tier 1 - Pursue",IF(AA53>=70,"Tier 2 - Pursue",IF(AA53>=60,"Tier 3 - Selective","Do Not Pursue"))))) | AC53: =IF(C53="","",IF(I53<>"","Named Contact",IF(AA53>0,"Outreach Logged","Cold"))) | AD53: =IF(B53="","",COUNTIF('Outreach Log'!$C:$C,B53)) | AE53: =IF(A53="","",IF(OR(K53="Rejected",K53="Closed"),IF(L53<>"",L53-A53,TODAY()-A53),TODAY()-A53)) | AF53: =IF(C53="","",IF(AND(AA53>=70,AC53="Cold"),"High-fit but cold",IF(AND(AA53<60,K53="Applied"),"Low-fit application",IF(AND(AA53>=70,OR(AC53="Named Contact",AC53="Outreach Logged")),"Targeted pursuit","Review"))))
A54: 46056 | B54: Uber | C54: Senior Program Manager, Governance Strategy & Engagement | D54: Senior | E54: US | F54: New York City, NY | G54: 65 | H54: Cold Portal | J54: Yes | K54: Rejected | M54: =IF(OR(L6="",A6=""),"",L6-A6) | P54: Applied 2026-02-03, per Uber Oracle Cloud candidate portal (Status: Not Selected). Retroactively logged 2026-09-16 — was missing from tracker entirely. Est. fit score: 65 — governance/strategy program work matches her intake-governance and delivery-cadence track record. | T54: =IF(G54="","",G54) | U54: =IF(C54="","",IF(OR(ISNUMBER(SEARCH("Director",C54)),ISNUMBER(SEARCH("Lead",C54)),ISNUMBER(SEARCH("Senior",C54)),ISNUMBER(SEARCH("Sr.",C54))),90,IF(OR(ISNUMBER(SEARCH("Manager",C54)),ISNUMBER(SEARCH("Program",C54)),ISNUMBER(SEARCH("Portfolio",C54))),80,60))) | V54: =IF(C54="","",IF(OR(ISNUMBER(SEARCH("AI",C54)),ISNUMBER(SEARCH("Data",C54)),ISNUMBER(SEARCH("Technology",C54)),ISNUMBER(SEARCH("Technical",C54)),ISNUMBER(SEARCH("Engineering",C54)),ISNUMBER(SEARCH("Platform",C54)),ISNUMBER(SEARCH("Portfolio",C54))),85,65)) | W54: =IF(C54="","",MIN(100,50+IF(S54<>"",25,0)+IF(R54<>"",15,0)+IF(P54<>"",10,0))) | X54: =IF(E54="","",IF(OR(E54="Canada",E54="CA"),100,IF(OR(E54="United States",E54="USA",E54="US"),IF(J54="Yes",45,75),65))) | Y54: =IF(C54="","",IF(OR(ISNUMBER(SEARCH("Program",C54)),ISNUMBER(SEARCH("Portfolio",C54)),ISNUMBER(SEARCH("Operations",C54)),ISNUMBER(SEARCH("Transformation",C54))),85,IF(ISNUMBER(SEARCH("Product Manager",C54)),55,70))) | Z54: =IF(C54="","",MIN(100,IF(I54<>"",60,10)+IF(AA54>0,MIN(40,AA54*20),0))) | AA54: =IF(T54="","",ROUND(T54*25%+U54*15%+V54*10%+W54*15%+X54*15%+Y54*10%+Z54*10%,0)) | AB54: =IF(AA54="","",IF(X54<50,"Selective / Barrier",IF(AA54>=80,"Tier 1 - Pursue",IF(AA54>=70,"Tier 2 - Pursue",IF(AA54>=60,"Tier 3 - Selective","Do Not Pursue"))))) | AC54: =IF(C54="","",IF(I54<>"","Named Contact",IF(AA54>0,"Outreach Logged","Cold"))) | AD54: =IF(B54="","",COUNTIF('Outreach Log'!$C:$C,B54)) | AE54: =IF(A54="","",IF(OR(K54="Rejected",K54="Closed"),IF(L54<>"",L54-A54,TODAY()-A54),TODAY()-A54)) | AF54: =IF(C54="","",IF(AND(AA54>=70,AC54="Cold"),"High-fit but cold",IF(AND(AA54<60,K54="Applied"),"Low-fit application",IF(AND(AA54>=70,OR(AC54="Named Contact",AC54="Outreach Logged")),"Targeted pursuit","Review"))))
A55: 46057 | B55: AMD | C55: Senior Program Manager | D55: Senior | E55: US | F55: Unconfirmed | H55: Cold Portal (iCIMS) | J55: Yes | K55: Applied | M55: =IF(OR(L7="",A7=""),"",L7-A7) | P55: Applied 2026-02-04 (confirmation email). No response found on file — status may be stale/ghosted; not shown in AMD candidate portal screenshot (2026-09-13), which may mean portal view was incomplete or truncated. Retroactively logged via Gmail review 2026-09-13. | T55: =IF(G55="","",G55) | U55: =IF(C55="","",IF(OR(ISNUMBER(SEARCH("Director",C55)),ISNUMBER(SEARCH("Lead",C55)),ISNUMBER(SEARCH("Senior",C55)),ISNUMBER(SEARCH("Sr.",C55))),90,IF(OR(ISNUMBER(SEARCH("Manager",C55)),ISNUMBER(SEARCH("Program",C55)),ISNUMBER(SEARCH("Portfolio",C55))),80,60))) | V55: =IF(C55="","",IF(OR(ISNUMBER(SEARCH("AI",C55)),ISNUMBER(SEARCH("Data",C55)),ISNUMBER(SEARCH("Technology",C55)),ISNUMBER(SEARCH("Technical",C55)),ISNUMBER(SEARCH("Engineering",C55)),ISNUMBER(SEARCH("Platform",C55)),ISNUMBER(SEARCH("Portfolio",C55))),85,65)) | W55: =IF(C55="","",MIN(100,50+IF(S55<>"",25,0)+IF(R55<>"",15,0)+IF(P55<>"",10,0))) | X55: =IF(E55="","",IF(OR(E55="Canada",E55="CA"),100,IF(OR(E55="United States",E55="USA",E55="US"),IF(J55="Yes",45,75),65))) | Y55: =IF(C55="","",IF(OR(ISNUMBER(SEARCH("Program",C55)),ISNUMBER(SEARCH("Portfolio",C55)),ISNUMBER(SEARCH("Operations",C55)),ISNUMBER(SEARCH("Transformation",C55))),85,IF(ISNUMBER(SEARCH("Product Manager",C55)),55,70))) | Z55: =IF(C55="","",MIN(100,IF(I55<>"",60,10)+IF(AA55>0,MIN(40,AA55*20),0))) | AA55: =IF(T55="","",ROUND(T55*25%+U55*15%+V55*10%+W55*15%+X55*15%+Y55*10%+Z55*10%,0)) | AB55: =IF(AA55="","",IF(X55<50,"Selective / Barrier",IF(AA55>=80,"Tier 1 - Pursue",IF(AA55>=70,"Tier 2 - Pursue",IF(AA55>=60,"Tier 3 - Selective","Do Not Pursue"))))) | AC55: =IF(C55="","",IF(I55<>"","Named Contact",IF(AA55>0,"Outreach Logged","Cold"))) | AD55: =IF(B55="","",COUNTIF('Outreach Log'!$C:$C,B55)) | AE55: =IF(A55="","",IF(OR(K55="Rejected",K55="Closed"),IF(L55<>"",L55-A55,TODAY()-A55),TODAY()-A55)) | AF55: =IF(C55="","",IF(AND(AA55>=70,AC55="Cold"),"High-fit but cold",IF(AND(AA55<60,K55="Applied"),"Low-fit application",IF(AND(AA55>=70,OR(AC55="Named Contact",AC55="Outreach Logged")),"Targeted pursuit","Review"))))
A56: 46058 | B56: eBay | C56: Dir., Insights Strat. & Transformation | D56: Director | E56: Canada | F56: Toronto | H56: Cold Portal | J56: No | K56: Rejected | L56: 46066 | M56: =IF(OR(L8="",A8=""),"",L8-A8) | P56: Applied 2026-02-05 (confirmation email). REJECTED 2026-02-13: eBay — "recruiting priorities have changed, no longer hiring for this role." Retroactively logged 2026-09-12. | T56: =IF(G56="","",G56) | U56: =IF(C56="","",IF(OR(ISNUMBER(SEARCH("Director",C56)),ISNUMBER(SEARCH("Lead",C56)),ISNUMBER(SEARCH("Senior",C56)),ISNUMBER(SEARCH("Sr.",C56))),90,IF(OR(ISNUMBER(SEARCH("Manager",C56)),ISNUMBER(SEARCH("Program",C56)),ISNUMBER(SEARCH("Portfolio",C56))),80,60))) | V56: =IF(C56="","",IF(OR(ISNUMBER(SEARCH("AI",C56)),ISNUMBER(SEARCH("Data",C56)),ISNUMBER(SEARCH("Technology",C56)),ISNUMBER(SEARCH("Technical",C56)),ISNUMBER(SEARCH("Engineering",C56)),ISNUMBER(SEARCH("Platform",C56)),ISNUMBER(SEARCH("Portfolio",C56))),85,65)) | W56: =IF(C56="","",MIN(100,50+IF(S56<>"",25,0)+IF(R56<>"",15,0)+IF(P56<>"",10,0))) | X56: =IF(E56="","",IF(OR(E56="Canada",E56="CA"),100,IF(OR(E56="United States",E56="USA",E56="US"),IF(J56="Yes",45,75),65))) | Y56: =IF(C56="","",IF(OR(ISNUMBER(SEARCH("Program",C56)),ISNUMBER(SEARCH("Portfolio",C56)),ISNUMBER(SEARCH("Operations",C56)),ISNUMBER(SEARCH("Transformation",C56))),85,IF(ISNUMBER(SEARCH("Product Manager",C56)),55,70))) | Z56: =IF(C56="","",MIN(100,IF(I56<>"",60,10)+IF(AA56>0,MIN(40,AA56*20),0))) | AA56: =IF(T56="","",ROUND(T56*25%+U56*15%+V56*10%+W56*15%+X56*15%+Y56*10%+Z56*10%,0)) | AB56: =IF(AA56="","",IF(X56<50,"Selective / Barrier",IF(AA56>=80,"Tier 1 - Pursue",IF(AA56>=70,"Tier 2 - Pursue",IF(AA56>=60,"Tier 3 - Selective","Do Not Pursue"))))) | AC56: =IF(C56="","",IF(I56<>"","Named Contact",IF(AA56>0,"Outreach Logged","Cold"))) | AD56: =IF(B56="","",COUNTIF('Outreach Log'!$C:$C,B56)) | AE56: =IF(A56="","",IF(OR(K56="Rejected",K56="Closed"),IF(L56<>"",L56-A56,TODAY()-A56),TODAY()-A56)) | AF56: =IF(C56="","",IF(AND(AA56>=70,AC56="Cold"),"High-fit but cold",IF(AND(AA56<60,K56="Applied"),"Low-fit application",IF(AND(AA56>=70,OR(AC56="Named Contact",AC56="Outreach Logged")),"Targeted pursuit","Review"))))
A57: 46058 | B57: Manulife | C57: Director, Change Enablement (Group Functions Technology) | D57: Director | E57: Canada | F57: Toronto | G57: 70 | H57: Cold Portal | J57: No | K57: Rejected | L57: 46129 | M57: =IF(OR(L9="",A9=""),"",L9-A9) | P57: Applied 2026-02-05. REJECTED 2026-04-17: "won't be moving forward with your application at this time." Retroactively logged via full Manulife Gmail history review 2026-09-16. | T57: =IF(G57="","",G57) | U57: =IF(C57="","",IF(OR(ISNUMBER(SEARCH("Director",C57)),ISNUMBER(SEARCH("Lead",C57)),ISNUMBER(SEARCH("Senior",C57)),ISNUMBER(SEARCH("Sr.",C57))),90,IF(OR(ISNUMBER(SEARCH("Manager",C57)),ISNUMBER(SEARCH("Program",C57)),ISNUMBER(SEARCH("Portfolio",C57))),80,60))) | V57: =IF(C57="","",IF(OR(ISNUMBER(SEARCH("AI",C57)),ISNUMBER(SEARCH("Data",C57)),ISNUMBER(SEARCH("Technology",C57)),ISNUMBER(SEARCH("Technical",C57)),ISNUMBER(SEARCH("Engineering",C57)),ISNUMBER(SEARCH("Platform",C57)),ISNUMBER(SEARCH("Portfolio",C57))),85,65)) | W57: =IF(C57="","",MIN(100,50+IF(S57<>"",25,0)+IF(R57<>"",15,0)+IF(P57<>"",10,0))) | X57: =IF(E57="","",IF(OR(E57="Canada",E57="CA"),100,IF(OR(E57="United States",E57="USA",E57="US"),IF(J57="Yes",45,75),65))) | Y57: =IF(C57="","",IF(OR(ISNUMBER(SEARCH("Program",C57)),ISNUMBER(SEARCH("Portfolio",C57)),ISNUMBER(SEARCH("Operations",C57)),ISNUMBER(SEARCH("Transformation",C57))),85,IF(ISNUMBER(SEARCH("Product Manager",C57)),55,70))) | Z57: =IF(C57="","",MIN(100,IF(I57<>"",60,10)+IF(AA57>0,MIN(40,AA57*20),0))) | AA57: =IF(T57="","",ROUND(T57*25%+U57*15%+V57*10%+W57*15%+X57*15%+Y57*10%+Z57*10%,0)) | AB57: =IF(AA57="","",IF(X57<50,"Selective / Barrier",IF(AA57>=80,"Tier 1 - Pursue",IF(AA57>=70,"Tier 2 - Pursue",IF(AA57>=60,"Tier 3 - Selective","Do Not Pursue"))))) | AC57: =IF(C57="","",IF(I57<>"","Named Contact",IF(AA57>0,"Outreach Logged","Cold"))) | AD57: =IF(B57="","",COUNTIF('Outreach Log'!$C:$C,B57)) | AE57: =IF(A57="","",IF(OR(K57="Rejected",K57="Closed"),IF(L57<>"",L57-A57,TODAY()-A57),TODAY()-A57)) | AF57: =IF(C57="","",IF(AND(AA57>=70,AC57="Cold"),"High-fit but cold",IF(AND(AA57<60,K57="Applied"),"Low-fit application",IF(AND(AA57>=70,OR(AC57="Named Contact",AC57="Outreach Logged")),"Targeted pursuit","Review"))))
A58: 46061 | B58: Manulife | C58: Director, Customer-Centricity & Transformation | D58: Director | E58: Canada | F58: Toronto | G58: 68 | H58: Cold Portal | J58: No | K58: Rejected | L58: 46122 | M58: =IF(OR(L10="",A10=""),"",L10-A10) | P58: Applied 2026-02-08. REJECTED 2026-04-10: "decided to pursue other candidates whose experience more closely..." Retroactively logged via full Manulife Gmail history review 2026-09-16. | T58: =IF(G58="","",G58) | U58: =IF(C58="","",IF(OR(ISNUMBER(SEARCH("Director",C58)),ISNUMBER(SEARCH("Lead",C58)),ISNUMBER(SEARCH("Senior",C58)),ISNUMBER(SEARCH("Sr.",C58))),90,IF(OR(ISNUMBER(SEARCH("Manager",C58)),ISNUMBER(SEARCH("Program",C58)),ISNUMBER(SEARCH("Portfolio",C58))),80,60))) | V58: =IF(C58="","",IF(OR(ISNUMBER(SEARCH("AI",C58)),ISNUMBER(SEARCH("Data",C58)),ISNUMBER(SEARCH("Technology",C58)),ISNUMBER(SEARCH("Technical",C58)),ISNUMBER(SEARCH("Engineering",C58)),ISNUMBER(SEARCH("Platform",C58)),ISNUMBER(SEARCH("Portfolio",C58))),85,65)) | W58: =IF(C58="","",MIN(100,50+IF(S58<>"",25,0)+IF(R58<>"",15,0)+IF(P58<>"",10,0))) | X58: =IF(E58="","",IF(OR(E58="Canada",E58="CA"),100,IF(OR(E58="United States",E58="USA",E58="US"),IF(J58="Yes",45,75),65))) | Y58: =IF(C58="","",IF(OR(ISNUMBER(SEARCH("Program",C58)),ISNUMBER(SEARCH("Portfolio",C58)),ISNUMBER(SEARCH("Operations",C58)),ISNUMBER(SEARCH("Transformation",C58))),85,IF(ISNUMBER(SEARCH("Product Manager",C58)),55,70))) | Z58: =IF(C58="","",MIN(100,IF(I58<>"",60,10)+IF(AA58>0,MIN(40,AA58*20),0))) | AA58: =IF(T58="","",ROUND(T58*25%+U58*15%+V58*10%+W58*15%+X58*15%+Y58*10%+Z58*10%,0)) | AB58: =IF(AA58="","",IF(X58<50,"Selective / Barrier",IF(AA58>=80,"Tier 1 - Pursue",IF(AA58>=70,"Tier 2 - Pursue",IF(AA58>=60,"Tier 3 - Selective","Do Not Pursue"))))) | AC58: =IF(C58="","",IF(I58<>"","Named Contact",IF(AA58>0,"Outreach Logged","Cold"))) | AD58: =IF(B58="","",COUNTIF('Outreach Log'!$C:$C,B58)) | AE58: =IF(A58="","",IF(OR(K58="Rejected",K58="Closed"),IF(L58<>"",L58-A58,TODAY()-A58),TODAY()-A58)) | AF58: =IF(C58="","",IF(AND(AA58>=70,AC58="Cold"),"High-fit but cold",IF(AND(AA58<60,K58="Applied"),"Low-fit application",IF(AND(AA58>=70,OR(AC58="Named Contact",AC58="Outreach Logged")),"Targeted pursuit","Review"))))
A59: 46061 | B59: TELUS | C59: Senior Program Manager (52499) | D59: Senior | E59: Canada | F59: Toronto | G59: 70 | H59: Cold Portal | J59: No | K59: Rejected | L59: 46097 | M59: =IF(OR(L11="",A11=""),"",L11-A11) | P59: Applied 2026-02-08 (confirmed via Workday confirmation email). REJECTED 2026-03-16 (role filled): "position has been filled." Retroactively logged 2026-09-18 — was missing from tracker entirely. | T59: =IF(G59="","",G59) | U59: =IF(C59="","",IF(OR(ISNUMBER(SEARCH("Director",C59)),ISNUMBER(SEARCH("Lead",C59)),ISNUMBER(SEARCH("Senior",C59)),ISNUMBER(SEARCH("Sr.",C59))),90,IF(OR(ISNUMBER(SEARCH("Manager",C59)),ISNUMBER(SEARCH("Program",C59)),ISNUMBER(SEARCH("Portfolio",C59))),80,60))) | V59: =IF(C59="","",IF(OR(ISNUMBER(SEARCH("AI",C59)),ISNUMBER(SEARCH("Data",C59)),ISNUMBER(SEARCH("Technology",C59)),ISNUMBER(SEARCH("Technical",C59)),ISNUMBER(SEARCH("Engineering",C59)),ISNUMBER(SEARCH("Platform",C59)),ISNUMBER(SEARCH("Portfolio",C59))),85,65)) | W59: =IF(C59="","",MIN(100,50+IF(S59<>"",25,0)+IF(R59<>"",15,0)+IF(P59<>"",10,0))) | X59: =IF(E59="","",IF(OR(E59="Canada",E59="CA"),100,IF(OR(E59="United States",E59="USA",E59="US"),IF(J59="Yes",45,75),65))) | Y59: =IF(C59="","",IF(OR(ISNUMBER(SEARCH("Program",C59)),ISNUMBER(SEARCH("Portfolio",C59)),ISNUMBER(SEARCH("Operations",C59)),ISNUMBER(SEARCH("Transformation",C59))),85,IF(ISNUMBER(SEARCH("Product Manager",C59)),55,70))) | Z59: =IF(C59="","",MIN(100,IF(I59<>"",60,10)+IF(AA59>0,MIN(40,AA59*20),0))) | AA59: =IF(T59="","",ROUND(T59*25%+U59*15%+V59*10%+W59*15%+X59*15%+Y59*10%+Z59*10%,0)) | AB59: =IF(AA59="","",IF(X59<50,"Selective / Barrier",IF(AA59>=80,"Tier 1 - Pursue",IF(AA59>=70,"Tier 2 - Pursue",IF(AA59>=60,"Tier 3 - Selective","Do Not Pursue"))))) | AC59: =IF(C59="","",IF(I59<>"","Named Contact",IF(AA59>0,"Outreach Logged","Cold"))) | AD59: =IF(B59="","",COUNTIF('Outreach Log'!$C:$C,B59)) | AE59: =IF(A59="","",IF(OR(K59="Rejected",K59="Closed"),IF(L59<>"",L59-A59,TODAY()-A59),TODAY()-A59)) | AF59: =IF(C59="","",IF(AND(AA59>=70,AC59="Cold"),"High-fit but cold",IF(AND(AA59<60,K59="Applied"),"Low-fit application",IF(AND(AA59>=70,OR(AC59="Named Contact",AC59="Outreach Logged")),"Targeted pursuit","Review"))))
A60: 46062 | B60: Manulife | C60: IT Portfolio Director | D60: Director | E60: Canada | F60: Toronto | G60: 80 | H60: Cold Portal | J60: No | K60: Rejected | L60: 46132 | M60: =IF(OR(L12="",A12=""),"",L12-A12) | P60: Applied 2026-02-09. REJECTED 2026-04-20: "won't be moving forward with your application at this time." Retroactively logged via full Manulife Gmail history review 2026-09-16. Est. fit score: 80 — Portfolio Director title is a very strong match to her core lane. | T60: =IF(G60="","",G60) | U60: =IF(C60="","",IF(OR(ISNUMBER(SEARCH("Director",C60)),ISNUMBER(SEARCH("Lead",C60)),ISNUMBER(SEARCH("Senior",C60)),ISNUMBER(SEARCH("Sr.",C60))),90,IF(OR(ISNUMBER(SEARCH("Manager",C60)),ISNUMBER(SEARCH("Program",C60)),ISNUMBER(SEARCH("Portfolio",C60))),80,60))) | V60: =IF(C60="","",IF(OR(ISNUMBER(SEARCH("AI",C60)),ISNUMBER(SEARCH("Data",C60)),ISNUMBER(SEARCH("Technology",C60)),ISNUMBER(SEARCH("Technical",C60)),ISNUMBER(SEARCH("Engineering",C60)),ISNUMBER(SEARCH("Platform",C60)),ISNUMBER(SEARCH("Portfolio",C60))),85,65)) | W60: =IF(C60="","",MIN(100,50+IF(S60<>"",25,0)+IF(R60<>"",15,0)+IF(P60<>"",10,0))) | X60: =IF(E60="","",IF(OR(E60="Canada",E60="CA"),100,IF(OR(E60="United States",E60="USA",E60="US"),IF(J60="Yes",45,75),65))) | Y60: =IF(C60="","",IF(OR(ISNUMBER(SEARCH("Program",C60)),ISNUMBER(SEARCH("Portfolio",C60)),ISNUMBER(SEARCH("Operations",C60)),ISNUMBER(SEARCH("Transformation",C60))),85,IF(ISNUMBER(SEARCH("Product Manager",C60)),55,70))) | Z60: =IF(C60="","",MIN(100,IF(I60<>"",60,10)+IF(AA60>0,MIN(40,AA60*20),0))) | AA60: =IF(T60="","",ROUND(T60*25%+U60*15%+V60*10%+W60*15%+X60*15%+Y60*10%+Z60*10%,0)) | AB60: =IF(AA60="","",IF(X60<50,"Selective / Barrier",IF(AA60>=80,"Tier 1 - Pursue",IF(AA60>=70,"Tier 2 - Pursue",IF(AA60>=60,"Tier 3 - Selective","Do Not Pursue"))))) | AC60: =IF(C60="","",IF(I60<>"","Named Contact",IF(AA60>0,"Outreach Logged","Cold"))) | AD60: =IF(B60="","",COUNTIF('Outreach Log'!$C:$C,B60)) | AE60: =IF(A60="","",IF(OR(K60="Rejected",K60="Closed"),IF(L60<>"",L60-A60,TODAY()-A60),TODAY()-A60)) | AF60: =IF(C60="","",IF(AND(AA60>=70,AC60="Cold"),"High-fit but cold",IF(AND(AA60<60,K60="Applied"),"Low-fit application",IF(AND(AA60>=70,OR(AC60="Named Contact",AC60="Outreach Logged")),"Targeted pursuit","Review"))))
A61: 46062 | B61: Manulife | C61: Agile Delivery Lead | D61: Lead | E61: Canada | F61: Toronto | G61: 65 | H61: Cold Portal | J61: No | K61: Rejected | L61: 46093 | M61: =IF(OR(L13="",A13=""),"",L13-A13) | P61: Applied 2026-02-09. REJECTED 2026-03-12: "won't be moving forward with your application at this time." Retroactively logged via full Manulife Gmail history review 2026-09-16. | T61: =IF(G61="","",G61) | U61: =IF(C61="","",IF(OR(ISNUMBER(SEARCH("Director",C61)),ISNUMBER(SEARCH("Lead",C61)),ISNUMBER(SEARCH("Senior",C61)),ISNUMBER(SEARCH("Sr.",C61))),90,IF(OR(ISNUMBER(SEARCH("Manager",C61)),ISNUMBER(SEARCH("Program",C61)),ISNUMBER(SEARCH("Portfolio",C61))),80,60))) | V61: =IF(C61="","",IF(OR(ISNUMBER(SEARCH("AI",C61)),ISNUMBER(SEARCH("Data",C61)),ISNUMBER(SEARCH("Technology",C61)),ISNUMBER(SEARCH("Technical",C61)),ISNUMBER(SEARCH("Engineering",C61)),ISNUMBER(SEARCH("Platform",C61)),ISNUMBER(SEARCH("Portfolio",C61))),85,65)) | W61: =IF(C61="","",MIN(100,50+IF(S61<>"",25,0)+IF(R61<>"",15,0)+IF(P61<>"",10,0))) | X61: =IF(E61="","",IF(OR(E61="Canada",E61="CA"),100,IF(OR(E61="United States",E61="USA",E61="US"),IF(J61="Yes",45,75),65))) | Y61: =IF(C61="","",IF(OR(ISNUMBER(SEARCH("Program",C61)),ISNUMBER(SEARCH("Portfolio",C61)),ISNUMBER(SEARCH("Operations",C61)),ISNUMBER(SEARCH("Transformation",C61))),85,IF(ISNUMBER(SEARCH("Product Manager",C61)),55,70))) | Z61: =IF(C61="","",MIN(100,IF(I61<>"",60,10)+IF(AA61>0,MIN(40,AA61*20),0))) | AA61: =IF(T61="","",ROUND(T61*25%+U61*15%+V61*10%+W61*15%+X61*15%+Y61*10%+Z61*10%,0)) | AB61: =IF(AA61="","",IF(X61<50,"Selective / Barrier",IF(AA61>=80,"Tier 1 - Pursue",IF(AA61>=70,"Tier 2 - Pursue",IF(AA61>=60,"Tier 3 - Selective","Do Not Pursue"))))) | AC61: =IF(C61="","",IF(I61<>"","Named Contact",IF(AA61>0,"Outreach Logged","Cold"))) | AD61: =IF(B61="","",COUNTIF('Outreach Log'!$C:$C,B61)) | AE61: =IF(A61="","",IF(OR(K61="Rejected",K61="Closed"),IF(L61<>"",L61-A61,TODAY()-A61),TODAY()-A61)) | AF61: =IF(C61="","",IF(AND(AA61>=70,AC61="Cold"),"High-fit but cold",IF(AND(AA61<60,K61="Applied"),"Low-fit application",IF(AND(AA61>=70,OR(AC61="Named Contact",AC61="Outreach Logged")),"Targeted pursuit","Review"))))
A62: 46066 | B62: Cohere | C62: Engineering Program Manager, North | D62: Manager | E62: Canada | F62: Toronto | H62: Cold Portal | J62: No | K62: Rejected | L62: 46192 | M62: =IF(OR(L14="",A14=""),"",L14-A14) | P62: REJECTED 2026-06-19: Cohere (Ashby) — "the position was filled before we had the opportunity to consider your candidacy." Retroactively logged; was missing from tracker. | T62: =IF(G62="","",G62) | U62: =IF(C62="","",IF(OR(ISNUMBER(SEARCH("Director",C62)),ISNUMBER(SEARCH("Lead",C62)),ISNUMBER(SEARCH("Senior",C62)),ISNUMBER(SEARCH("Sr.",C62))),90,IF(OR(ISNUMBER(SEARCH("Manager",C62)),ISNUMBER(SEARCH("Program",C62)),ISNUMBER(SEARCH("Portfolio",C62))),80,60))) | V62: =IF(C62="","",IF(OR(ISNUMBER(SEARCH("AI",C62)),ISNUMBER(SEARCH("Data",C62)),ISNUMBER(SEARCH("Technology",C62)),ISNUMBER(SEARCH("Technical",C62)),ISNUMBER(SEARCH("Engineering",C62)),ISNUMBER(SEARCH("Platform",C62)),ISNUMBER(SEARCH("Portfolio",C62))),85,65)) | W62: =IF(C62="","",MIN(100,50+IF(S62<>"",25,0)+IF(R62<>"",15,0)+IF(P62<>"",10,0))) | X62: =IF(E62="","",IF(OR(E62="Canada",E62="CA"),100,IF(OR(E62="United States",E62="USA",E62="US"),IF(J62="Yes",45,75),65))) | Y62: =IF(C62="","",IF(OR(ISNUMBER(SEARCH("Program",C62)),ISNUMBER(SEARCH("Portfolio",C62)),ISNUMBER(SEARCH("Operations",C62)),ISNUMBER(SEARCH("Transformation",C62))),85,IF(ISNUMBER(SEARCH("Product Manager",C62)),55,70))) | Z62: =IF(C62="","",MIN(100,IF(I62<>"",60,10)+IF(AA62>0,MIN(40,AA62*20),0))) | AA62: =IF(T62="","",ROUND(T62*25%+U62*15%+V62*10%+W62*15%+X62*15%+Y62*10%+Z62*10%,0)) | AB62: =IF(AA62="","",IF(X62<50,"Selective / Barrier",IF(AA62>=80,"Tier 1 - Pursue",IF(AA62>=70,"Tier 2 - Pursue",IF(AA62>=60,"Tier 3 - Selective","Do Not Pursue"))))) | AC62: =IF(C62="","",IF(I62<>"","Named Contact",IF(AA62>0,"Outreach Logged","Cold"))) | AD62: =IF(B62="","",COUNTIF('Outreach Log'!$C:$C,B62)) | AE62: =IF(A62="","",IF(OR(K62="Rejected",K62="Closed"),IF(L62<>"",L62-A62,TODAY()-A62),TODAY()-A62)) | AF62: =IF(C62="","",IF(AND(AA62>=70,AC62="Cold"),"High-fit but cold",IF(AND(AA62<60,K62="Applied"),"Low-fit application",IF(AND(AA62>=70,OR(AC62="Named Contact",AC62="Outreach Logged")),"Targeted pursuit","Review"))))
A63: 46066 | B63: Zip | C63: Manager, Business Development | D63: Manager | E63: Canada | F63: Toronto | G63: 25 | H63: Cold Portal | J63: No | K63: Closed | L63: 46261 | M63: =IF(OR(L15="",A15=""),"",L15-A15) | P63: Application date not previously logged in tracker. Response received 2026-08-27 via Zip Hiring Team (no-reply@ashbyhq.com): hiring paused for this role, not a rejection of fit. Zip has asked to keep Elena's info on file for future headcount. No prior record of this application or its tailored resume in the tracker — logging status only. | Est. fit score: 25% — Business Development discipline is a significant mismatch from her program/portfolio management background, despite Canada/no-sponsorship fit | Date Applied confirmed 2026-02-13 via Zip Hiring Team confirmation email (Ashby). | T63: =IF(G63="","",G63) | U63: =IF(C63="","",IF(OR(ISNUMBER(SEARCH("Director",C63)),ISNUMBER(SEARCH("Lead",C63)),ISNUMBER(SEARCH("Senior",C63)),ISNUMBER(SEARCH("Sr.",C63))),90,IF(OR(ISNUMBER(SEARCH("Manager",C63)),ISNUMBER(SEARCH("Program",C63)),ISNUMBER(SEARCH("Portfolio",C63))),80,60))) | V63: =IF(C63="","",IF(OR(ISNUMBER(SEARCH("AI",C63)),ISNUMBER(SEARCH("Data",C63)),ISNUMBER(SEARCH("Technology",C63)),ISNUMBER(SEARCH("Technical",C63)),ISNUMBER(SEARCH("Engineering",C63)),ISNUMBER(SEARCH("Platform",C63)),ISNUMBER(SEARCH("Portfolio",C63))),85,65)) | W63: =IF(C63="","",MIN(100,50+IF(S63<>"",25,0)+IF(R63<>"",15,0)+IF(P63<>"",10,0))) | X63: =IF(E63="","",IF(OR(E63="Canada",E63="CA"),100,IF(OR(E63="United States",E63="USA",E63="US"),IF(J63="Yes",45,75),65))) | Y63: =IF(C63="","",IF(OR(ISNUMBER(SEARCH("Program",C63)),ISNUMBER(SEARCH("Portfolio",C63)),ISNUMBER(SEARCH("Operations",C63)),ISNUMBER(SEARCH("Transformation",C63))),85,IF(ISNUMBER(SEARCH("Product Manager",C63)),55,70))) | Z63: =IF(C63="","",MIN(100,IF(I63<>"",60,10)+IF(AA63>0,MIN(40,AA63*20),0))) | AA63: =IF(T63="","",ROUND(T63*25%+U63*15%+V63*10%+W63*15%+X63*15%+Y63*10%+Z63*10%,0)) | AB63: =IF(AA63="","",IF(X63<50,"Selective / Barrier",IF(AA63>=80,"Tier 1 - Pursue",IF(AA63>=70,"Tier 2 - Pursue",IF(AA63>=60,"Tier 3 - Selective","Do Not Pursue"))))) | AC63: =IF(C63="","",IF(I63<>"","Named Contact",IF(AA63>0,"Outreach Logged","Cold"))) | AD63: =IF(B63="","",COUNTIF('Outreach Log'!$C:$C,B63)) | AE63: =IF(A63="","",IF(OR(K63="Rejected",K63="Closed"),IF(L63<>"",L63-A63,TODAY()-A63),TODAY()-A63)) | AF63: =IF(C63="","",IF(AND(AA63>=70,AC63="Cold"),"High-fit but cold",IF(AND(AA63<60,K63="Applied"),"Low-fit application",IF(AND(AA63>=70,OR(AC63="Named Contact",AC63="Outreach Logged")),"Targeted pursuit","Review"))))
A64: 46066 | B64: TELUS | C64: Senior Program Manager - Virtual Position (52874) | D64: Senior | E64: Canada | F64: Remote (Virtual) | G64: 70 | H64: Cold Portal | J64: No | K64: Rejected | L64: 46133 | M64: =IF(OR(L16="",A16=""),"",L16-A16) | P64: Applied 2026-02-13 (confirmed via Workday confirmation email). REJECTED 2026-04-21 (role filled): "position has been filled." Retroactively logged 2026-09-18 — was missing from tracker entirely. | T64: =IF(G64="","",G64) | U64: =IF(C64="","",IF(OR(ISNUMBER(SEARCH("Director",C64)),ISNUMBER(SEARCH("Lead",C64)),ISNUMBER(SEARCH("Senior",C64)),ISNUMBER(SEARCH("Sr.",C64))),90,IF(OR(ISNUMBER(SEARCH("Manager",C64)),ISNUMBER(SEARCH("Program",C64)),ISNUMBER(SEARCH("Portfolio",C64))),80,60))) | V64: =IF(C64="","",IF(OR(ISNUMBER(SEARCH("AI",C64)),ISNUMBER(SEARCH("Data",C64)),ISNUMBER(SEARCH("Technology",C64)),ISNUMBER(SEARCH("Technical",C64)),ISNUMBER(SEARCH("Engineering",C64)),ISNUMBER(SEARCH("Platform",C64)),ISNUMBER(SEARCH("Portfolio",C64))),85,65)) | W64: =IF(C64="","",MIN(100,50+IF(S64<>"",25,0)+IF(R64<>"",15,0)+IF(P64<>"",10,0))) | X64: =IF(E64="","",IF(OR(E64="Canada",E64="CA"),100,IF(OR(E64="United States",E64="USA",E64="US"),IF(J64="Yes",45,75),65))) | Y64: =IF(C64="","",IF(OR(ISNUMBER(SEARCH("Program",C64)),ISNUMBER(SEARCH("Portfolio",C64)),ISNUMBER(SEARCH("Operations",C64)),ISNUMBER(SEARCH("Transformation",C64))),85,IF(ISNUMBER(SEARCH("Product Manager",C64)),55,70))) | Z64: =IF(C64="","",MIN(100,IF(I64<>"",60,10)+IF(AA64>0,MIN(40,AA64*20),0))) | AA64: =IF(T64="","",ROUND(T64*25%+U64*15%+V64*10%+W64*15%+X64*15%+Y64*10%+Z64*10%,0)) | AB64: =IF(AA64="","",IF(X64<50,"Selective / Barrier",IF(AA64>=80,"Tier 1 - Pursue",IF(AA64>=70,"Tier 2 - Pursue",IF(AA64>=60,"Tier 3 - Selective","Do Not Pursue"))))) | AC64: =IF(C64="","",IF(I64<>"","Named Contact",IF(AA64>0,"Outreach Logged","Cold"))) | AD64: =IF(B64="","",COUNTIF('Outreach Log'!$C:$C,B64)) | AE64: =IF(A64="","",IF(OR(K64="Rejected",K64="Closed"),IF(L64<>"",L64-A64,TODAY()-A64),TODAY()-A64)) | AF64: =IF(C64="","",IF(AND(AA64>=70,AC64="Cold"),"High-fit but cold",IF(AND(AA64<60,K64="Applied"),"Low-fit application",IF(AND(AA64>=70,OR(AC64="Named Contact",AC64="Outreach Logged")),"Targeted pursuit","Review"))))
A65: 46070 | B65: Hydro One | C65: Finance Manager - Technology | D65: Manager | E65: Canada | F65: Toronto | G65: 50 | H65: Cold Portal | J65: No | K65: Rejected | L65: 46248 | M65: =IF(OR(L17="",A17=""),"",L17-A17) | P65: Rejected 2026-08-14 via Hydro One SuccessFactors. Application was not previously logged in tracker; original apply date unknown. Role surfaced via saved job agent at jobs.hydroone.com. ROLE PATTERN (Hydro One Finance/Technology manager postings): bridges finance, engineering, and technology stakeholders; budget/cost analysis, financial reporting for tech initiatives, cross-functional influence without formal authority. STRENGTHS: cross-functional influence, Bell TCO cost-model/stakeholder experience (finance, procurement, accounting) is directly relevant. GAPS: role is Finance-Manager-titled, not Program/Portfolio-Manager-titled — may screen for finance credentials (CPA/accounting background) Elena does not hold; utility/regulated-energy sector domain not previously evidenced. | Date Applied confirmed 2026-02-17 via Hydro One confirmation email (Req ID: 51042). | T65: =IF(G65="","",G65) | U65: =IF(C65="","",IF(OR(ISNUMBER(SEARCH("Director",C65)),ISNUMBER(SEARCH("Lead",C65)),ISNUMBER(SEARCH("Senior",C65)),ISNUMBER(SEARCH("Sr.",C65))),90,IF(OR(ISNUMBER(SEARCH("Manager",C65)),ISNUMBER(SEARCH("Program",C65)),ISNUMBER(SEARCH("Portfolio",C65))),80,60))) | V65: =IF(C65="","",IF(OR(ISNUMBER(SEARCH("AI",C65)),ISNUMBER(SEARCH("Data",C65)),ISNUMBER(SEARCH("Technology",C65)),ISNUMBER(SEARCH("Technical",C65)),ISNUMBER(SEARCH("Engineering",C65)),ISNUMBER(SEARCH("Platform",C65)),ISNUMBER(SEARCH("Portfolio",C65))),85,65)) | W65: =IF(C65="","",MIN(100,50+IF(S65<>"",25,0)+IF(R65<>"",15,0)+IF(P65<>"",10,0))) | X65: =IF(E65="","",IF(OR(E65="Canada",E65="CA"),100,IF(OR(E65="United States",E65="USA",E65="US"),IF(J65="Yes",45,75),65))) | Y65: =IF(C65="","",IF(OR(ISNUMBER(SEARCH("Program",C65)),ISNUMBER(SEARCH("Portfolio",C65)),ISNUMBER(SEARCH("Operations",C65)),ISNUMBER(SEARCH("Transformation",C65))),85,IF(ISNUMBER(SEARCH("Product Manager",C65)),55,70))) | Z65: =IF(C65="","",MIN(100,IF(I65<>"",60,10)+IF(AA65>0,MIN(40,AA65*20),0))) | AA65: =IF(T65="","",ROUND(T65*25%+U65*15%+V65*10%+W65*15%+X65*15%+Y65*10%+Z65*10%,0)) | AB65: =IF(AA65="","",IF(X65<50,"Selective / Barrier",IF(AA65>=80,"Tier 1 - Pursue",IF(AA65>=70,"Tier 2 - Pursue",IF(AA65>=60,"Tier 3 - Selective","Do Not Pursue"))))) | AC65: =IF(C65="","",IF(I65<>"","Named Contact",IF(AA65>0,"Outreach Logged","Cold"))) | AD65: =IF(B65="","",COUNTIF('Outreach Log'!$C:$C,B65)) | AE65: =IF(A65="","",IF(OR(K65="Rejected",K65="Closed"),IF(L65<>"",L65-A65,TODAY()-A65),TODAY()-A65)) | AF65: =IF(C65="","",IF(AND(AA65>=70,AC65="Cold"),"High-fit but cold",IF(AND(AA65<60,K65="Applied"),"Low-fit application",IF(AND(AA65>=70,OR(AC65="Named Contact",AC65="Outreach Logged")),"Targeted pursuit","Review"))))
A66: 46072 | B66: Uber | C66: Senior Strategy and Operations Manager - Consumer Pricing & Insights | D66: Senior | E66: Canada | F66: Toronto, ON | G66: 48 | H66: Cold Portal | J66: No | K66: Rejected | M66: =IF(OR(L18="",A18=""),"",L18-A18) | P66: Applied 2026-02-19, per Uber Oracle Cloud candidate portal (Status: Not Selected). Retroactively logged 2026-09-16 — was missing from tracker entirely. Est. fit score: 48 — Strategy & Operations / Consumer Pricing is a step away from her core Program/Portfolio Management lane, closer to a business-strategy/analytics discipline. | T66: =IF(G66="","",G66) | U66: =IF(C66="","",IF(OR(ISNUMBER(SEARCH("Director",C66)),ISNUMBER(SEARCH("Lead",C66)),ISNUMBER(SEARCH("Senior",C66)),ISNUMBER(SEARCH("Sr.",C66))),90,IF(OR(ISNUMBER(SEARCH("Manager",C66)),ISNUMBER(SEARCH("Program",C66)),ISNUMBER(SEARCH("Portfolio",C66))),80,60))) | V66: =IF(C66="","",IF(OR(ISNUMBER(SEARCH("AI",C66)),ISNUMBER(SEARCH("Data",C66)),ISNUMBER(SEARCH("Technology",C66)),ISNUMBER(SEARCH("Technical",C66)),ISNUMBER(SEARCH("Engineering",C66)),ISNUMBER(SEARCH("Platform",C66)),ISNUMBER(SEARCH("Portfolio",C66))),85,65)) | W66: =IF(C66="","",MIN(100,50+IF(S66<>"",25,0)+IF(R66<>"",15,0)+IF(P66<>"",10,0))) | X66: =IF(E66="","",IF(OR(E66="Canada",E66="CA"),100,IF(OR(E66="United States",E66="USA",E66="US"),IF(J66="Yes",45,75),65))) | Y66: =IF(C66="","",IF(OR(ISNUMBER(SEARCH("Program",C66)),ISNUMBER(SEARCH("Portfolio",C66)),ISNUMBER(SEARCH("Operations",C66)),ISNUMBER(SEARCH("Transformation",C66))),85,IF(ISNUMBER(SEARCH("Product Manager",C66)),55,70))) | Z66: =IF(C66="","",MIN(100,IF(I66<>"",60,10)+IF(AA66>0,MIN(40,AA66*20),0))) | AA66: =IF(T66="","",ROUND(T66*25%+U66*15%+V66*10%+W66*15%+X66*15%+Y66*10%+Z66*10%,0)) | AB66: =IF(AA66="","",IF(X66<50,"Selective / Barrier",IF(AA66>=80,"Tier 1 - Pursue",IF(AA66>=70,"Tier 2 - Pursue",IF(AA66>=60,"Tier 3 - Selective","Do Not Pursue"))))) | AC66: =IF(C66="","",IF(I66<>"","Named Contact",IF(AA66>0,"Outreach Logged","Cold"))) | AD66: =IF(B66="","",COUNTIF('Outreach Log'!$C:$C,B66)) | AE66: =IF(A66="","",IF(OR(K66="Rejected",K66="Closed"),IF(L66<>"",L66-A66,TODAY()-A66),TODAY()-A66)) | AF66: =IF(C66="","",IF(AND(AA66>=70,AC66="Cold"),"High-fit but cold",IF(AND(AA66<60,K66="Applied"),"Low-fit application",IF(AND(AA66>=70,OR(AC66="Named Contact",AC66="Outreach Logged")),"Targeted pursuit","Review"))))
A67: 46073 | B67: Capco | C67: Project Manager - Wealth & Asset Management | D67: Senior/Manager | E67: Canada | F67: Toronto | G67: 66 | H67: Cold Portal | J67: No | K67: Rejected | M67: =IF(OR(L66="",A66=""),"",L66-A66) | P67: Wealth & Asset Management practice, Permanent. Delivers complex change programs for financial services clients: end-to-end project plans, vendor management, cross-functional stakeholder engagement, executive-ready materials. Solid generalist PM fit; scored slightly below other Capco roles due to no direct wealth/asset management domain experience. From Greenhouse portal review; distinct from other Capco applications. Rejected. | R67: Domain mismatch (Wealth/Asset Mgmt) — generalist PM only | S67: Wealth/Asset Mgmt domain PM. End-to-end delivery. Vendor coordination. Executive-ready materials. | T67: =IF(G67="","",G67) | U67: =IF(C67="","",IF(OR(ISNUMBER(SEARCH("Director",C67)),ISNUMBER(SEARCH("Lead",C67)),ISNUMBER(SEARCH("Senior",C67)),ISNUMBER(SEARCH("Sr.",C67))),90,IF(OR(ISNUMBER(SEARCH("Manager",C67)),ISNUMBER(SEARCH("Program",C67)),ISNUMBER(SEARCH("Portfolio",C67))),80,60))) | V67: =IF(C67="","",IF(OR(ISNUMBER(SEARCH("AI",C67)),ISNUMBER(SEARCH("Data",C67)),ISNUMBER(SEARCH("Technology",C67)),ISNUMBER(SEARCH("Technical",C67)),ISNUMBER(SEARCH("Engineering",C67)),ISNUMBER(SEARCH("Platform",C67)),ISNUMBER(SEARCH("Portfolio",C67))),85,65)) | W67: =IF(C67="","",MIN(100,50+IF(S67<>"",25,0)+IF(R67<>"",15,0)+IF(P67<>"",10,0))) | X67: =IF(E67="","",IF(OR(E67="Canada",E67="CA"),100,IF(OR(E67="United States",E67="USA",E67="US"),IF(J67="Yes",45,75),65))) | Y67: =IF(C67="","",IF(OR(ISNUMBER(SEARCH("Program",C67)),ISNUMBER(SEARCH("Portfolio",C67)),ISNUMBER(SEARCH("Operations",C67)),ISNUMBER(SEARCH("Transformation",C67))),85,IF(ISNUMBER(SEARCH("Product Manager",C67)),55,70))) | Z67: =IF(C67="","",MIN(100,IF(I67<>"",60,10)+IF(AA67>0,MIN(40,AA67*20),0))) | AA67: =IF(T67="","",ROUND(T67*25%+U67*15%+V67*10%+W67*15%+X67*15%+Y67*10%+Z67*10%,0)) | AB67: =IF(AA67="","",IF(X67<50,"Selective / Barrier",IF(AA67>=80,"Tier 1 - Pursue",IF(AA67>=70,"Tier 2 - Pursue",IF(AA67>=60,"Tier 3 - Selective","Do Not Pursue"))))) | AC67: =IF(C67="","",IF(I67<>"","Named Contact",IF(AA67>0,"Outreach Logged","Cold"))) | AD67: =IF(B67="","",COUNTIF('Outreach Log'!$C:$C,B67)) | AE67: =IF(A67="","",IF(OR(K67="Rejected",K67="Closed"),IF(L67<>"",L67-A67,TODAY()-A67),TODAY()-A67)) | AF67: =IF(C67="","",IF(AND(AA67>=70,AC67="Cold"),"High-fit but cold",IF(AND(AA67<60,K67="Applied"),"Low-fit application",IF(AND(AA67>=70,OR(AC67="Named Contact",AC67="Outreach Logged")),"Targeted pursuit","Review"))))
A68: 46073 | B68: Figma | C68: Strategic Program Manager | D68: Senior/Manager | E68: US | F68: San Francisco / New York (Remote US eligible) | G68: 58 | H68: Cold Portal | J68: Yes | K68: Rejected | M68: =IF(OR(L67="",A67=""),"",L67-A67) | P68: Strategic right hand to VP of Product Support; leads annual planning process, cross-functional OKR alignment, business cases for strategic initiatives, executive narrative/All Hands content. 6+ years strategic program management / business ops in SaaS required. Moderate fit: strong program leadership and executive communication overlap, but role skews more Chief-of-Staff / business-ops strategy than technical program delivery. $122K-$260K USD base range (SF/NY hub). From Greenhouse portal review. Rejected. | R68: Role-type mismatch (Business-ops/Chief-of-Staff vs. technical TPM) | S68: 6+ yrs strategic program mgmt/biz ops in SaaS. Annual planning, OKRs. Business case building. Executive storytelling/change management. | T68: =IF(G68="","",G68) | U68: =IF(C68="","",IF(OR(ISNUMBER(SEARCH("Director",C68)),ISNUMBER(SEARCH("Lead",C68)),ISNUMBER(SEARCH("Senior",C68)),ISNUMBER(SEARCH("Sr.",C68))),90,IF(OR(ISNUMBER(SEARCH("Manager",C68)),ISNUMBER(SEARCH("Program",C68)),ISNUMBER(SEARCH("Portfolio",C68))),80,60))) | V68: =IF(C68="","",IF(OR(ISNUMBER(SEARCH("AI",C68)),ISNUMBER(SEARCH("Data",C68)),ISNUMBER(SEARCH("Technology",C68)),ISNUMBER(SEARCH("Technical",C68)),ISNUMBER(SEARCH("Engineering",C68)),ISNUMBER(SEARCH("Platform",C68)),ISNUMBER(SEARCH("Portfolio",C68))),85,65)) | W68: =IF(C68="","",MIN(100,50+IF(S68<>"",25,0)+IF(R68<>"",15,0)+IF(P68<>"",10,0))) | X68: =IF(E68="","",IF(OR(E68="Canada",E68="CA"),100,IF(OR(E68="United States",E68="USA",E68="US"),IF(J68="Yes",45,75),65))) | Y68: =IF(C68="","",IF(OR(ISNUMBER(SEARCH("Program",C68)),ISNUMBER(SEARCH("Portfolio",C68)),ISNUMBER(SEARCH("Operations",C68)),ISNUMBER(SEARCH("Transformation",C68))),85,IF(ISNUMBER(SEARCH("Product Manager",C68)),55,70))) | Z68: =IF(C68="","",MIN(100,IF(I68<>"",60,10)+IF(AA68>0,MIN(40,AA68*20),0))) | AA68: =IF(T68="","",ROUND(T68*25%+U68*15%+V68*10%+W68*15%+X68*15%+Y68*10%+Z68*10%,0)) | AB68: =IF(AA68="","",IF(X68<50,"Selective / Barrier",IF(AA68>=80,"Tier 1 - Pursue",IF(AA68>=70,"Tier 2 - Pursue",IF(AA68>=60,"Tier 3 - Selective","Do Not Pursue"))))) | AC68: =IF(C68="","",IF(I68<>"","Named Contact",IF(AA68>0,"Outreach Logged","Cold"))) | AD68: =IF(B68="","",COUNTIF('Outreach Log'!$C:$C,B68)) | AE68: =IF(A68="","",IF(OR(K68="Rejected",K68="Closed"),IF(L68<>"",L68-A68,TODAY()-A68),TODAY()-A68)) | AF68: =IF(C68="","",IF(AND(AA68>=70,AC68="Cold"),"High-fit but cold",IF(AND(AA68<60,K68="Applied"),"Low-fit application",IF(AND(AA68>=70,OR(AC68="Named Contact",AC68="Outreach Logged")),"Targeted pursuit","Review"))))
A69: 46073 | B69: Compass | C69: Senior Technical Program Manager | D69: Senior | E69: US | F69: New York City | G69: 66 | H69: Cold Portal | J69: Yes | K69: Rejected | M69: =IF(OR(L68="",A68=""),"",L68-A68) | P69: Leads cross-org Mobile Engineering initiatives (Agent/Client-facing features), owns program lifecycle, KPIs, and executive narratives across BOS/NY/DC/Seattle. Requires BS/MS CS, 5+ years TPM in high-pace tech, hands-on familiarity with AWS/cloud architecture, containerization, CI/CD. Moderate fit: strong program leadership overlap but role skews toward mobile/consumer tech engineering depth outside core enterprise data/AI background. From Greenhouse portal review. Rejected. | R69: Technical depth gap (mobile eng/AWS/containerization) | S69: BS/MS CS. 5+ yrs TPM high-pace tech. AWS/cloud, containerization, CI/CD, microservices. Security frameworks. | T69: =IF(G69="","",G69) | U69: =IF(C69="","",IF(OR(ISNUMBER(SEARCH("Director",C69)),ISNUMBER(SEARCH("Lead",C69)),ISNUMBER(SEARCH("Senior",C69)),ISNUMBER(SEARCH("Sr.",C69))),90,IF(OR(ISNUMBER(SEARCH("Manager",C69)),ISNUMBER(SEARCH("Program",C69)),ISNUMBER(SEARCH("Portfolio",C69))),80,60))) | V69: =IF(C69="","",IF(OR(ISNUMBER(SEARCH("AI",C69)),ISNUMBER(SEARCH("Data",C69)),ISNUMBER(SEARCH("Technology",C69)),ISNUMBER(SEARCH("Technical",C69)),ISNUMBER(SEARCH("Engineering",C69)),ISNUMBER(SEARCH("Platform",C69)),ISNUMBER(SEARCH("Portfolio",C69))),85,65)) | W69: =IF(C69="","",MIN(100,50+IF(S69<>"",25,0)+IF(R69<>"",15,0)+IF(P69<>"",10,0))) | X69: =IF(E69="","",IF(OR(E69="Canada",E69="CA"),100,IF(OR(E69="United States",E69="USA",E69="US"),IF(J69="Yes",45,75),65))) | Y69: =IF(C69="","",IF(OR(ISNUMBER(SEARCH("Program",C69)),ISNUMBER(SEARCH("Portfolio",C69)),ISNUMBER(SEARCH("Operations",C69)),ISNUMBER(SEARCH("Transformation",C69))),85,IF(ISNUMBER(SEARCH("Product Manager",C69)),55,70))) | Z69: =IF(C69="","",MIN(100,IF(I69<>"",60,10)+IF(AA69>0,MIN(40,AA69*20),0))) | AA69: =IF(T69="","",ROUND(T69*25%+U69*15%+V69*10%+W69*15%+X69*15%+Y69*10%+Z69*10%,0)) | AB69: =IF(AA69="","",IF(X69<50,"Selective / Barrier",IF(AA69>=80,"Tier 1 - Pursue",IF(AA69>=70,"Tier 2 - Pursue",IF(AA69>=60,"Tier 3 - Selective","Do Not Pursue"))))) | AC69: =IF(C69="","",IF(I69<>"","Named Contact",IF(AA69>0,"Outreach Logged","Cold"))) | AD69: =IF(B69="","",COUNTIF('Outreach Log'!$C:$C,B69)) | AE69: =IF(A69="","",IF(OR(K69="Rejected",K69="Closed"),IF(L69<>"",L69-A69,TODAY()-A69),TODAY()-A69)) | AF69: =IF(C69="","",IF(AND(AA69>=70,AC69="Cold"),"High-fit but cold",IF(AND(AA69<60,K69="Applied"),"Low-fit application",IF(AND(AA69>=70,OR(AC69="Named Contact",AC69="Outreach Logged")),"Targeted pursuit","Review"))))
A70: 46073 | B70: Robinhood | C70: Staff Technical Program Manager | D70: Senior/Staff (IC6) | E70: US | F70: Menlo Park, CA / New York, NY | G70: 63 | H70: Cold Portal | J70: Yes | K70: Rejected | M70: =IF(OR(L69="",A69=""),"",L69-A69) | P70: Brokerage Technical Program Management team; leads programs on system performance, observability, automation for core brokerage infrastructure. 5+ years leading complex technical/engineering programs; requires deep system architecture fluency and in-office 3 days/week. Moderate fit: strong program leadership overlap but role demands hands-on distributed-systems technical depth beyond enterprise data/AI portfolio background. From Greenhouse portal review. Rejected. | R70: Technical depth gap (distributed systems architecture) | S70: 5+ yrs leading complex technical/eng programs. System architecture fluency. Distributed systems. In-office 3 days/wk. | T70: =IF(G70="","",G70) | U70: =IF(C70="","",IF(OR(ISNUMBER(SEARCH("Director",C70)),ISNUMBER(SEARCH("Lead",C70)),ISNUMBER(SEARCH("Senior",C70)),ISNUMBER(SEARCH("Sr.",C70))),90,IF(OR(ISNUMBER(SEARCH("Manager",C70)),ISNUMBER(SEARCH("Program",C70)),ISNUMBER(SEARCH("Portfolio",C70))),80,60))) | V70: =IF(C70="","",IF(OR(ISNUMBER(SEARCH("AI",C70)),ISNUMBER(SEARCH("Data",C70)),ISNUMBER(SEARCH("Technology",C70)),ISNUMBER(SEARCH("Technical",C70)),ISNUMBER(SEARCH("Engineering",C70)),ISNUMBER(SEARCH("Platform",C70)),ISNUMBER(SEARCH("Portfolio",C70))),85,65)) | W70: =IF(C70="","",MIN(100,50+IF(S70<>"",25,0)+IF(R70<>"",15,0)+IF(P70<>"",10,0))) | X70: =IF(E70="","",IF(OR(E70="Canada",E70="CA"),100,IF(OR(E70="United States",E70="USA",E70="US"),IF(J70="Yes",45,75),65))) | Y70: =IF(C70="","",IF(OR(ISNUMBER(SEARCH("Program",C70)),ISNUMBER(SEARCH("Portfolio",C70)),ISNUMBER(SEARCH("Operations",C70)),ISNUMBER(SEARCH("Transformation",C70))),85,IF(ISNUMBER(SEARCH("Product Manager",C70)),55,70))) | Z70: =IF(C70="","",MIN(100,IF(I70<>"",60,10)+IF(AA70>0,MIN(40,AA70*20),0))) | AA70: =IF(T70="","",ROUND(T70*25%+U70*15%+V70*10%+W70*15%+X70*15%+Y70*10%+Z70*10%,0)) | AB70: =IF(AA70="","",IF(X70<50,"Selective / Barrier",IF(AA70>=80,"Tier 1 - Pursue",IF(AA70>=70,"Tier 2 - Pursue",IF(AA70>=60,"Tier 3 - Selective","Do Not Pursue"))))) | AC70: =IF(C70="","",IF(I70<>"","Named Contact",IF(AA70>0,"Outreach Logged","Cold"))) | AD70: =IF(B70="","",COUNTIF('Outreach Log'!$C:$C,B70)) | AE70: =IF(A70="","",IF(OR(K70="Rejected",K70="Closed"),IF(L70<>"",L70-A70,TODAY()-A70),TODAY()-A70)) | AF70: =IF(C70="","",IF(AND(AA70>=70,AC70="Cold"),"High-fit but cold",IF(AND(AA70<60,K70="Applied"),"Low-fit application",IF(AND(AA70>=70,OR(AC70="Named Contact",AC70="Outreach Logged")),"Targeted pursuit","Review"))))
A71: 46073 | B71: Stripe | C71: Manager, Support Process Program Managers | D71: Senior Manager (people manager) | E71: US | F71: Remote | G71: 58 | H71: Cold Portal | J71: Yes | K71: Rejected | M71: =IF(OR(L70="",A70=""),"",L70-A70) | P71: From Greenhouse portal: 'Applied 7 months ago'; distinct from Stripe Design Program Manager, AI already logged; title cut off; date approximate | User confirmed rejected (Sep 20, 2026). | Manages team of 5-8 program managers within Support org; owns Launch Readiness, Quality, Knowledge Management programs. Requires 10+ years ops/support/strategy&ops, 5+ years managing PMs directly. Moderate fit: strong program leadership but role centers on people-managing a PM team within customer support ops, a narrower fit than broader enterprise TPM/portfolio work. From Greenhouse portal review. Rejected. | R71: Role-type mismatch (people-manages PM team vs. broad TPM) | S71: 10+ yrs ops/support/strategy&ops/consulting. 5+ yrs managing PM teams (5-8 direct reports). Support process ownership (QA, Launch Readiness). | T71: =IF(G71="","",G71) | U71: =IF(C71="","",IF(OR(ISNUMBER(SEARCH("Director",C71)),ISNUMBER(SEARCH("Lead",C71)),ISNUMBER(SEARCH("Senior",C71)),ISNUMBER(SEARCH("Sr.",C71))),90,IF(OR(ISNUMBER(SEARCH("Manager",C71)),ISNUMBER(SEARCH("Program",C71)),ISNUMBER(SEARCH("Portfolio",C71))),80,60))) | V71: =IF(C71="","",IF(OR(ISNUMBER(SEARCH("AI",C71)),ISNUMBER(SEARCH("Data",C71)),ISNUMBER(SEARCH("Technology",C71)),ISNUMBER(SEARCH("Technical",C71)),ISNUMBER(SEARCH("Engineering",C71)),ISNUMBER(SEARCH("Platform",C71)),ISNUMBER(SEARCH("Portfolio",C71))),85,65)) | W71: =IF(C71="","",MIN(100,50+IF(S71<>"",25,0)+IF(R71<>"",15,0)+IF(P71<>"",10,0))) | X71: =IF(E71="","",IF(OR(E71="Canada",E71="CA"),100,IF(OR(E71="United States",E71="USA",E71="US"),IF(J71="Yes",45,75),65))) | Y71: =IF(C71="","",IF(OR(ISNUMBER(SEARCH("Program",C71)),ISNUMBER(SEARCH("Portfolio",C71)),ISNUMBER(SEARCH("Operations",C71)),ISNUMBER(SEARCH("Transformation",C71))),85,IF(ISNUMBER(SEARCH("Product Manager",C71)),55,70))) | Z71: =IF(C71="","",MIN(100,IF(I71<>"",60,10)+IF(AA71>0,MIN(40,AA71*20),0))) | AA71: =IF(T71="","",ROUND(T71*25%+U71*15%+V71*10%+W71*15%+X71*15%+Y71*10%+Z71*10%,0)) | AB71: =IF(AA71="","",IF(X71<50,"Selective / Barrier",IF(AA71>=80,"Tier 1 - Pursue",IF(AA71>=70,"Tier 2 - Pursue",IF(AA71>=60,"Tier 3 - Selective","Do Not Pursue"))))) | AC71: =IF(C71="","",IF(I71<>"","Named Contact",IF(AA71>0,"Outreach Logged","Cold"))) | AD71: =IF(B71="","",COUNTIF('Outreach Log'!$C:$C,B71)) | AE71: =IF(A71="","",IF(OR(K71="Rejected",K71="Closed"),IF(L71<>"",L71-A71,TODAY()-A71),TODAY()-A71)) | AF71: =IF(C71="","",IF(AND(AA71>=70,AC71="Cold"),"High-fit but cold",IF(AND(AA71<60,K71="Applied"),"Low-fit application",IF(AND(AA71>=70,OR(AC71="Named Contact",AC71="Outreach Logged")),"Targeted pursuit","Review"))))
A72: 46073 | B72: Clutch Technologies Inc. | C72: Project Manager | D72: Senior | E72: Canada | F72: Mississauga, ON | G72: 62 | H72: Cold Portal | J72: No | K72: Rejected | M72: =IF(OR(L71="",A71=""),"",L71-A71) | P72: Canada's largest online used car retailer. Leads complex cross-functional operational initiatives spanning operations, engineering, and business teams; 5+ years PM, preferably manufacturing/complex ops/logistics background. Moderate fit: strong general PM and cross-functional delivery skills, but role is operations/logistics-domain focused rather than tech/data program management. From Greenhouse portal review. Rejected. | R72: Industry mismatch (operations/logistics/retail vs. tech) | S72: 5+ yrs PM, preferably manufacturing/logistics/complex ops. Multi-stakeholder ops projects. PM tools (Asana/Jira/Smartsheet). | T72: =IF(G72="","",G72) | U72: =IF(C72="","",IF(OR(ISNUMBER(SEARCH("Director",C72)),ISNUMBER(SEARCH("Lead",C72)),ISNUMBER(SEARCH("Senior",C72)),ISNUMBER(SEARCH("Sr.",C72))),90,IF(OR(ISNUMBER(SEARCH("Manager",C72)),ISNUMBER(SEARCH("Program",C72)),ISNUMBER(SEARCH("Portfolio",C72))),80,60))) | V72: =IF(C72="","",IF(OR(ISNUMBER(SEARCH("AI",C72)),ISNUMBER(SEARCH("Data",C72)),ISNUMBER(SEARCH("Technology",C72)),ISNUMBER(SEARCH("Technical",C72)),ISNUMBER(SEARCH("Engineering",C72)),ISNUMBER(SEARCH("Platform",C72)),ISNUMBER(SEARCH("Portfolio",C72))),85,65)) | W72: =IF(C72="","",MIN(100,50+IF(S72<>"",25,0)+IF(R72<>"",15,0)+IF(P72<>"",10,0))) | X72: =IF(E72="","",IF(OR(E72="Canada",E72="CA"),100,IF(OR(E72="United States",E72="USA",E72="US"),IF(J72="Yes",45,75),65))) | Y72: =IF(C72="","",IF(OR(ISNUMBER(SEARCH("Program",C72)),ISNUMBER(SEARCH("Portfolio",C72)),ISNUMBER(SEARCH("Operations",C72)),ISNUMBER(SEARCH("Transformation",C72))),85,IF(ISNUMBER(SEARCH("Product Manager",C72)),55,70))) | Z72: =IF(C72="","",MIN(100,IF(I72<>"",60,10)+IF(AA72>0,MIN(40,AA72*20),0))) | AA72: =IF(T72="","",ROUND(T72*25%+U72*15%+V72*10%+W72*15%+X72*15%+Y72*10%+Z72*10%,0)) | AB72: =IF(AA72="","",IF(X72<50,"Selective / Barrier",IF(AA72>=80,"Tier 1 - Pursue",IF(AA72>=70,"Tier 2 - Pursue",IF(AA72>=60,"Tier 3 - Selective","Do Not Pursue"))))) | AC72: =IF(C72="","",IF(I72<>"","Named Contact",IF(AA72>0,"Outreach Logged","Cold"))) | AD72: =IF(B72="","",COUNTIF('Outreach Log'!$C:$C,B72)) | AE72: =IF(A72="","",IF(OR(K72="Rejected",K72="Closed"),IF(L72<>"",L72-A72,TODAY()-A72),TODAY()-A72)) | AF72: =IF(C72="","",IF(AND(AA72>=70,AC72="Cold"),"High-fit but cold",IF(AND(AA72<60,K72="Applied"),"Low-fit application",IF(AND(AA72>=70,OR(AC72="Named Contact",AC72="Outreach Logged")),"Targeted pursuit","Review"))))
A73: 46073 | B73: Dropbox | C73: Senior Strategy & Operations Program Manager | D73: Senior IC | E73: Canada | F73: Remote - Canada (Select locations) | G73: 75 | H73: Cold Portal | J73: No | K73: Rejected | M73: =IF(OR(L72="",A72=""),"",L72-A72) | P73: Small high-impact team partnering with Product/Eng/Design/GTM/Exec leadership on strategy, operating cadence (goals, QBRs, roadmap reviews), and cross-functional execution. 10+ years program management/biz ops/strategy at high-growth SaaS company. Strong fit: closely mirrors enterprise portfolio/program leadership and executive-facing strategic delivery background. Pay range $178,500-$241,500 CAD. From Greenhouse portal review. Rejected. | R73: Strong fit — executive strategy/program leadership match | S73: 10+ yrs program mgmt/biz ops/strategy at high-growth SaaS. Operating cadence design (goals, QBRs). Data tools (Tableau/Amplitude). | T73: =IF(G73="","",G73) | U73: =IF(C73="","",IF(OR(ISNUMBER(SEARCH("Director",C73)),ISNUMBER(SEARCH("Lead",C73)),ISNUMBER(SEARCH("Senior",C73)),ISNUMBER(SEARCH("Sr.",C73))),90,IF(OR(ISNUMBER(SEARCH("Manager",C73)),ISNUMBER(SEARCH("Program",C73)),ISNUMBER(SEARCH("Portfolio",C73))),80,60))) | V73: =IF(C73="","",IF(OR(ISNUMBER(SEARCH("AI",C73)),ISNUMBER(SEARCH("Data",C73)),ISNUMBER(SEARCH("Technology",C73)),ISNUMBER(SEARCH("Technical",C73)),ISNUMBER(SEARCH("Engineering",C73)),ISNUMBER(SEARCH("Platform",C73)),ISNUMBER(SEARCH("Portfolio",C73))),85,65)) | W73: =IF(C73="","",MIN(100,50+IF(S73<>"",25,0)+IF(R73<>"",15,0)+IF(P73<>"",10,0))) | X73: =IF(E73="","",IF(OR(E73="Canada",E73="CA"),100,IF(OR(E73="United States",E73="USA",E73="US"),IF(J73="Yes",45,75),65))) | Y73: =IF(C73="","",IF(OR(ISNUMBER(SEARCH("Program",C73)),ISNUMBER(SEARCH("Portfolio",C73)),ISNUMBER(SEARCH("Operations",C73)),ISNUMBER(SEARCH("Transformation",C73))),85,IF(ISNUMBER(SEARCH("Product Manager",C73)),55,70))) | Z73: =IF(C73="","",MIN(100,IF(I73<>"",60,10)+IF(AA73>0,MIN(40,AA73*20),0))) | AA73: =IF(T73="","",ROUND(T73*25%+U73*15%+V73*10%+W73*15%+X73*15%+Y73*10%+Z73*10%,0)) | AB73: =IF(AA73="","",IF(X73<50,"Selective / Barrier",IF(AA73>=80,"Tier 1 - Pursue",IF(AA73>=70,"Tier 2 - Pursue",IF(AA73>=60,"Tier 3 - Selective","Do Not Pursue"))))) | AC73: =IF(C73="","",IF(I73<>"","Named Contact",IF(AA73>0,"Outreach Logged","Cold"))) | AD73: =IF(B73="","",COUNTIF('Outreach Log'!$C:$C,B73)) | AE73: =IF(A73="","",IF(OR(K73="Rejected",K73="Closed"),IF(L73<>"",L73-A73,TODAY()-A73),TODAY()-A73)) | AF73: =IF(C73="","",IF(AND(AA73>=70,AC73="Cold"),"High-fit but cold",IF(AND(AA73<60,K73="Applied"),"Low-fit application",IF(AND(AA73>=70,OR(AC73="Named Contact",AC73="Outreach Logged")),"Targeted pursuit","Review"))))
A74: 46073 | B74: Stripe | C74: Program Manager, Enterprise Servicing | D74: Senior | E74: US | F74: US (Remote-eligible) | G74: 66 | H74: Cold Portal | J74: Yes | K74: Rejected | M74: =IF(OR(L73="",A73=""),"",L73-A73) | P74: From Greenhouse portal: 'Applied 7 months ago'; third distinct Stripe application (also has Design Program Manager AI and Manager Support Process Program Managers logged); title cut off; date approximate | User confirmed rejected (Sep 20, 2026). | Customer Advocacy & Programs team; owns Enterprise Servicing program for Stripe's largest customers end-to-end (strategy, cross-functional alignment, execution, measurement) with CS/TAM/GTM/Product/Ops/Finance/Legal. 5+ years PM/biz ops/consulting. Good fit: strong program ownership and cross-functional stakeholder management overlap. From Greenhouse portal review. Rejected. | R74: Good fit — cross-functional program ownership | S74: 5+ yrs PM/biz ops/consulting. Enterprise customer post-sales program design. Cross-functional (CS/TAM/GTM/Product/Ops/Finance/Legal). | T74: =IF(G74="","",G74) | U74: =IF(C74="","",IF(OR(ISNUMBER(SEARCH("Director",C74)),ISNUMBER(SEARCH("Lead",C74)),ISNUMBER(SEARCH("Senior",C74)),ISNUMBER(SEARCH("Sr.",C74))),90,IF(OR(ISNUMBER(SEARCH("Manager",C74)),ISNUMBER(SEARCH("Program",C74)),ISNUMBER(SEARCH("Portfolio",C74))),80,60))) | V74: =IF(C74="","",IF(OR(ISNUMBER(SEARCH("AI",C74)),ISNUMBER(SEARCH("Data",C74)),ISNUMBER(SEARCH("Technology",C74)),ISNUMBER(SEARCH("Technical",C74)),ISNUMBER(SEARCH("Engineering",C74)),ISNUMBER(SEARCH("Platform",C74)),ISNUMBER(SEARCH("Portfolio",C74))),85,65)) | W74: =IF(C74="","",MIN(100,50+IF(S74<>"",25,0)+IF(R74<>"",15,0)+IF(P74<>"",10,0))) | X74: =IF(E74="","",IF(OR(E74="Canada",E74="CA"),100,IF(OR(E74="United States",E74="USA",E74="US"),IF(J74="Yes",45,75),65))) | Y74: =IF(C74="","",IF(OR(ISNUMBER(SEARCH("Program",C74)),ISNUMBER(SEARCH("Portfolio",C74)),ISNUMBER(SEARCH("Operations",C74)),ISNUMBER(SEARCH("Transformation",C74))),85,IF(ISNUMBER(SEARCH("Product Manager",C74)),55,70))) | Z74: =IF(C74="","",MIN(100,IF(I74<>"",60,10)+IF(AA74>0,MIN(40,AA74*20),0))) | AA74: =IF(T74="","",ROUND(T74*25%+U74*15%+V74*10%+W74*15%+X74*15%+Y74*10%+Z74*10%,0)) | AB74: =IF(AA74="","",IF(X74<50,"Selective / Barrier",IF(AA74>=80,"Tier 1 - Pursue",IF(AA74>=70,"Tier 2 - Pursue",IF(AA74>=60,"Tier 3 - Selective","Do Not Pursue"))))) | AC74: =IF(C74="","",IF(I74<>"","Named Contact",IF(AA74>0,"Outreach Logged","Cold"))) | AD74: =IF(B74="","",COUNTIF('Outreach Log'!$C:$C,B74)) | AE74: =IF(A74="","",IF(OR(K74="Rejected",K74="Closed"),IF(L74<>"",L74-A74,TODAY()-A74),TODAY()-A74)) | AF74: =IF(C74="","",IF(AND(AA74>=70,AC74="Cold"),"High-fit but cold",IF(AND(AA74<60,K74="Applied"),"Low-fit application",IF(AND(AA74>=70,OR(AC74="Named Contact",AC74="Outreach Logged")),"Targeted pursuit","Review"))))
A75: 46073 | B75: Stripe | C75: Strategy & Business Operations, Stripe Business Performance | D75: Senior/Principal | E75: US | F75: San Francisco / Seattle / Chicago / New York / US-Remote | G75: 60 | H75: Cold Portal | J75: Yes | K75: Rejected | M75: =IF(OR(L74="",A74=""),"",L74-A74) | P75: From Greenhouse portal: 'Applied 7 months ago'; fourth distinct Stripe application (also has Design Program Manager AI, Manager Support Process Program Managers, Program Manager Enterprise Servicing logged); date approximate | User confirmed rejected (Sep 20, 2026). | Strategy & Business Performance team, close partnership with exec team on 3-year strategy and annual planning; heavy data analytics/SQL and financial modeling focus. Requires 12+ years strategy & ops/data science/finance/PM at tech companies. Moderate fit: strong strategic program experience but role weights quantitative data-science/SQL analysis more heavily than program delivery. From Greenhouse portal review. Rejected. | R75: Skill-weighting mismatch (SQL/data-science heavy vs. program delivery) | S75: 12+ yrs strategy&ops/data science/finance/PM at tech cos. Heavy SQL/data analytics. Exec-level strategy partnership. | T75: =IF(G75="","",G75) | U75: =IF(C75="","",IF(OR(ISNUMBER(SEARCH("Director",C75)),ISNUMBER(SEARCH("Lead",C75)),ISNUMBER(SEARCH("Senior",C75)),ISNUMBER(SEARCH("Sr.",C75))),90,IF(OR(ISNUMBER(SEARCH("Manager",C75)),ISNUMBER(SEARCH("Program",C75)),ISNUMBER(SEARCH("Portfolio",C75))),80,60))) | V75: =IF(C75="","",IF(OR(ISNUMBER(SEARCH("AI",C75)),ISNUMBER(SEARCH("Data",C75)),ISNUMBER(SEARCH("Technology",C75)),ISNUMBER(SEARCH("Technical",C75)),ISNUMBER(SEARCH("Engineering",C75)),ISNUMBER(SEARCH("Platform",C75)),ISNUMBER(SEARCH("Portfolio",C75))),85,65)) | W75: =IF(C75="","",MIN(100,50+IF(S75<>"",25,0)+IF(R75<>"",15,0)+IF(P75<>"",10,0))) | X75: =IF(E75="","",IF(OR(E75="Canada",E75="CA"),100,IF(OR(E75="United States",E75="USA",E75="US"),IF(J75="Yes",45,75),65))) | Y75: =IF(C75="","",IF(OR(ISNUMBER(SEARCH("Program",C75)),ISNUMBER(SEARCH("Portfolio",C75)),ISNUMBER(SEARCH("Operations",C75)),ISNUMBER(SEARCH("Transformation",C75))),85,IF(ISNUMBER(SEARCH("Product Manager",C75)),55,70))) | Z75: =IF(C75="","",MIN(100,IF(I75<>"",60,10)+IF(AA75>0,MIN(40,AA75*20),0))) | AA75: =IF(T75="","",ROUND(T75*25%+U75*15%+V75*10%+W75*15%+X75*15%+Y75*10%+Z75*10%,0)) | AB75: =IF(AA75="","",IF(X75<50,"Selective / Barrier",IF(AA75>=80,"Tier 1 - Pursue",IF(AA75>=70,"Tier 2 - Pursue",IF(AA75>=60,"Tier 3 - Selective","Do Not Pursue"))))) | AC75: =IF(C75="","",IF(I75<>"","Named Contact",IF(AA75>0,"Outreach Logged","Cold"))) | AD75: =IF(B75="","",COUNTIF('Outreach Log'!$C:$C,B75)) | AE75: =IF(A75="","",IF(OR(K75="Rejected",K75="Closed"),IF(L75<>"",L75-A75,TODAY()-A75),TODAY()-A75)) | AF75: =IF(C75="","",IF(AND(AA75>=70,AC75="Cold"),"High-fit but cold",IF(AND(AA75<60,K75="Applied"),"Low-fit application",IF(AND(AA75>=70,OR(AC75="Named Contact",AC75="Outreach Logged")),"Targeted pursuit","Review"))))
A76: 46073 | B76: Lyft | C76: Manager, Global IT Support & Operations | E76: Canada | F76: Toronto | J76: No | K76: Rejected | P76: From Greenhouse portal: 'Applied 7 months ago' (Toronto, Canada); distinct from Lyft Senior Program Manager (Tech) already logged; date approximate | User confirmed rejected (Sep 20, 2026). | R76: Not yet analyzed — pending role description | T76: =IF(G76="","",G76) | U76: =IF(C76="","",IF(OR(ISNUMBER(SEARCH("Director",C76)),ISNUMBER(SEARCH("Lead",C76)),ISNUMBER(SEARCH("Senior",C76)),ISNUMBER(SEARCH("Sr.",C76))),90,IF(OR(ISNUMBER(SEARCH("Manager",C76)),ISNUMBER(SEARCH("Program",C76)),ISNUMBER(SEARCH("Portfolio",C76))),80,60))) | V76: =IF(C76="","",IF(OR(ISNUMBER(SEARCH("AI",C76)),ISNUMBER(SEARCH("Data",C76)),ISNUMBER(SEARCH("Technology",C76)),ISNUMBER(SEARCH("Technical",C76)),ISNUMBER(SEARCH("Engineering",C76)),ISNUMBER(SEARCH("Platform",C76)),ISNUMBER(SEARCH("Portfolio",C76))),85,65)) | W76: =IF(C76="","",MIN(100,50+IF(S76<>"",25,0)+IF(R76<>"",15,0)+IF(P76<>"",10,0))) | X76: =IF(E76="","",IF(OR(E76="Canada",E76="CA"),100,IF(OR(E76="United States",E76="USA",E76="US"),IF(J76="Yes",45,75),65))) | Y76: =IF(C76="","",IF(OR(ISNUMBER(SEARCH("Program",C76)),ISNUMBER(SEARCH("Portfolio",C76)),ISNUMBER(SEARCH("Operations",C76)),ISNUMBER(SEARCH("Transformation",C76))),85,IF(ISNUMBER(SEARCH("Product Manager",C76)),55,70))) | Z76: =IF(C76="","",MIN(100,IF(I76<>"",60,10)+IF(AA76>0,MIN(40,AA76*20),0))) | AA76: =IF(T76="","",ROUND(T76*25%+U76*15%+V76*10%+W76*15%+X76*15%+Y76*10%+Z76*10%,0)) | AB76: =IF(AA76="","",IF(X76<50,"Selective / Barrier",IF(AA76>=80,"Tier 1 - Pursue",IF(AA76>=70,"Tier 2 - Pursue",IF(AA76>=60,"Tier 3 - Selective","Do Not Pursue"))))) | AC76: =IF(C76="","",IF(I76<>"","Named Contact",IF(AA76>0,"Outreach Logged","Cold"))) | AD76: =IF(B76="","",COUNTIF('Outreach Log'!$C:$C,B76)) | AE76: =IF(A76="","",IF(OR(K76="Rejected",K76="Closed"),IF(L76<>"",L76-A76,TODAY()-A76),TODAY()-A76)) | AF76: =IF(C76="","",IF(AND(AA76>=70,AC76="Cold"),"High-fit but cold",IF(AND(AA76<60,K76="Applied"),"Low-fit application",IF(AND(AA76>=70,OR(AC76="Named Contact",AC76="Outreach Logged")),"Targeted pursuit","Review"))))
A77: 46073 | B77: Five9 | C77: Professional Services Program Manager | D77: Senior | E77: Canada | F77: Remote, Canada (Ontario-based pay range) | G77: 54 | H77: Cold Portal | J77: No | K77: Rejected | M77: =IF(OR(L76="",A76=""),"",L76-A76) | P77: Leads multi-customer Contact Center/AI deployment implementation projects day-to-day. 5+ years PM/Scrum Master/Technical Consultant; Contact Center industry and VoIP/CCaaS platform experience (Genesys, Avaya, Cisco, NICE) highly desired; bilingual English/French required. Lower fit: heavy contact-center/telephony domain specificity (CCaaS, IVR, ACD, dialer) and French-bilingual requirement are the primary gaps versus general enterprise TPM background. Salary $81,200-$150,800 CAD (Ontario). | R77: Industry domain gap (contact center/telephony) + language requirement (French) | S77: 5+ yrs PM/Scrum Master/Tech Consultant. Contact Center/VoIP/CCaaS platform experience (Genesys/Avaya/Cisco/NICE). Bilingual English/French. PMP/PRINCE2/Agile cert preferred. Up to 25% travel. | T77: =IF(G77="","",G77) | U77: =IF(C77="","",IF(OR(ISNUMBER(SEARCH("Director",C77)),ISNUMBER(SEARCH("Lead",C77)),ISNUMBER(SEARCH("Senior",C77)),ISNUMBER(SEARCH("Sr.",C77))),90,IF(OR(ISNUMBER(SEARCH("Manager",C77)),ISNUMBER(SEARCH("Program",C77)),ISNUMBER(SEARCH("Portfolio",C77))),80,60))) | V77: =IF(C77="","",IF(OR(ISNUMBER(SEARCH("AI",C77)),ISNUMBER(SEARCH("Data",C77)),ISNUMBER(SEARCH("Technology",C77)),ISNUMBER(SEARCH("Technical",C77)),ISNUMBER(SEARCH("Engineering",C77)),ISNUMBER(SEARCH("Platform",C77)),ISNUMBER(SEARCH("Portfolio",C77))),85,65)) | W77: =IF(C77="","",MIN(100,50+IF(S77<>"",25,0)+IF(R77<>"",15,0)+IF(P77<>"",10,0))) | X77: =IF(E77="","",IF(OR(E77="Canada",E77="CA"),100,IF(OR(E77="United States",E77="USA",E77="US"),IF(J77="Yes",45,75),65))) | Y77: =IF(C77="","",IF(OR(ISNUMBER(SEARCH("Program",C77)),ISNUMBER(SEARCH("Portfolio",C77)),ISNUMBER(SEARCH("Operations",C77)),ISNUMBER(SEARCH("Transformation",C77))),85,IF(ISNUMBER(SEARCH("Product Manager",C77)),55,70))) | Z77: =IF(C77="","",MIN(100,IF(I77<>"",60,10)+IF(AA77>0,MIN(40,AA77*20),0))) | AA77: =IF(T77="","",ROUND(T77*25%+U77*15%+V77*10%+W77*15%+X77*15%+Y77*10%+Z77*10%,0)) | AB77: =IF(AA77="","",IF(X77<50,"Selective / Barrier",IF(AA77>=80,"Tier 1 - Pursue",IF(AA77>=70,"Tier 2 - Pursue",IF(AA77>=60,"Tier 3 - Selective","Do Not Pursue"))))) | AC77: =IF(C77="","",IF(I77<>"","Named Contact",IF(AA77>0,"Outreach Logged","Cold"))) | AD77: =IF(B77="","",COUNTIF('Outreach Log'!$C:$C,B77)) | AE77: =IF(A77="","",IF(OR(K77="Rejected",K77="Closed"),IF(L77<>"",L77-A77,TODAY()-A77),TODAY()-A77)) | AF77: =IF(C77="","",IF(AND(AA77>=70,AC77="Cold"),"High-fit but cold",IF(AND(AA77<60,K77="Applied"),"Low-fit application",IF(AND(AA77>=70,OR(AC77="Named Contact",AC77="Outreach Logged")),"Targeted pursuit","Review"))))
A78: 46073 | B78: Block | C78: Implementation & Onboarding Program Manager | D78: Mid-level/Entry (customer-facing) | E78: Canada | F78: Toronto, ON | G78: 33 | H78: Cold Portal | J78: No | K78: Rejected | M78: =IF(OR(L77="",A77=""),"",L77-A77) | P78: From Greenhouse portal: 'Applied 7 months ago'; title cut off; date approximate | User confirmed rejected (Sep 20, 2026). | Customer-facing Seller Onboarding role for Square merchants: virtual/onsite merchant training, hardware installation, data entry/account configuration. Only 4-5 years customer-facing experience required, hourly pay (CAD $34.13-$46.97/hr). Low fit: major seniority mismatch (overqualified) and discipline mismatch — this is a hands-on customer implementation specialist role, not senior program/portfolio management. | R78: Seniority mismatch (overqualified, hourly entry/mid-level role) + discipline mismatch | S78: 4-5+ yrs customer-facing implementation/support/account mgmt. Hardware installation. Hourly pay role. Merchant onboarding/POS-payments a plus. | T78: =IF(G78="","",G78) | U78: =IF(C78="","",IF(OR(ISNUMBER(SEARCH("Director",C78)),ISNUMBER(SEARCH("Lead",C78)),ISNUMBER(SEARCH("Senior",C78)),ISNUMBER(SEARCH("Sr.",C78))),90,IF(OR(ISNUMBER(SEARCH("Manager",C78)),ISNUMBER(SEARCH("Program",C78)),ISNUMBER(SEARCH("Portfolio",C78))),80,60))) | V78: =IF(C78="","",IF(OR(ISNUMBER(SEARCH("AI",C78)),ISNUMBER(SEARCH("Data",C78)),ISNUMBER(SEARCH("Technology",C78)),ISNUMBER(SEARCH("Technical",C78)),ISNUMBER(SEARCH("Engineering",C78)),ISNUMBER(SEARCH("Platform",C78)),ISNUMBER(SEARCH("Portfolio",C78))),85,65)) | W78: =IF(C78="","",MIN(100,50+IF(S78<>"",25,0)+IF(R78<>"",15,0)+IF(P78<>"",10,0))) | X78: =IF(E78="","",IF(OR(E78="Canada",E78="CA"),100,IF(OR(E78="United States",E78="USA",E78="US"),IF(J78="Yes",45,75),65))) | Y78: =IF(C78="","",IF(OR(ISNUMBER(SEARCH("Program",C78)),ISNUMBER(SEARCH("Portfolio",C78)),ISNUMBER(SEARCH("Operations",C78)),ISNUMBER(SEARCH("Transformation",C78))),85,IF(ISNUMBER(SEARCH("Product Manager",C78)),55,70))) | Z78: =IF(C78="","",MIN(100,IF(I78<>"",60,10)+IF(AA78>0,MIN(40,AA78*20),0))) | AA78: =IF(T78="","",ROUND(T78*25%+U78*15%+V78*10%+W78*15%+X78*15%+Y78*10%+Z78*10%,0)) | AB78: =IF(AA78="","",IF(X78<50,"Selective / Barrier",IF(AA78>=80,"Tier 1 - Pursue",IF(AA78>=70,"Tier 2 - Pursue",IF(AA78>=60,"Tier 3 - Selective","Do Not Pursue"))))) | AC78: =IF(C78="","",IF(I78<>"","Named Contact",IF(AA78>0,"Outreach Logged","Cold"))) | AD78: =IF(B78="","",COUNTIF('Outreach Log'!$C:$C,B78)) | AE78: =IF(A78="","",IF(OR(K78="Rejected",K78="Closed"),IF(L78<>"",L78-A78,TODAY()-A78),TODAY()-A78)) | AF78: =IF(C78="","",IF(AND(AA78>=70,AC78="Cold"),"High-fit but cold",IF(AND(AA78<60,K78="Applied"),"Low-fit application",IF(AND(AA78>=70,OR(AC78="Named Contact",AC78="Outreach Logged")),"Targeted pursuit","Review"))))
A79: 46073 | B79: Rubrik Job Board | C79: Manager, Project Management Office (PMO Manager) | D79: Manager | E79: US | F79: US-Remote | G79: 76 | H79: Cold Portal | J79: Yes | K79: Rejected | M79: =IF(OR(L79="",A79=""),"",L79-A79) | P79: From Greenhouse portal: 'Applied 7 months ago'; title cut off; date approximate | User confirmed rejected (Sep 20, 2026). | Builds/leads PMO function at security/AI ops company; owns governance/methodology, portfolio oversight, resource management, executive dashboards, PM mentorship. 5+ years program mgmt, 3+ years specifically leading/building a PMO; PMI-PMOCP/PMP/PRINCE2/MSP certs preferred; PPM tools (Jira/Asana/Monday). Strong fit: closely mirrors enterprise portfolio governance and PMO-building background; specific certification (PMP/PMOCP) may be the main gap if not held. Base pay $140,000-$210,100 USD. | R79: Strong fit — certification (PMP/PMOCP) may be the main gap | S79: 5+ yrs PM, 3+ yrs building/leading a PMO. PMI-PMOCP/PMP/PRINCE2/MSP certs preferred. PPM tools (Jira/Asana/Monday). Executive dashboards/reporting. PM mentorship. | T79: =IF(G79="","",G79) | U79: =IF(C79="","",IF(OR(ISNUMBER(SEARCH("Director",C79)),ISNUMBER(SEARCH("Lead",C79)),ISNUMBER(SEARCH("Senior",C79)),ISNUMBER(SEARCH("Sr.",C79))),90,IF(OR(ISNUMBER(SEARCH("Manager",C79)),ISNUMBER(SEARCH("Program",C79)),ISNUMBER(SEARCH("Portfolio",C79))),80,60))) | V79: =IF(C79="","",IF(OR(ISNUMBER(SEARCH("AI",C79)),ISNUMBER(SEARCH("Data",C79)),ISNUMBER(SEARCH("Technology",C79)),ISNUMBER(SEARCH("Technical",C79)),ISNUMBER(SEARCH("Engineering",C79)),ISNUMBER(SEARCH("Platform",C79)),ISNUMBER(SEARCH("Portfolio",C79))),85,65)) | W79: =IF(C79="","",MIN(100,50+IF(S79<>"",25,0)+IF(R79<>"",15,0)+IF(P79<>"",10,0))) | X79: =IF(E79="","",IF(OR(E79="Canada",E79="CA"),100,IF(OR(E79="United States",E79="USA",E79="US"),IF(J79="Yes",45,75),65))) | Y79: =IF(C79="","",IF(OR(ISNUMBER(SEARCH("Program",C79)),ISNUMBER(SEARCH("Portfolio",C79)),ISNUMBER(SEARCH("Operations",C79)),ISNUMBER(SEARCH("Transformation",C79))),85,IF(ISNUMBER(SEARCH("Product Manager",C79)),55,70))) | Z79: =IF(C79="","",MIN(100,IF(I79<>"",60,10)+IF(AA79>0,MIN(40,AA79*20),0))) | AA79: =IF(T79="","",ROUND(T79*25%+U79*15%+V79*10%+W79*15%+X79*15%+Y79*10%+Z79*10%,0)) | AB79: =IF(AA79="","",IF(X79<50,"Selective / Barrier",IF(AA79>=80,"Tier 1 - Pursue",IF(AA79>=70,"Tier 2 - Pursue",IF(AA79>=60,"Tier 3 - Selective","Do Not Pursue"))))) | AC79: =IF(C79="","",IF(I79<>"","Named Contact",IF(AA79>0,"Outreach Logged","Cold"))) | AD79: =IF(B79="","",COUNTIF('Outreach Log'!$C:$C,B79)) | AE79: =IF(A79="","",IF(OR(K79="Rejected",K79="Closed"),IF(L79<>"",L79-A79,TODAY()-A79),TODAY()-A79)) | AF79: =IF(C79="","",IF(AND(AA79>=70,AC79="Cold"),"High-fit but cold",IF(AND(AA79<60,K79="Applied"),"Low-fit application",IF(AND(AA79>=70,OR(AC79="Named Contact",AC79="Outreach Logged")),"Targeted pursuit","Review"))))
A80: 46073 | B80: Instacart | C80: Senior Program Manager, Consumer | D80: Senior | E80: Canada | F80: Remote (ON/AB/BC/NS only) | G80: 52 | H80: Cold Portal | J80: No | K80: Rejected | M80: =IF(OR(L80="",A80=""),"",L80-A80) | P80: From Greenhouse portal: 'Applied 7 months ago'; date approximate | User confirmed rejected (Sep 20, 2026). | Actual title is Senior Program Manager, Creative Operations — oversees in-house creative agency portfolio (people/time/budget) blending portfolio management with hands-on program leadership for complex creative initiatives. 8-10 years Creative Operations/Production Management/Studio Operations specifically (not general enterprise PM). Low-moderate fit: strong portfolio management and capacity-planning overlap, but requires deep creative/agency production domain expertise — a specialized vertical outside enterprise tech/data background. Base pay CAD $143,000-$151,000. | R80: Domain mismatch (Creative Operations/agency production, not enterprise tech) | S80: 8-10 yrs Creative Ops/Production Mgmt/Studio Ops. Portfolio + program mgmt blend. Capacity planning/resource forecasting. Agency environment experience preferred. Tools: Workfront/Asana/Monday. | T80: =IF(G80="","",G80) | U80: =IF(C80="","",IF(OR(ISNUMBER(SEARCH("Director",C80)),ISNUMBER(SEARCH("Lead",C80)),ISNUMBER(SEARCH("Senior",C80)),ISNUMBER(SEARCH("Sr.",C80))),90,IF(OR(ISNUMBER(SEARCH("Manager",C80)),ISNUMBER(SEARCH("Program",C80)),ISNUMBER(SEARCH("Portfolio",C80))),80,60))) | V80: =IF(C80="","",IF(OR(ISNUMBER(SEARCH("AI",C80)),ISNUMBER(SEARCH("Data",C80)),ISNUMBER(SEARCH("Technology",C80)),ISNUMBER(SEARCH("Technical",C80)),ISNUMBER(SEARCH("Engineering",C80)),ISNUMBER(SEARCH("Platform",C80)),ISNUMBER(SEARCH("Portfolio",C80))),85,65)) | W80: =IF(C80="","",MIN(100,50+IF(S80<>"",25,0)+IF(R80<>"",15,0)+IF(P80<>"",10,0))) | X80: =IF(E80="","",IF(OR(E80="Canada",E80="CA"),100,IF(OR(E80="United States",E80="USA",E80="US"),IF(J80="Yes",45,75),65))) | Y80: =IF(C80="","",IF(OR(ISNUMBER(SEARCH("Program",C80)),ISNUMBER(SEARCH("Portfolio",C80)),ISNUMBER(SEARCH("Operations",C80)),ISNUMBER(SEARCH("Transformation",C80))),85,IF(ISNUMBER(SEARCH("Product Manager",C80)),55,70))) | Z80: =IF(C80="","",MIN(100,IF(I80<>"",60,10)+IF(AA80>0,MIN(40,AA80*20),0))) | AA80: =IF(T80="","",ROUND(T80*25%+U80*15%+V80*10%+W80*15%+X80*15%+Y80*10%+Z80*10%,0)) | AB80: =IF(AA80="","",IF(X80<50,"Selective / Barrier",IF(AA80>=80,"Tier 1 - Pursue",IF(AA80>=70,"Tier 2 - Pursue",IF(AA80>=60,"Tier 3 - Selective","Do Not Pursue"))))) | AC80: =IF(C80="","",IF(I80<>"","Named Contact",IF(AA80>0,"Outreach Logged","Cold"))) | AD80: =IF(B80="","",COUNTIF('Outreach Log'!$C:$C,B80)) | AE80: =IF(A80="","",IF(OR(K80="Rejected",K80="Closed"),IF(L80<>"",L80-A80,TODAY()-A80),TODAY()-A80)) | AF80: =IF(C80="","",IF(AND(AA80>=70,AC80="Cold"),"High-fit but cold",IF(AND(AA80<60,K80="Applied"),"Low-fit application",IF(AND(AA80>=70,OR(AC80="Named Contact",AC80="Outreach Logged")),"Targeted pursuit","Review"))))
A81: 46073 | B81: DigitalOcean | C81: Director, Startup Ecosystem | D81: Director | E81: US | F81: Remote (San Francisco listed) | G81: 40 | H81: Cold Portal | J81: Yes | K81: Rejected | M81: =IF(OR(L81="",A81=""),"",L81-A81) | P81: From Greenhouse portal: 'Applied 7 months ago'; date approximate | User confirmed rejected (Sep 20, 2026). | Leads DigitalOcean's Startups Program and venture-partner ecosystem strategy for AI startups; owns developer marketing, community engagement, venture partnerships. Requires strong developer marketing background and track record building venture partnerships specifically in AI/cloud. Low fit: this is a Marketing/Partnerships/Developer-Relations discipline role, not enterprise program/portfolio management — a different job family entirely despite senior scope and AI focus overlap. Base pay $192,800-$241,000 USD. | R81: Discipline mismatch (Developer Marketing/Venture Partnerships, not program management) | S81: Developer marketing background. Venture partnership track record (AI/cloud space). Team leadership. Startup ecosystem/community engagement. AI technology knowledge desirable. | T81: =IF(G81="","",G81) | U81: =IF(C81="","",IF(OR(ISNUMBER(SEARCH("Director",C81)),ISNUMBER(SEARCH("Lead",C81)),ISNUMBER(SEARCH("Senior",C81)),ISNUMBER(SEARCH("Sr.",C81))),90,IF(OR(ISNUMBER(SEARCH("Manager",C81)),ISNUMBER(SEARCH("Program",C81)),ISNUMBER(SEARCH("Portfolio",C81))),80,60))) | V81: =IF(C81="","",IF(OR(ISNUMBER(SEARCH("AI",C81)),ISNUMBER(SEARCH("Data",C81)),ISNUMBER(SEARCH("Technology",C81)),ISNUMBER(SEARCH("Technical",C81)),ISNUMBER(SEARCH("Engineering",C81)),ISNUMBER(SEARCH("Platform",C81)),ISNUMBER(SEARCH("Portfolio",C81))),85,65)) | W81: =IF(C81="","",MIN(100,50+IF(S81<>"",25,0)+IF(R81<>"",15,0)+IF(P81<>"",10,0))) | X81: =IF(E81="","",IF(OR(E81="Canada",E81="CA"),100,IF(OR(E81="United States",E81="USA",E81="US"),IF(J81="Yes",45,75),65))) | Y81: =IF(C81="","",IF(OR(ISNUMBER(SEARCH("Program",C81)),ISNUMBER(SEARCH("Portfolio",C81)),ISNUMBER(SEARCH("Operations",C81)),ISNUMBER(SEARCH("Transformation",C81))),85,IF(ISNUMBER(SEARCH("Product Manager",C81)),55,70))) | Z81: =IF(C81="","",MIN(100,IF(I81<>"",60,10)+IF(AA81>0,MIN(40,AA81*20),0))) | AA81: =IF(T81="","",ROUND(T81*25%+U81*15%+V81*10%+W81*15%+X81*15%+Y81*10%+Z81*10%,0)) | AB81: =IF(AA81="","",IF(X81<50,"Selective / Barrier",IF(AA81>=80,"Tier 1 - Pursue",IF(AA81>=70,"Tier 2 - Pursue",IF(AA81>=60,"Tier 3 - Selective","Do Not Pursue"))))) | AC81: =IF(C81="","",IF(I81<>"","Named Contact",IF(AA81>0,"Outreach Logged","Cold"))) | AD81: =IF(B81="","",COUNTIF('Outreach Log'!$C:$C,B81)) | AE81: =IF(A81="","",IF(OR(K81="Rejected",K81="Closed"),IF(L81<>"",L81-A81,TODAY()-A81),TODAY()-A81)) | AF81: =IF(C81="","",IF(AND(AA81>=70,AC81="Cold"),"High-fit but cold",IF(AND(AA81<60,K81="Applied"),"Low-fit application",IF(AND(AA81>=70,OR(AC81="Named Contact",AC81="Outreach Logged")),"Targeted pursuit","Review"))))
A82: 46073 | B82: BridgeBio Pharma | C82: Associate Director/Director, Strategy & Operations - AI Initiatives | D82: Associate Director/Director | E82: US | F82: Palo Alto, CA / San Francisco, CA (fully in-person) | G82: 64 | H82: Cold Portal | J82: Yes | K82: Rejected | M82: =IF(OR(L82="",A82=""),"",L82-A82) | P82: From Greenhouse portal: 'Applied 7 months ago'; title cut off; date approximate | User confirmed rejected (Sep 20, 2026). | Reports to Chief of Staff to CEO; leads AI initiative delivery (POC through scaled deployment) across R&D/G&A/Commercial at biopharma; owns RAID, vendor evaluation, executive/Board-level communications. Only 3-5+ years experience required (strategy&ops/product ops/transformation/consulting) — notably junior for the seniority framing (Director level). Biopharma industry experience helpful but not required. Moderate fit: strong AI program delivery and executive communication overlap; fully in-person (daily, no remote) requirement and lower years-experience threshold versus your background are the main frictions. | R82: Good fit — but fully in-person requirement + years-experience threshold below your level | S82: 3-5+ yrs strategy&ops/product ops/transformation/consulting. AI/ML or GenAI POC-to-scaled-adoption delivery. Executive/Board-level communication. Fully in-person daily (SF/Palo Alto). | T82: =IF(G82="","",G82) | U82: =IF(C82="","",IF(OR(ISNUMBER(SEARCH("Director",C82)),ISNUMBER(SEARCH("Lead",C82)),ISNUMBER(SEARCH("Senior",C82)),ISNUMBER(SEARCH("Sr.",C82))),90,IF(OR(ISNUMBER(SEARCH("Manager",C82)),ISNUMBER(SEARCH("Program",C82)),ISNUMBER(SEARCH("Portfolio",C82))),80,60))) | V82: =IF(C82="","",IF(OR(ISNUMBER(SEARCH("AI",C82)),ISNUMBER(SEARCH("Data",C82)),ISNUMBER(SEARCH("Technology",C82)),ISNUMBER(SEARCH("Technical",C82)),ISNUMBER(SEARCH("Engineering",C82)),ISNUMBER(SEARCH("Platform",C82)),ISNUMBER(SEARCH("Portfolio",C82))),85,65)) | W82: =IF(C82="","",MIN(100,50+IF(S82<>"",25,0)+IF(R82<>"",15,0)+IF(P82<>"",10,0))) | X82: =IF(E82="","",IF(OR(E82="Canada",E82="CA"),100,IF(OR(E82="United States",E82="USA",E82="US"),IF(J82="Yes",45,75),65))) | Y82: =IF(C82="","",IF(OR(ISNUMBER(SEARCH("Program",C82)),ISNUMBER(SEARCH("Portfolio",C82)),ISNUMBER(SEARCH("Operations",C82)),ISNUMBER(SEARCH("Transformation",C82))),85,IF(ISNUMBER(SEARCH("Product Manager",C82)),55,70))) | Z82: =IF(C82="","",MIN(100,IF(I82<>"",60,10)+IF(AA82>0,MIN(40,AA82*20),0))) | AA82: =IF(T82="","",ROUND(T82*25%+U82*15%+V82*10%+W82*15%+X82*15%+Y82*10%+Z82*10%,0)) | AB82: =IF(AA82="","",IF(X82<50,"Selective / Barrier",IF(AA82>=80,"Tier 1 - Pursue",IF(AA82>=70,"Tier 2 - Pursue",IF(AA82>=60,"Tier 3 - Selective","Do Not Pursue"))))) | AC82: =IF(C82="","",IF(I82<>"","Named Contact",IF(AA82>0,"Outreach Logged","Cold"))) | AD82: =IF(B82="","",COUNTIF('Outreach Log'!$C:$C,B82)) | AE82: =IF(A82="","",IF(OR(K82="Rejected",K82="Closed"),IF(L82<>"",L82-A82,TODAY()-A82),TODAY()-A82)) | AF82: =IF(C82="","",IF(AND(AA82>=70,AC82="Cold"),"High-fit but cold",IF(AND(AA82<60,K82="Applied"),"Low-fit application",IF(AND(AA82>=70,OR(AC82="Named Contact",AC82="Outreach Logged")),"Targeted pursuit","Review"))))
A83: 46073 | B83: Capco | C83: Program Manager (Principal Consultant) | D83: Senior/Principal | E83: Canada | F83: Toronto | G83: 79 | H83: Cold Portal | J83: No | K83: Rejected | M83: =IF(OR(L82="",A82=""),"",L82-A82) | P83: Client-facing delivery lead for complex application development / re-engineering programs; owns co-delivery plans, milestones, customer relationship management through go-live and handoff to operations. 10+ years PM/implementation experience required. Strong fit given extensive multi-client consulting delivery background (IBM) and enterprise program leadership; banking experience desirable but not required. From Greenhouse portal review; distinct from other Capco applications. Rejected. | R83: Strong fit — consulting delivery background match | S83: 10+ yrs PM/implementation. Complex app dev / re-engineering projects. Technical solutioning. Customer-facing (banking a plus). | T83: =IF(G83="","",G83) | U83: =IF(C83="","",IF(OR(ISNUMBER(SEARCH("Director",C83)),ISNUMBER(SEARCH("Lead",C83)),ISNUMBER(SEARCH("Senior",C83)),ISNUMBER(SEARCH("Sr.",C83))),90,IF(OR(ISNUMBER(SEARCH("Manager",C83)),ISNUMBER(SEARCH("Program",C83)),ISNUMBER(SEARCH("Portfolio",C83))),80,60))) | V83: =IF(C83="","",IF(OR(ISNUMBER(SEARCH("AI",C83)),ISNUMBER(SEARCH("Data",C83)),ISNUMBER(SEARCH("Technology",C83)),ISNUMBER(SEARCH("Technical",C83)),ISNUMBER(SEARCH("Engineering",C83)),ISNUMBER(SEARCH("Platform",C83)),ISNUMBER(SEARCH("Portfolio",C83))),85,65)) | W83: =IF(C83="","",MIN(100,50+IF(S83<>"",25,0)+IF(R83<>"",15,0)+IF(P83<>"",10,0))) | X83: =IF(E83="","",IF(OR(E83="Canada",E83="CA"),100,IF(OR(E83="United States",E83="USA",E83="US"),IF(J83="Yes",45,75),65))) | Y83: =IF(C83="","",IF(OR(ISNUMBER(SEARCH("Program",C83)),ISNUMBER(SEARCH("Portfolio",C83)),ISNUMBER(SEARCH("Operations",C83)),ISNUMBER(SEARCH("Transformation",C83))),85,IF(ISNUMBER(SEARCH("Product Manager",C83)),55,70))) | Z83: =IF(C83="","",MIN(100,IF(I83<>"",60,10)+IF(AA83>0,MIN(40,AA83*20),0))) | AA83: =IF(T83="","",ROUND(T83*25%+U83*15%+V83*10%+W83*15%+X83*15%+Y83*10%+Z83*10%,0)) | AB83: =IF(AA83="","",IF(X83<50,"Selective / Barrier",IF(AA83>=80,"Tier 1 - Pursue",IF(AA83>=70,"Tier 2 - Pursue",IF(AA83>=60,"Tier 3 - Selective","Do Not Pursue"))))) | AC83: =IF(C83="","",IF(I83<>"","Named Contact",IF(AA83>0,"Outreach Logged","Cold"))) | AD83: =IF(B83="","",COUNTIF('Outreach Log'!$C:$C,B83)) | AE83: =IF(A83="","",IF(OR(K83="Rejected",K83="Closed"),IF(L83<>"",L83-A83,TODAY()-A83),TODAY()-A83)) | AF83: =IF(C83="","",IF(AND(AA83>=70,AC83="Cold"),"High-fit but cold",IF(AND(AA83<60,K83="Applied"),"Low-fit application",IF(AND(AA83>=70,OR(AC83="Named Contact",AC83="Outreach Logged")),"Targeted pursuit","Review"))))
A84: 46073 | B84: Coinbase Careers Page | C84: Senior Product Manager, HR Technology | D84: Senior | E84: US | F84: Remote - USA (in-person offsites required) | G84: 60 | H84: Cold Portal | J84: Yes | K84: Rejected | M84: =IF(OR(L84="",A84=""),"",L84-A84) | P84: From Greenhouse portal: 'Applied 7 months ago'; date approximate | User confirmed rejected (Sep 20, 2026). | Leads HR Technology portfolio (internal tools, third-party solutions, AI integrations) within People Success domain, reports to Head of HR Technology. 8+ years leading cross-functional tech initiatives, buy-vs-build decisions, Agile/Jira/Confluence. Moderate fit: strong portfolio leadership, vendor management, and AI-forward initiative overlap; role is titled 'Product Manager' (a discipline distinction) though scope reads closer to technical program/portfolio management than classic product ownership. Base salary $176,035-$207,100 USD. | R84: Title/discipline ambiguity (Product Manager title, TPM-like scope) — moderate fit | S84: 8+ yrs cross-functional tech initiative leadership. Buy vs. build decisions. HR domain + Slack/Google Workspace integrations. AI-forward initiatives. Agile/Jira/Confluence. | T84: =IF(G84="","",G84) | U84: =IF(C84="","",IF(OR(ISNUMBER(SEARCH("Director",C84)),ISNUMBER(SEARCH("Lead",C84)),ISNUMBER(SEARCH("Senior",C84)),ISNUMBER(SEARCH("Sr.",C84))),90,IF(OR(ISNUMBER(SEARCH("Manager",C84)),ISNUMBER(SEARCH("Program",C84)),ISNUMBER(SEARCH("Portfolio",C84))),80,60))) | V84: =IF(C84="","",IF(OR(ISNUMBER(SEARCH("AI",C84)),ISNUMBER(SEARCH("Data",C84)),ISNUMBER(SEARCH("Technology",C84)),ISNUMBER(SEARCH("Technical",C84)),ISNUMBER(SEARCH("Engineering",C84)),ISNUMBER(SEARCH("Platform",C84)),ISNUMBER(SEARCH("Portfolio",C84))),85,65)) | W84: =IF(C84="","",MIN(100,50+IF(S84<>"",25,0)+IF(R84<>"",15,0)+IF(P84<>"",10,0))) | X84: =IF(E84="","",IF(OR(E84="Canada",E84="CA"),100,IF(OR(E84="United States",E84="USA",E84="US"),IF(J84="Yes",45,75),65))) | Y84: =IF(C84="","",IF(OR(ISNUMBER(SEARCH("Program",C84)),ISNUMBER(SEARCH("Portfolio",C84)),ISNUMBER(SEARCH("Operations",C84)),ISNUMBER(SEARCH("Transformation",C84))),85,IF(ISNUMBER(SEARCH("Product Manager",C84)),55,70))) | Z84: =IF(C84="","",MIN(100,IF(I84<>"",60,10)+IF(AA84>0,MIN(40,AA84*20),0))) | AA84: =IF(T84="","",ROUND(T84*25%+U84*15%+V84*10%+W84*15%+X84*15%+Y84*10%+Z84*10%,0)) | AB84: =IF(AA84="","",IF(X84<50,"Selective / Barrier",IF(AA84>=80,"Tier 1 - Pursue",IF(AA84>=70,"Tier 2 - Pursue",IF(AA84>=60,"Tier 3 - Selective","Do Not Pursue"))))) | AC84: =IF(C84="","",IF(I84<>"","Named Contact",IF(AA84>0,"Outreach Logged","Cold"))) | AD84: =IF(B84="","",COUNTIF('Outreach Log'!$C:$C,B84)) | AE84: =IF(A84="","",IF(OR(K84="Rejected",K84="Closed"),IF(L84<>"",L84-A84,TODAY()-A84),TODAY()-A84)) | AF84: =IF(C84="","",IF(AND(AA84>=70,AC84="Cold"),"High-fit but cold",IF(AND(AA84<60,K84="Applied"),"Low-fit application",IF(AND(AA84>=70,OR(AC84="Named Contact",AC84="Outreach Logged")),"Targeted pursuit","Review"))))
A85: 46073 | B85: Gusto, Inc. | C85: Senior Manager, Program Manager | D85: Senior Manager (people manager) | E85: US | F85: Denver, CO / NYC / SF / Seattle / LA (Hybrid 2-3 days) | G85: 77 | H85: Cold Portal | J85: Yes | K85: Rejected | M85: =IF(OR(L85="",A85=""),"",L85-A85) | P85: From Greenhouse portal: 'Applied 7 months ago'; title cut off; date approximate | User confirmed rejected (Sep 20, 2026). | PMO leadership role; leads team of 3-5 Program Managers driving cross-functional CX/Product/Eng initiatives with AI-enabled operational readiness. 8+ years program management, 4+ years leading/coaching PMs (including leading leaders). Strong fit: closely mirrors enterprise portfolio/PMO leadership, executive influence, and AI-driven program experience; people-manager scope (leading a PM team) is a good match given demonstrated leadership background. Cash comp $154,045-$223,573 depending on location. | R85: Strong fit — no clear skills gap identified | S85: 8+ yrs program mgmt/ops/PM. 4+ yrs leading/coaching PMs (leading leaders). AI-driven program experience required. Service design principles. Tools: Asana/Notion/Airtable/JIRA. | T85: =IF(G85="","",G85) | U85: =IF(C85="","",IF(OR(ISNUMBER(SEARCH("Director",C85)),ISNUMBER(SEARCH("Lead",C85)),ISNUMBER(SEARCH("Senior",C85)),ISNUMBER(SEARCH("Sr.",C85))),90,IF(OR(ISNUMBER(SEARCH("Manager",C85)),ISNUMBER(SEARCH("Program",C85)),ISNUMBER(SEARCH("Portfolio",C85))),80,60))) | V85: =IF(C85="","",IF(OR(ISNUMBER(SEARCH("AI",C85)),ISNUMBER(SEARCH("Data",C85)),ISNUMBER(SEARCH("Technology",C85)),ISNUMBER(SEARCH("Technical",C85)),ISNUMBER(SEARCH("Engineering",C85)),ISNUMBER(SEARCH("Platform",C85)),ISNUMBER(SEARCH("Portfolio",C85))),85,65)) | W85: =IF(C85="","",MIN(100,50+IF(S85<>"",25,0)+IF(R85<>"",15,0)+IF(P85<>"",10,0))) | X85: =IF(E85="","",IF(OR(E85="Canada",E85="CA"),100,IF(OR(E85="United States",E85="USA",E85="US"),IF(J85="Yes",45,75),65))) | Y85: =IF(C85="","",IF(OR(ISNUMBER(SEARCH("Program",C85)),ISNUMBER(SEARCH("Portfolio",C85)),ISNUMBER(SEARCH("Operations",C85)),ISNUMBER(SEARCH("Transformation",C85))),85,IF(ISNUMBER(SEARCH("Product Manager",C85)),55,70))) | Z85: =IF(C85="","",MIN(100,IF(I85<>"",60,10)+IF(AA85>0,MIN(40,AA85*20),0))) | AA85: =IF(T85="","",ROUND(T85*25%+U85*15%+V85*10%+W85*15%+X85*15%+Y85*10%+Z85*10%,0)) | AB85: =IF(AA85="","",IF(X85<50,"Selective / Barrier",IF(AA85>=80,"Tier 1 - Pursue",IF(AA85>=70,"Tier 2 - Pursue",IF(AA85>=60,"Tier 3 - Selective","Do Not Pursue"))))) | AC85: =IF(C85="","",IF(I85<>"","Named Contact",IF(AA85>0,"Outreach Logged","Cold"))) | AD85: =IF(B85="","",COUNTIF('Outreach Log'!$C:$C,B85)) | AE85: =IF(A85="","",IF(OR(K85="Rejected",K85="Closed"),IF(L85<>"",L85-A85,TODAY()-A85),TODAY()-A85)) | AF85: =IF(C85="","",IF(AND(AA85>=70,AC85="Cold"),"High-fit but cold",IF(AND(AA85<60,K85="Applied"),"Low-fit application",IF(AND(AA85>=70,OR(AC85="Named Contact",AC85="Outreach Logged")),"Targeted pursuit","Review"))))
